Workbook

Sheet Automotive
A1: Full Name | B1: First Name | C1: Last Name | D1: Job Title | E1: Seniority Level | F1: Seniority Rank | G1: Lead Score | H1: Opportunity Score | I1: Company Name | J1: Industry | K1: Location | L1: Company Domain | M1: LinkedIn Profile | N1: Phone | O1: Email/Gmail | P1: Follow Up 1 | Q1: Follow Up 2 | R1: Follow Up 3 | S1: Follow Up 4 | T1: Follow Up 5 | U1: Email 1 | V1: Email 2 | W1: Email 3 | X1: Email 4 | Y1: Email 5 | Z1: Cold Call 1 | AA1: Cold Call 2 | AB1: Cold Call 3 | AC1: Meeting | AD1: RFQ | AE1: Quote | AF1: Won | AG1: Lost | AH1: Outcome Status | AI1: Rejection Reason | AJ1: Interest Reason | AK1: Notes | AL1: First Contact | AM1: Last Contact | AN1: Next Follow-up | AO1: Lead Warmth Level | AP1: Priority | AQ1: Recommended Channel | AR1: Current Stage | AS1: Value Proposition | AT1: Pain Point
A2: Djordje Stevanovic | B2: Djordje | C2: Stevanovic | D2: Group Chief Procurement Officer | E2: C-Level | F2: 1 | G2: A+ | H2: 100 | I2: Coesia S.p.A. | J2: Automotive | K2: Bologna, Emilia-Romagna, Italy | L2: coesia.com | M2: https://www.linkedin.com/in/djordje-stevanovic-644b282/ | P2: Enviado | AL2: 2026-07-01 | AM2: 2026-07-01
A3: Camillo Di Giulio | B3: Camillo | C3: Di Giulio | D3: Chief Procurement Officer | E3: C-Level | F3: 1 | G3: A+ | H3: 100 | I3: Ferroli Group | J3: Automotive | K3: Bologna, Emilia-Romagna, Italy | L3: ferroli.com | M3: https://www.linkedin.com/in/camillodigiulio/ | AD3: Hecho | AH3: RFQ | AM3: 2026-07-01
A4: Shashi Gupta | B4: Shashi | C4: Gupta | D4: Chief Procurement Officer - Wiring Harness Division | E4: C-Level | F4: 1 | G4: A+ | H4: 100 | I4: Samvardhana Motherson International Ltd. | J4: Automotive | K4: Delhi, India | L4: smil.co.in | M4: https://www.linkedin.com/in/shashi-gupta-b675324/ | AH4: Won | AK4: cerrado
A5: Mostafa Badawy | B5: Mostafa | C5: Badawy | D5: Chief Software Engineer | E5: C-Level | F5: 1 | G5: B | H5: 65 | I5: Valeo | J5: Automotive | K5: الجيزة الجيزة مصر | L5: valeo.com | M5: https://www.linkedin.com/in/mostafa-badawy-b5034088/ | AO5: Caliente | AP5: Alta | AQ5: Email
A6: Pierre Baudoin | B6: Pierre | C6: Baudoin | D6: Group Purchasing Segment Director - Plastic Aspect Parts & CDA BG Plastics Commodity Manager | E6: Director | F6: 4 | G6: A+ | H6: 100 | I6: Valeo | J6: Automotive | K6: Paris, Île-de-France, France | L6: valeo.com | M6: https://www.linkedin.com/in/pierre-baudoin-93ba00107/
A7: Satish Tanwar | B7: Satish | C7: Tanwar | D7: DGM & Head - Quality Excellence, SQA, New Product Development, APQP, PFMEA and Problem Solving | E7: Head | F7: 5 | G7: B+ | H7: 76 | I7: International tractors limited | J7: Automotive | K7: Noida, Uttar Pradesh, India | L7: sonalika.com | M7: https://www.linkedin.com/in/satish-tanwar-ba1533172/
A8: Gabriel Rosko | B8: Gabriel | C8: Rosko | D8: Purchasing Commodity Manager | E8: Manager | F8: 6 | G8: A+ | H8: 94 | I8: Adient | J8: Automotive | K8: Pluak Daeng, Rayong, Thailand | L8: adient.com | M8: https://www.linkedin.com/in/gabriel-rosko-75577747/
A9: Linda Bliznáková | B9: Linda | C9: Bliznáková | D9: Global Commodity Manager Fasteners | E9: Manager | F9: 6 | G9: A+ | H9: 94 | I9: Adient | J9: Automotive | K9: Bratislava Metropolitan Area | L9: adient.com | M9: https://www.linkedin.com/in/linda-blizn%c3%a1kov%c3%a1-6317378b/
A10: Naima Boudjelida | B10: Naima | C10: Boudjelida | D10: Commodity Manager Packaging EMEA | E10: Manager | F10: 6 | G10: A+ | H10: 94 | I10: Adient | J10: Automotive | K10: Strasbourg, Grand Est, France | L10: adient.com | M10: https://www.linkedin.com/in/naima-boudjelida-4354b9163/
A11: Pavel Ružička | B11: Pavel | C11: Ružička | D11: Commodity Manager TRIM EMEA | E11: Manager | F11: 6 | G11: A+ | H11: 94 | I11: Adient | J11: Automotive | K11: Bratislava, Slovakia | L11: adient.com | M11: https://www.linkedin.com/in/ruzickapavel/
A12: Salatiel Mateus, MBA | B12: Salatiel | C12: Mateus | D12: Senior Commodity Manager - North America | E12: Manager | F12: 6 | G12: A+ | H12: 94 | I12: Adient | J12: Automotive | K12: Detroit Metropolitan Area, United States | L12: adient.com | M12: https://www.linkedin.com/in/salatiel-mateus-filho-mba/
A13: Iulian Zediu | B13: Iulian | C13: Zediu | D13: Senior Supplier Development Engineer - Local Manager | E13: Manager | F13: 6 | G13: A+ | H13: 100 | I13: Allison Off-Highway Drive & Motion Systems | J13: Automotive | K13: Reggio nell'Emilia, Emilia-Romagna, Italy | L13: allisonoffhighway.com | M13: https://www.linkedin.com/in/iulian-zediu-60abb740/
A14: Burak Macit | B14: Burak | C14: Macit | D14: Purchasing Manager Europe - Airbag | E14: Manager | F14: 6 | G14: A+ | H14: 94 | I14: Autoliv | J14: Automotive | K14: Istanbul, Turkey | L14: autoliv.com | M14: https://www.linkedin.com/in/burak-macit-94a9184a/
A15: Tim Popa | B15: Tim | C15: Popa | D15: Senior Commodity Manager - Strategic & Sourcing | E15: Manager | F15: 6 | G15: A+ | H15: 94 | I15: Autoliv | J15: Automotive | K15: Macomb, Michigan, United States | L15: autoliv.com | M15: https://www.linkedin.com/in/tim-popa-12506011/
A16: Rathesh KR | B16: Rathesh | C16: KR | D16: Global Commodity Manager | E16: Manager | F16: 6 | G16: A+ | H16: 94 | I16: Autoliv India | J16: Automotive | K16: Greater Bengaluru Area, India | L16: autoliv.com | M16: https://www.linkedin.com/in/rathesh-kr-9b74065a/
A17: Günhan Tekin | B17: Günhan | C17: Tekin | D17: Purchasing Manager | Raw Material | Tooling | Indirect Service | E17: Manager | F17: 6 | G17: A+ | H17: 100 | I17: Beyçelik Gestamp | J17: Automotive | K17: Bursa, Turkey | L17: beycelikgestamp.com.tr | M17: https://www.linkedin.com/in/günhan-tekin-03612869/
... A123: Martha Ocádiz | B123: Martha | C123: Ocádiz | D123: Global Strategic Sourcing Manager - Category Manager. Harnesses - Cables & Seats | E123: Manager | F123: 6 | G123: A+ | H123: 94 | I123: Polaris Inc. | J123: Automotive | K123: Nuevo León, Mexico | L123: polaris.com | M123: https://www.linkedin.com/in/martha-ocadiz/
A124: Bramantyo - | B124: Bramantyo | D124: Procurement Manager | E124: Manager | F124: 6 | G124: A+ | H124: 94 | I124: PT Toyota Motor Manufacturing Indonesia | J124: Automotive | K124: Indonesia | L124: toyota.co.id | M124: https://www.linkedin.com/in/bramantyo-a487a219/
A125: Hari Bala Manoj S | B125: Hari | C125: S | D125: Assistant Manager - Buyer Paints & Sealants | E125: Manager | F125: 6 | G125: A+ | H125: 94 | I125: Renault Nissan Technology & Business Centre India | J125: Automotive | K125: Tiruchirappalli, Tamil Nadu, India | L125: rntbci.in | M125: https://www.linkedin.com/in/hari-bala-manoj-s-67079623/
A126: Ravikumar Parasa | B126: Ravikumar | C126: Parasa | D126: Procurement Manager | E126: Manager | F126: 6 | G126: A+ | H126: 94 | I126: Renault Nissan Technology & Business Centre India | J126: Automotive | K126: Chennai, Tamil Nadu, India | L126: rntbci.in | M126: https://www.linkedin.com/in/pv-ravikumar04/
A127: Ercan Mutlu | B127: Ercan | C127: Mutlu | D127: Regional Supplier Purchasing Manager | E127: Manager | F127: 6 | G127: A+ | H127: 94 | I127: Renault-Nissan-Mitsubishi | J127: Automotive | K127: Turkey | L127: alliance-2022.com | M127: https://www.linkedin.com/in/ercan-mutlu-87a67966/
A128: Paola Schipitoski Rohde Buffa | B128: Paola | C128: Buffa | D128: Project Purchasing Manager | E128: Manager | F128: 6 | G128: A+ | H128: 94 | I128: Renault-Nissan-Mitsubishi | J128: Automotive | K128: São José dos Pinhais, Paraná, Brazil | L128: alliance-2022.com | M128: https://www.linkedin.com/in/paola-schipitoski-rohde-buffa-6b472826/
A129: Erica McBride-Rapp (Barbon) MS SCM, CPSM | B129: Erica | C129: CPSM | D129: Senior Purchasing Manager | E129: Manager | F129: 6 | G129: A+ | H129: 94 | I129: Rivian | J129: Automotive | K129: Philadelphia, Pennsylvania, United States | L129: rivian.com | M129: https://www.linkedin.com/in/erica-mcbride-rapp-barbon-ms-scm-cpsm-468a477b/
A130: Francisco Fernández | B130: Francisco | C130: Fernández | D130: Lead Purchasing Manager, Interiors | E130: Manager | F130: 6 | G130: A+ | H130: 94 | I130: Rivian | J130: Automotive | K130: Milpitas, California, United States | L130: rivian.com | M130: https://www.linkedin.com/in/francisco-fernández-1499b61a/
A131: Ivy Li | B131: Ivy | C131: Li | D131: Lead Purchasing Manager | E131: Manager | F131: 6 | G131: A+ | H131: 94 | I131: Rivian | J131: Automotive | K131: San Francisco Bay Area | L131: rivian.com | M131: https://www.linkedin.com/in/ivylisy/
A132: Manish Deshmukh | B132: Manish | C132: Deshmukh | D132: Lead Purchasing Manager | E132: Manager | F132: 6 | G132: A+ | H132: 94 | I132: Rivian | J132: Automotive | K132: Plymouth, Michigan, United States | L132: rivian.com | M132: https://www.linkedin.com/in/manish-deshmukh-391aab52/
A133: Panzavolta Mattia | B133: Panzavolta | C133: Mattia | D133: Purchasing Manager | E133: Manager | F133: 6 | G133: A+ | H133: 94 | I133: RONCUZZI S.R.L. | J133: Automotive | K133: Faenza, Emilia-Romagna, Italy | L133: roncuzzi.com | M133: https://www.linkedin.com/in/panzavolta-mattia-5817118b/
A134: Alessandro Del Din | B134: Alessandro | C134: Del Din | D134: Purchasing Global Commodity Manager Tires, EMEA Commodity Manager Steering | E134: Manager | F134: 6 | G134: A+ | H134: 94 | I134: Stellantis | J134: Automotive | K134: Greater Turin Metropolitan Area | L134: stellantis.com | M134: https://www.linkedin.com/in/alessandro-del-din-1a9a5863/
A135: Avinash chandrasekar | B135: Avinash | C135: chandrasekar | D135: Sourcing Manager - India & Asia Pacific | E135: Manager | F135: 6 | G135: A+ | H135: 94 | I135: Stellantis | J135: Automotive | K135: Chennai, Tamil Nadu, India | L135: stellantis.com | M135: https://www.linkedin.com/in/avinash-chandrasekar-71292323/
A136: Delphine MONTEIRO FEBVIN | B136: Delphine | C136: FEBVIN | D136: Purchasing Manager Functional Exterior Plastic Parts | E136: Manager | F136: 6 | G136: A+ | H136: 100 | I136: Stellantis | J136: Automotive | K136: Poissy, Île-de-France, France | L136: stellantis.com | M136: https://www.linkedin.com/in/delphine-monteiro-febvin-85948110/
... A170: Petre Bogdan Nicoara | B170: Petre | C170: Nicoara | D170: Serial Purchasing Manager Europe | E170: Manager | F170: 6 | G170: A+ | H170: 94 | I170: Webasto Group | J170: Automotive | K170: Arad, Romania | L170: webasto.com | M170: https://www.linkedin.com/in/bogdannicoara/
A171: Adrián García Ortiz | B171: Adrián | C171: Ortiz | D171: Commodity Manager | E171: Manager | F171: 6 | G171: A+ | H171: 94 | I171: Yanfeng | J171: Automotive | K171: Querétaro, Querétaro, Mexico | M171: https://www.linkedin.com/in/adrián-garcía-ortiz-5165412a/
A172: Anikó Richter | B172: Anikó | C172: Richter | D172: YFI Logistics Procurement Manager EMEA | E172: Manager | F172: 6 | G172: A+ | H172: 94 | I172: Yanfeng | J172: Automotive | K172: Sopron, Győr-Moson-Sopron, Hungary | M172: https://www.linkedin.com/in/anik%c3%b3-richter-37b589169/
A173: Carey Caswell | B173: Carey | C173: Caswell | D173: Senior Procurement Manager — Plastics Tooling NA/EMEA | E173: Manager | F173: 6 | G173: A+ | H173: 100 | I173: Yanfeng | J173: Automotive | K173: Holland, Michigan, United States | M173: https://www.linkedin.com/in/carey-caswell-01720113/
A174: Jose Baptista | B174: Jose | C174: Baptista | D174: Procurement Manager - IT&Telco, Packaging, Security, Scrap, Travel and Fleet - EMEA | E174: Manager | F174: 6 | G174: A+ | H174: 94 | I174: Yazaki Europe Middle East and Africa | J174: Automotive | K174: Aveiro, Aveiro, Portugal | L174: yazaki-europe.com | M174: https://www.linkedin.com/in/jose-baptista-b8555272/
A175: Marco Palmitessa | B175: Marco | C175: Palmitessa | D175: Purchasing Manager | E175: Manager | F175: 6 | G175: A+ | H175: 94 | I175: Yazaki Europe Middle East and Africa | J175: Automotive | K175: Rivoli, Piedmont, Italy | L175: yazaki-europe.com | M175: https://www.linkedin.com/in/marco-palmitessa-1439762/
A176: Achin Sharma | B176: Achin | C176: Sharma | D176: Purchasing Manager | E176: Manager | F176: 6 | G176: A+ | H176: 94 | I176: Yazaki India Private Limited | J176: Automotive | K176: Bengaluru, Karnataka, India | M176: https://www.linkedin.com/in/achin-sharma-a614a0a1/
A177: Érica Oliveira | B177: Érica | C177: Oliveira | D177: Purchasing Manager | E177: Manager | F177: 6 | G177: A+ | H177: 94 | I177: Yazaki Mercosul | J177: Automotive | K177: Tatuí, São Paulo, Brazil | L177: yazaki-group.com | M177: https://www.linkedin.com/in/érica-oliveira-godói-b1424323/
A178: Adrian Muñoz | B178: Adrian | C178: Muñoz | D178: Senior Global Commodity Manager | Stampings | Cutting & Bending Medium/Large | E178: Manager | F178: 6 | G178: A+ | H178: 94 | I178: ZF Group | J178: Automotive | K178: Madrid, Spain | L178: zf.com | M178: https://www.linkedin.com/in/adrianbouzo/
A179: Liliana Pérez y Sosa | B179: Liliana | C179: Pérez y Sosa | D179: Purchasing Manager | E179: Manager | F179: 6 | G179: A+ | H179: 94 | I179: ZF Group | J179: Automotive | K179: Toluca, México, Mexico | L179: zf.com | M179: https://www.linkedin.com/in/liliana-pérez-y-sosa-34728623/
A180: Michal Koterba | B180: Michal | C180: Koterba | D180: Global Supply Chain Manager | E180: Manager | F180: 6 | G180: A+ | H180: 94 | I180: ZF Group | J180: Automotive | K180: Bielsko-Biała Metropolitan Area, Poland | L180: zf.com | M180: https://www.linkedin.com/in/michal-koterba-34437441/
A181: Rajesh Rajan S | B181: Rajesh | C181: S | D181: Assistant Sourcing Manager | E181: Manager | F181: 6 | G181: A+ | H181: 94 | I181: ZF Group | J181: Automotive | K181: Chennai, Tamil Nadu, India | L181: zf.com | M181: https://www.linkedin.com/in/rajesh-rajan-s/
A182: Tomasz Macyk | B182: Tomasz | C182: Macyk | D182: Purchasing Commodity Manager | E182: Manager | F182: 6 | G182: A+ | H182: 94 | I182: ZF Group | J182: Automotive | K182: Poland, Poland | L182: zf.com | M182: https://www.linkedin.com/in/tomasz-macyk-21057548/
A183: William Sun | B183: William | C183: Sun | D183: Sr. Commodity Purchasing Manager - Forging Forming & Steel Components, Chassis Solution, Asia | E183: Manager | F183: 6 | G183: A+ | H183: 94 | I183: ZF Group | J183: Automotive | K183: Xuhui District, Shanghai, China | L183: zf.com | M183: https://www.linkedin.com/in/william-sun-sunyan5/
A184: Robert Nieczyporuk | B184: Robert | C184: Nieczyporuk | D184: Commodity Manager Global Fasteners & Formings | E184: Manager | F184: 6 | G184: A+ | H184: 94 | I184: ZF LIFETEC | J184: Automotive | K184: Częstochowa i okolice | L184: zf-lifetec.com | M184: https://www.linkedin.com/in/robertnieczyporuk/
A185: Dhananjay Khairnar | B185: Dhananjay | C185: Khairnar | D185: Procurement Manager | E185: Manager | F185: 6 | G185: A+ | H185: 94 | I185: Škoda Auto Volkswagen India Private Limited | J185: Automotive | K185: Pune, Maharashtra, India | L185: skoda-vw.co.in | M185: https://www.linkedin.com/in/dhananjay-khairnar-62665514b/
A186: Shane Xu | B186: Shane | C186: Xu | D186: SQE Manager | E186: Manager | F186: 6 | G186: B+ | H186: 74 | I186: Autoliv | J186: Automotive | K186: 中国 江苏省 南京市 | L186: autoliv.com | M186: https://www.linkedin.com/in/shanexu/
A187: Rishabh Saxena | B187: Rishabh | C187: Saxena | D187: Assistant Manager SQA | E187: Manager | F187: 6 | G187: B+ | H187: 74 | I187: FORVIA HELLA | J187: Automotive | K187: Gurugram, Haryana, India | L187: hella.com | M187: https://www.linkedin.com/in/rishabh-saxena-b6321b146/
A188: VINOD SURYAVANSHI | B188: Vinod | C188: Suryavanshi | D188: Assistant Manager [SQA] | E188: Manager | F188: 6 | G188: B+ | H188: 74 | I188: HD Hyundai Construction Equipment India Pvt Ltd | J188: Automotive | K188: Pune, Maharashtra, India | L188: hd-hyundaice.com | M188: https://www.linkedin.com/in/vinod-suryavanshi-923a65109/
... A191: Alexandre Hirakawa Tanaka | B191: Alexandre | C191: Tanaka | D191: Product Quality Engineer Master & MAN Quality Liasion Manager | E191: Manager | F191: 6 | G191: B+ | H191: 74 | I191: Volkswagen Caminhões e Ônibus | J191: Automotive | K191: São Paulo, São Paulo, Brazil | L191: vwco.com.br | M191: https://www.linkedin.com/in/alexandre-hirakawa-tanaka/
A192: ajay jadhav | B192: Ajay | C192: Jadhav | D192: Deputy Manager SQA | E192: Manager | F192: 6 | G192: B+ | H192: 74 | I192: Yazaki India Private Limited | J192: Automotive | K192: Pune, Maharashtra, India | M192: https://www.linkedin.com/in/ajay-jadhav-44b0a12a/
A193: SENTHIL NATHAN | B193: Senthil | C193: Nathan | D193: Assistant Manager NPD & SQA | E193: Manager | F193: 6 | G193: B+ | H193: 74 | I193: ZF Rane Automotive India Private Limited | J193: Automotive | K193: Chennai, Tamil Nadu, India | L193: ranegroup.com | M193: https://www.linkedin.com/in/senthil-nathan-19554227/
A194: Ömercan Gültiken | B194: Ömercan | C194: Gültiken | D194: Senior Buyer - Commodity Team Leader | E194: Lead | F194: 7 | G194: A+ | H194: 90 | I194: AISIN Europe | J194: Automotive | K194: Leuven, Flemish Region, Belgium | L194: aisin-europe.com | M194: https://www.linkedin.com/in/%c3%b6mercan-g%c3%bcltiken-616aaa61/
A195: Janis Walker | B195: Janis | C195: Walker | D195: Lead Buyer Cluster Packaging | E195: Lead | F195: 7 | G195: A+ | H195: 90 | I195: Alfred Kärcher GmbH & Co. KG | J195: Automotive | K195: Winnenden, Baden-Württemberg, Germany | L195: karcher.com | M195: https://www.linkedin.com/in/janis-walker-15a993210/
A196: Julian Thun | B196: Julian | C196: Thun | D196: Global Lead Buyer - Plastic Assemblies | E196: Lead | F196: 7 | G196: A+ | H196: 100 | I196: Brose Group | J196: Automotive | K196: Bamberg, Bavaria, Germany | L196: brose.com | M196: https://www.linkedin.com/in/julian-thun-350990a8/
A197: Jacek Połącarz | B197: Jacek | C197: Połącarz | D197: Lead Buyer - Global Commodity Buyer Capex/Tooling (Koordynator ds. Zakupów) | E197: Lead | F197: 7 | G197: A+ | H197: 100 | I197: Cooper Standard | J197: Automotive | K197: Bielsko-Biała Metropolitan Area | L197: cooperstandard.com | M197: https://www.linkedin.com/in/jacek-polacarz/
A198: Leïla Mebrak | B198: Leïla | C198: Mebrak | D198: Lead & Commodity Buyer - Chrome, Mechatronic & Metals | E198: Lead | F198: 7 | G198: A+ | H198: 90 | I198: Flex-N-Gate Europe | J198: Automotive | K198: Belfort, Bourgogne-Franche-Comté, France | L198: flex-n-gate.com | M198: https://www.linkedin.com/in/leïla-mebrak-b7591a43/
A199: Axel Dolderer | B199: Axel | C199: Dolderer | D199: Global Lead Buyer Stamping & Bent Parts | E199: Lead | F199: 7 | G199: A+ | H199: 90 | I199: MAHLE | J199: Automotive | K199: Stuttgart Region | L199: mahle.com | M199: https://www.linkedin.com/in/axel-dolderer-21a2b167/
A200: Juliana Salomão Oliveira | B200: Juliana | C200: Oliveira | D200: Global Lead Buyer - Semiconductor | E200: Lead | F200: 7 | G200: A+ | H200: 90 | I200: MAHLE | J200: Automotive | K200: Valencia, Valencian Community, Spain | L200: mahle.com | M200: https://www.linkedin.com/in/juliana-salom%c3%a3o-oliveira-16040815/
A201: Antonio Amaro Avila | B201: Antonio | C201: Avila | D201: Lead Supplier Quality Engineer, Operations & Manufacturing | E201: Lead | F201: 7 | G201: A+ | H201: 100 | I201: Rivian | J201: Automotive | K201: Saltillo, Coahuila, Mexico | L201: rivian.com | M201: https://www.linkedin.com/in/antonio-amaro-avila-496a0218/
A202: Gregory Turner | B202: Gregory | C202: Turner | D202: Lead Supplier Development Engineer - Propulsion & EPC | E202: Lead | F202: 7 | G202: A+ | H202: 100 | I202: Rivian | J202: Automotive | K202: Irvine, California, United States | L202: rivian.com | M202: https://www.linkedin.com/in/gregory-turner-7a02318/
A203: Ricardo Velasquez | B203: Ricardo | C203: Velasquez | D203: Lead Supplier Development Engineer - Interior Cockpit | E203: Lead | F203: 7 | G203: A+ | H203: 100 | I203: Rivian | J203: Automotive | K203: Bloomington, Illinois, United States | L203: rivian.com | M203: https://www.linkedin.com/in/ricardo-velasquez-788710113/
A204: Srikanth Badrinarayanan | B204: Srikanth | C204: Badrinarayanan | D204: Lead Supplier Development Engineer - Stamping | E204: Lead | F204: 7 | G204: A+ | H204: 100 | I204: Rivian | J204: Automotive | K204: Rochester, Michigan, United States | L204: rivian.com | M204: https://www.linkedin.com/in/srikanth-badrinarayanan-b828139/
... A235: Barış Kılıç | B235: Barış | C235: Kılıç | D235: Senior Buyer, Parts & Components Purchasing/PLASTICS Section | E235: Senior | F235: 8 | G235: A+ | H235: 100 | I235: Toyota Motor Europe | J235: Automotive | K235: Turkey | L235: toyota-europe.com | M235: https://www.linkedin.com/in/bariskiliic/
A236: Nikola Stamenkovic | B236: Nikola | C236: Stamenkovic | D236: Senior Supplier Quality Engineer | E236: Senior | F236: 8 | G236: A+ | H236: 100 | I236: Yanfeng | J236: Automotive | K236: Kragujevac, Centralna Srbija, Serbia | M236: https://www.linkedin.com/in/nikola-stamenkovic-44854614b/
A237: Abdelrhman Shawky | B237: Abdelrhman | C237: Shawky | D237: Senior Supplier Quality Assurance Engineer | E237: Senior | F237: 8 | G237: A+ | H237: 100 | I237: Yazaki Egypt | J237: Automotive | K237: الجيزة الجيزة مصر | L237: yazaki-europe.com | M237: https://www.linkedin.com/in/abdelrhman-shawky-296018104/
A238: Andrew Tong | B238: Andrew | C238: Tong | D238: Senior Supplier Development Engineer | E238: Senior | F238: 8 | G238: A+ | H238: 100 | I238: ZF Group | J238: Automotive | K238: WP. Kuala Lumpur, Federal Territory of Kuala Lumpur, Malaysia | L238: zf.com | M238: https://www.linkedin.com/in/andrewtong19/
A239: Arturo Barcenas Cabrera | B239: Arturo | C239: Cabrera | D239: Sr. Supplier Development Engineer | E239: Senior | F239: 8 | G239: A+ | H239: 100 | I239: ZF Group | J239: Automotive | K239: Auburn Hills, Michigan, United States | L239: zf.com | M239: https://www.linkedin.com/in/arturo-barcenas-cabrera-90a4b334/
A240: Diego Fernández Rivera | B240: Diego | C240: Rivera | D240: Senior Commodity Buyer, Tooling - Gages, measuring machines / Cutting tools | E240: Senior | F240: 8 | G240: A+ | H240: 100 | I240: ZF Group | J240: Automotive | K240: Querétaro, Mexico | L240: zf.com | M240: https://www.linkedin.com/in/diego-fernández-rivera-a4373768/
A241: Edrei Casteli | B241: Edrei | C241: Casteli | D241: Senior Supplier Development Engineer | E241: Senior | F241: 8 | G241: A+ | H241: 100 | I241: ZF Group | J241: Automotive | K241: Simpsonville, South Carolina, United States | L241: zf.com | M241: https://www.linkedin.com/in/edrei-casteli-1611b9232/
A242: Luis Maria Del Rio | B242: Luis | C242: Del Rio | D242: Senior Sourcing Buyer Metal Stampings | E242: Senior | F242: 8 | G242: A | H242: 88 | I242: Adient | J242: Automotive | K242: Detroit Metropolitan Area | L242: adient.com | M242: https://www.linkedin.com/in/luis-maria-del-rio-221a9a26/
A243: Jose Roberto Espinosa Mendez | B243: Jose | C243: Mendez | D243: Senior Project Buyer | E243: Senior | F243: 8 | G243: A | H243: 88 | I243: Audi México | J243: Automotive | K243: Mexico | L243: audi.com.mx | M243: https://www.linkedin.com/in/ingespinosa/
A244: Víctor César Gutiérrez | B244: Víctor | C244: Gutiérrez | D244: Senior Commodity Buyer | E244: Senior | F244: 8 | G244: A | H244: 88 | I244: Autoliv | J244: Automotive | K244: Querétaro, Mexico | L244: autoliv.com | M244: https://www.linkedin.com/in/vã­ctor-cã©sar-gutiã©rrez-940138143/
A245: Lelia Ligorio | B245: Lelia | C245: Ligorio | D245: Senior Buyer | E245: Senior | F245: 8 | G245: A | H245: 88 | I245: Automobili Lamborghini S.p.A. | J245: Automotive | K245: Bologna, Emilia-Romagna, Italy | L245: lamborghini.com | M245: https://www.linkedin.com/in/lelia-ligorio-a2bab861/
A246: Chris Harmon | B246: Chris | C246: Harmon | D246: Senior Commodity Buyer | E246: Senior | F246: 8 | G246: A | H246: 88 | I246: BorgWarner | J246: Automotive | K246: Greenville-Spartanburg-Anderson, South Carolina Area | L246: borgwarner.com | M246: https://www.linkedin.com/in/christopherlharmon/
A247: Fausto D. Gamboa | B247: Fausto | C247: Gamboa | D247: Sr Buyer | E247: Senior | F247: 8 | G247: A | H247: 88 | I247: BorgWarner | J247: Automotive | K247: Reynosa, Tamaulipas, Mexico | L247: borgwarner.com | M247: https://www.linkedin.com/in/faustodgamboav/
A248: Felipe Zapata | B248: Felipe | C248: Zapata | D248: Senior Buyer | E248: Senior | F248: 8 | G248: A | H248: 88 | I248: BorgWarner | J248: Automotive | K248: Mexico, Mexico | L248: borgwarner.com | M248: https://www.linkedin.com/in/felipe-zapata-516540b4/
... A259: Ranjeet Singh | B259: Ranjeet | C259: Singh | D259: Senior Buyer - Global Procurement | E259: Senior | F259: 8 | G259: A | H259: 88 | I259: Flex-N-Gate | J259: Automotive | K259: Bradford County, Pennsylvania, United States | L259: flex-n-gate.com | M259: https://www.linkedin.com/in/ranjeet-singh-10411517b/
A260: Baratharun . | B260: Baratharun | D260: Senior Buyer | E260: Senior | F260: 8 | G260: A | H260: 88 | I260: Ford Motor Company | J260: Automotive | K260: Chennai, Tamil Nadu, India | L260: ford.com | M260: https://www.linkedin.com/in/baratharun/
A261: Mert Kastan | B261: Mert | C261: Kastan | D261: Senior Commodity Buyer | E261: Senior | F261: 8 | G261: A | H261: 88 | I261: Ford Motor Company | J261: Automotive | K261: Istanbul, Türkiye | L261: ford.com | M261: https://www.linkedin.com/in/mert-kastan-42b177134/
A262: Marvin Modjadji | B262: Marvin | C262: Modjadji | D262: IMG FCSD Regional Senior Buyer- Body Exterior | E262: Senior | F262: 8 | G262: A | H262: 88 | I262: Ford Motor Company of Southern Africa | J262: Automotive | K262: City of Tshwane, Gauteng, South Africa | L262: ford.co.za | M262: https://www.linkedin.com/in/marvin-modjadji-91010332/
A263: Richard Dukhanti | B263: Richard | C263: Dukhanti | D263: Senior Buyer | E263: Senior | F263: 8 | G263: A | H263: 88 | I263: Ford Motor Company of Southern Africa | J263: Automotive | K263: City of Johannesburg, Gauteng, South Africa | L263: ford.co.za | M263: https://www.linkedin.com/in/richard-dukhanti-34668154/
A264: Burcu Çelepöven | B264: Burcu | C264: Çelepöven | D264: Senior Puchasing Commodity Buyer(chassis and trim parts) | E264: Senior | F264: 8 | G264: A | H264: 88 | I264: Ford Otosan | J264: Automotive | K264: Kocaeli, Turkey | L264: fordotosan.com.tr | M264: https://www.linkedin.com/in/burcu-çelepöven-006b7a63/
A265: Marina Bostelmann | B265: Marina | C265: Bostelmann | D265: Senior Serial Life and Productivity Buyer | E265: Senior | F265: 8 | G265: A | H265: 88 | I265: FORVIA | J265: Automotive | K265: Curitiba, Paraná, Brazil | L265: forvia.com | M265: https://www.linkedin.com/in/marina-bostelmann-4510a7b6/
A266: Cindy Terry | B266: Cindy | C266: Terry | D266: Senior Supply Chain Planner/Buyer | E266: Senior | F266: 8 | G266: A | H266: 88 | I266: FORVIA HELLA | J266: Automotive | K266: Peachtree City, Georgia, United States | L266: hella.com | M266: https://www.linkedin.com/in/cindy-terry-b0b7a191/
A267: Paul Stef | B267: Paul | C267: Stef | D267: Senior Buyer Construction Operational Materials and Supplier&IT Hardware & Facility Management | E267: Senior | F267: 8 | G267: A | H267: 88 | I267: FORVIA HELLA | J267: Automotive | K267: Timişoara, Timiş, Romania | L267: hella.com | M267: https://www.linkedin.com/in/paul-stef-50114479/
A268: Brian M. | B268: Brian | C268: M. | D268: Senior Buyer | E268: Senior | F268: 8 | G268: A | H268: 88 | I268: General Motors | J268: Automotive | K268: Detroit Metropolitan Area, United States | L268: gm.com | M268: https://www.linkedin.com/in/brian-m-7b44ab55/
A269: Chrissy Sneden | B269: Chrissy | C269: Sneden | D269: Senior Buyer, Deco Trim | E269: Senior | F269: 8 | G269: A | H269: 88 | I269: General Motors | J269: Automotive | K269: Rochester, Michigan, United States | L269: gm.com | M269: https://www.linkedin.com/in/christine-sneden-1526521b/
A270: Flor de Maria Karpinski | B270: Flor | C270: de Maria Karpinski | D270: Senior Commodity Buyer | E270: Senior | F270: 8 | G270: A | H270: 88 | I270: General Motors | J270: Automotive | K270: Fuquay-Varina, North Carolina, United States | L270: gm.com | M270: https://www.linkedin.com/in/flor-de-maria-karpinski-25778846/
A271: Menali Bandkau | B271: Menali | C271: Bandkau | D271: Senior Buyer- Structures | E271: Senior | F271: 8 | G271: A | H271: 88 | I271: General Motors | J271: Automotive | K271: Detroit Metropolitan Area | L271: gm.com | M271: https://www.linkedin.com/in/menali-dalian-37527074/
A272: Carlos Golbi | B272: Carlos | C272: Golbi | D272: Senior Buyer | E272: Senior | F272: 8 | G272: A | H272: 88 | I272: General Motors South America | J272: Automotive | K272: Greater São Paulo Area | L272: gm.com.br | M272: https://www.linkedin.com/in/carlos-golbi-6714a692/
... A327: Alexander D. Doman, MBA | B327: Alexander | C327: Doman | D327: Senior Commodity Buyer (Textile Fabrics & Chemicals for USA & MX) | E327: Senior | F327: 8 | G327: A | H327: 88 | I327: Webasto Americas | J327: Automotive | K327: Detroit Metropolitan Area | L327: webasto.com | M327: https://www.linkedin.com/in/alexander-d-doman-mba-77545918/
A328: Jay Gohil | B328: Jay | C328: Gohil | D328: Senior Strategic Buyer | E328: Senior | F328: 8 | G328: A | H328: 88 | I328: Yanfeng | J328: Automotive | K328: Vadodara, Gujarat, India | M328: https://www.linkedin.com/in/jay-gohil-613364b6/
A329: Jorge Valdes | B329: Jorge | C329: Valdes | D329: Regional Senior Commodity Buyer | E329: Senior | F329: 8 | G329: A | H329: 88 | I329: Yanfeng | J329: Automotive | K329: United States | M329: https://www.linkedin.com/in/jorge-valdes-b3643b229/
A330: Murwan Kadry | B330: Murwan | C330: Kadry | D330: Senior Buyer | E330: Senior | F330: 8 | G330: A | H330: 88 | I330: Yazaki North America | J330: Automotive | K330: Detroit Metropolitan Area | L330: yazaki-na.com | M330: https://www.linkedin.com/in/murwan-kadry-126b0010/
A331: Carmen de Arriba De la Fuente | B331: Carmen | C331: De la Fuente | D331: Senior Commodity Buyer | E331: Senior | F331: 8 | G331: A | H331: 88 | I331: ZF Group | J331: Automotive | K331: Greater Vigo Metropolitan Area | L331: zf.com | M331: https://www.linkedin.com/in/carmen-de-arriba-de-la-fuente-978a4986/
A332: Diego Eburneo | B332: Diego | C332: Eburneo | D332: Sr Project Buyer | E332: Senior | F332: 8 | G332: A | H332: 88 | I332: ZF Group | J332: Automotive | K332: São Paulo, Brazil | L332: zf.com | M332: https://www.linkedin.com/in/diego-eburneo/
A333: Guilherme Mosna | B333: Guilherme | C333: Mosna | D333: Sr. Global Commodity Buyer | E333: Senior | F333: 8 | G333: A | H333: 88 | I333: ZF Group | J333: Automotive | K333: Brasil | L333: zf.com | M333: https://www.linkedin.com/in/guilherme-mosna-922626258/
A334: Marcel Dachniewski | B334: Marcel | C334: Dachniewski | D334: Senior Commodity Buyer | E334: Senior | F334: 8 | G334: A | H334: 88 | I334: ZF Group | J334: Automotive | K334: Lodz Metropolitan Area, Poland | L334: zf.com | M334: https://www.linkedin.com/in/dachniewski/
...

Sheet Pharmaceutical
A1: Full Name | B1: First Name | C1: Last Name | D1: Job Title | E1: Seniority Level | F1: Seniority Rank | G1: Lead Score | H1: Opportunity Score | I1: Company Name | J1: Industry | K1: Location | L1: Company Domain | M1: LinkedIn Profile | N1: Phone | O1: Email/Gmail | P1: Follow Up 1 | Q1: Follow Up 2 | R1: Follow Up 3 | S1: Follow Up 4 | T1: Follow Up 5 | U1: Email 1 | V1: Email 2 | W1: Email 3 | X1: Email 4 | Y1: Email 5 | Z1: Cold Call 1 | AA1: Cold Call 2 | AB1: Cold Call 3 | AC1: Meeting | AD1: RFQ | AE1: Quote | AF1: Won | AG1: Lost | AH1: Outcome Status | AI1: Rejection Reason | AJ1: Interest Reason | AK1: Notes | AL1: First Contact | AM1: Last Contact | AN1: Next Follow-up
A2: Richard Jones | B2: Richard | C2: Jones | D2: Senior Director, Forward Deployed Principal Software Engineer | E2: Director | F2: 4 | G2: C+ | H2: 56 | I2: Pfizer | J2: Pharmaceutical | K2: Greater Brighton and Hove Area | L2: pfizer.com | M2: https://www.linkedin.com/in/richard-jones-8b7aa53/
A3: Burak Aydınalp | B3: Burak | C3: Aydınalp | D3: Direct Materials Procurement Manager | E3: Manager | F3: 6 | G3: A | H3: 87 | I3: Abdi Ibrahim Pharmaceuticals | J3: Pharmaceutical | K3: Istanbul, Istanbul, Türkiye | L3: abdiibrahim.com.tr | M3: https://www.linkedin.com/in/burak-ayd%c4%b1nalp-732a3354/
A4: Hazal Pala Özdemir | B4: Hazal | C4: Özdemir | D4: Direct Materials Procurement Manager | E4: Manager | F4: 6 | G4: A | H4: 87 | I4: Abdi Ibrahim Pharmaceuticals | J4: Pharmaceutical | K4: Istanbul, Turkey | L4: abdiibrahim.com.tr | M4: https://www.linkedin.com/in/hazal-pala-%c3%b6zdemir-31979586/
A5: Uğur Ahmet Eder | B5: Uğur | C5: Eder | D5: Purchasing Manager - International Markets and Services Purchasing Manager Algeria & Kazakhstan | E5: Manager | F5: 6 | G5: A | H5: 87 | I5: Abdi Ibrahim Pharmaceuticals | J5: Pharmaceutical | K5: Istanbul, Turkey | L5: abdiibrahim.com.tr | M5: https://www.linkedin.com/in/u%c4%9fur-ahmet-eder-94193284/
A6: Krunal Joshi | B6: Krunal | C6: Joshi | D6: Purchasing Manager | E6: Manager | F6: 6 | G6: A | H6: 87 | I6: Alembic Pharmaceuticals Limited | J6: Pharmaceutical | K6: Vadodara, Gujarat, India | L6: alembic-india.com | M6: https://www.linkedin.com/in/krunal-joshi-941a4528/
A7: Sharon DeFeo | B7: Sharon | C7: DeFeo | D7: Global Procurement Manager | E7: Manager | F7: 6 | G7: A | H7: 87 | I7: Allergan | J7: Pharmaceutical | K7: New York City Metropolitan Area | L7: abbvie.com | M7: https://www.linkedin.com/in/sharondefeo/
A8: KIRANKUMAR NAYEE | B8: Kirankumar | C8: Nayee | D8: Procurement Manager | E8: Manager | F8: 6 | G8: A | H8: 87 | I8: Amneal Pharmaceuticals | J8: Pharmaceutical | K8: Ahmedabad, Gujarat, India | L8: amneal.com | M8: https://www.linkedin.com/in/kirankumar-nayee-1607b453/
A9: Claire Campenon | B9: Claire | C9: Campenon | D9: Packaging Purchasing Manager | E9: Manager | F9: 6 | G9: A | H9: 87 | I9: Arkopharma | J9: Pharmaceutical | K9: Nice, Provence-Alpes-Côte d'Azur, France | L9: arkopharma.com | M9: https://www.linkedin.com/in/claire-campenon-1919423a/
A10: Carolina P. | B10: Carolina | C10: P. | D10: Purchasing Manager | E10: Manager | F10: 6 | G10: A | H10: 87 | I10: Arnet Pharmaceutical Corp | J10: Pharmaceutical | K10: Fort Lauderdale, Florida, United States | L10: arnetusa.com | M10: https://www.linkedin.com/in/carolina-p-30428417/
A11: Simon Marshall, FCIPS | B11: Simon | C11: FCIPS | D11: Global Procurement Manager | E11: Manager | F11: 6 | G11: A | H11: 87 | I11: AstraZeneca | J11: Pharmaceutical | K11: Derbyshire, England, United Kingdom | L11: astrazeneca.com | M11: https://www.linkedin.com/in/simon-marshall-fcips-2a18a422/
A12: Steve Madeley | B12: Steve | C12: Madeley | D12: Sourcing manager | E12: Manager | F12: 6 | G12: A | H12: 87 | I12: AstraZeneca | J12: Pharmaceutical | K12: Greater Manchester, England, United Kingdom | L12: astrazeneca.com | M12: https://www.linkedin.com/in/steve-madeley-b55a3926/
A13: Cesare Zinanni | B13: Cesare | C13: Zinanni | D13: Purchasing Manager | E13: Manager | F13: 6 | G13: A | H13: 87 | I13: Boehringer Ingelheim | J13: Pharmaceutical | K13: Montevarchi, Toscana, Italia | L13: boehringer-ingelheim.com | M13: https://www.linkedin.com/in/cesare-zinanni-02bb80/
... A61: Jay Prakash | B61: Jay | C61: Prakash | D61: Global Strategic Sourcing Manager Packaging Materials | E61: Manager | F61: 6 | G61: A | H61: 87 | I61: SUN PHARMA | J61: Pharmaceutical | K61: Mumbai, Maharashtra, India | L61: sunpharma.com | M61: https://www.linkedin.com/in/jay-prakash-1327b37b/
A62: Mohamed Samir Shokry Ali | B62: Mohamed | C62: Ali | D62: Procurement Manager (Supply Chain) | E62: Manager | F62: 6 | G62: A | H62: 87 | I62: Sunny Pharmaceutical | J62: Pharmaceutical | K62: Egypt, Egypt | M62: https://www.linkedin.com/in/mohamed-samir-shokry-ali-7ab907bb/
A63: Diana Alpuche | B63: Diana | C63: Alpuche | D63: Strategic Procurement Manager - Category Leader | E63: Manager | F63: 6 | G63: A | H63: 87 | I63: Takeda | J63: Pharmaceutical | K63: Mexico City, Ciudad de México, Mexico | L63: takeda.com | M63: https://www.linkedin.com/in/diana-alpuche-3a0b581b/
A64: Gustavo Oliveira | B64: Gustavo | C64: Oliveira | D64: Senior Strategic Procurement Manager - LATAM | E64: Manager | F64: 6 | G64: A | H64: 87 | I64: Takeda | J64: Pharmaceutical | K64: São Paulo, São Paulo, Brazil | L64: takeda.com | M64: https://www.linkedin.com/in/gustavo-oliveira-22a2072b/
A65: David Loudner | B65: David | C65: Loudner | D65: Global Strategic Sourcing Manager | E65: Manager | F65: 6 | G65: A | H65: 87 | I65: West Pharmaceutical Services | J65: Pharmaceutical | K65: Greater Tampa Bay Area, United States | L65: westpharma.com | M65: https://www.linkedin.com/in/david-loudner-1057641b/
A66: Orla King | B66: Orla | C66: King | D66: Site Procurement Manager | E66: Manager | F66: 6 | G66: A | H66: 87 | I66: West Pharmaceutical Services | J66: Pharmaceutical | K66: Dublin, County Dublin, Ireland | L66: westpharma.com | M66: https://www.linkedin.com/in/orla-king-01759322/
A67: Lucas Lalouani | B67: Lucas | C67: Lalouani | D67: Packaging Group Lead Buyer Pharma / Cosmetics | E67: Lead | F67: 7 | G67: A | H67: 83 | I67: FAREVA | J67: Pharmaceutical | K67: France | L67: fareva.com | M67: https://www.linkedin.com/in/lucas-lalouani-59b5a1123/
A68: Mihaela Vučić | B68: Mihaela | C68: Vučić | D68: Lead Sourcing Specialist | E68: Lead | F68: 7 | G68: A | H68: 83 | I68: Novo Nordisk | J68: Pharmaceutical | K68: Zagreb, Zagreb, Croatia | L68: novonordisk.com | M68: https://www.linkedin.com/in/vucicmihaela168/
A69: Alexiane Tissot | B69: Alexiane | C69: Tissot | D69: Global Category Lead Buyer - Packaging, Global Procurement | E69: Lead | F69: 7 | G69: A | H69: 83 | I69: Sanofi | J69: Pharmaceutical | K69: Greater Lyon Area, France | L69: sanofi.com | M69: https://www.linkedin.com/in/alexiane-tissot-46b4729a/
A70: Ana Daniela Fernandes Guandalini | B70: Ana | C70: Guandalini | D70: Primary Packaging Global Lead Buyer CHC | E70: Lead | F70: 7 | G70: A | H70: 83 | I70: Sanofi | J70: Pharmaceutical | K70: Chattanooga, Tennessee, United States | L70: sanofi.com | M70: https://www.linkedin.com/in/ana-daniela-fernandes-guandalini-b6469b13/
A71: Laurence PLANTEROSE | B71: Laurence | C71: PLANTEROSE | D71: Global Lead Buyer Clinical Supplies - Worlwide | E71: Lead | F71: 7 | G71: A | H71: 83 | I71: Sanofi | J71: Pharmaceutical | K71: Greater Lyon Area | L71: sanofi.com | M71: https://www.linkedin.com/in/laurence-planterose-8b597311/
A72: Noha Mayhoub | B72: Noha | C72: Mayhoub | D72: Global Lead Buyer, ATME | E72: Lead | F72: 7 | G72: A | H72: 83 | I72: Sanofi | J72: Pharmaceutical | K72: Egypt | L72: sanofi.com | M72: https://www.linkedin.com/in/noha-mayhoub-593a6b53/
A73: Adrien Donati | B73: Adrien | C73: Donati | D73: Lead Buyer - Glass Raw Materials, Packaging & Special projects | E73: Lead | F73: 7 | G73: A | H73: 83 | I73: SGD Pharma | J73: Pharmaceutical | K73: France | L73: sgd-pharma.com | M73: https://www.linkedin.com/in/adrien-donati-7999a9108/
A74: Marcin Hanusewicz | B74: Marcin | C74: Hanusewicz | D74: Senior Procurement Specialist | E74: Senior | F74: 8 | G74: A | H74: 81 | I74: Adamed Pharma | J74: Pharmaceutical | K74: Warsaw Metropolitan Area | L74: adamed.com | M74: https://www.linkedin.com/in/marcin-hanusewicz-7066a82b/
... A79: Rony Varghese | B79: Rony | C79: Varghese | D79: Senior Buyer - NPI & Strategic Projects | E79: Senior | F79: 8 | G79: A | H79: 81 | I79: PCI Pharma Services | J79: Pharmaceutical | K79: Dublin, County Dublin, Ireland | L79: pci.com | M79: https://www.linkedin.com/in/rony-varghese-82402167/
A80: Marco Balacco | B80: Marco | C80: Balacco | D80: Senior Buyer and Warehouse | E80: Senior | F80: 8 | G80: A | H80: 81 | I80: Pharmaceutical Company | J80: Pharmaceutical | K80: Milan, Lombardy, Italy | M80: https://www.linkedin.com/in/marco-balacco-2511a111/
A81: Andrea Cowell | B81: Andrea | C81: Cowell | D81: Senior Procurement Specialist | E81: Senior | F81: 8 | G81: A | H81: 81 | I81: Piramal Pharma Ltd | J81: Pharmaceutical | K81: Ashington, England, United Kingdom | L81: piramalpharma.com | M81: https://www.linkedin.com/in/andrea-cowell-a33b0a29/
A82: Tunde Ogunlana (MBA, CITLS, MMIPM, CPP- ACSC, ENG) | B82: Tunde | C82: Ogunlana | D82: Senior Procurement Officer | E82: Senior | F82: 8 | G82: A | H82: 81 | I82: Swiss Pharma Limited | J82: Pharmaceutical | K82: Lagos State, Nigeria | L82: swiphanigeria.com | M82: https://www.linkedin.com/in/tunde-ogunlana-mba-citls-mmipm-cpp-acsc-eng-73b39285/
A83: Mike Lanzone | B83: Mike | C83: Lanzone | D83: Senior Buyer | E83: Senior | F83: 8 | G83: A | H83: 81 | I83: Unither Pharmaceuticals | J83: Pharmaceutical | K83: Fairport, New York, United States | L83: unither-pharma.com | M83: https://www.linkedin.com/in/mlanzone/
A84: Shawna Spahn | B84: Shawna | C84: Spahn | D84: Senior Quality Engineer | E84: Senior | F84: 8 | G84: B | H84: 61 | I84: AbbVie | J84: Pharmaceutical | K84: Cincinnati Metropolitan Area | L84: abbvie.com | M84: https://www.linkedin.com/in/shawna-spahn-6b34901a/
A85: Tracy M. Gray Fields | B85: Tracy | C85: Fields | D85: Senior Quality Engineer | E85: Senior | F85: 8 | G85: B | H85: 61 | I85: AbbVie | J85: Pharmaceutical | K85: Greater Chicago Area | L85: abbvie.com | M85: https://www.linkedin.com/in/tracy-m-gray-fields-b113338/
A86: Carlisse Abreu | B86: Carlisse | C86: Abreu | D86: Sr Principal Quality Assurance Engineer - IDAP Dry | E86: Senior | F86: 8 | G86: B | H86: 61 | I86: Eli Lilly and Company | J86: Pharmaceutical | K86: Indianapolis, Indiana, United States | L86: lilly.com | M86: https://www.linkedin.com/in/carlisse-abreu-86678625/
A87: Ilias Foufopoulos | B87: Ilias | C87: Foufopoulos | D87: Senior Quality Assurance Engineer | E87: Senior | F87: 8 | G87: B | H87: 61 | I87: Pharmathen | J87: Pharmaceutical | K87: Pallíni, Attiki, Greece | L87: pharmathen.com | M87: https://www.linkedin.com/in/ilias-foufopoulos/
A88: Mayank Kumar | B88: Mayank | C88: Kumar | D88: Senior Quality Assurance Engineer | E88: Senior | F88: 8 | G88: B | H88: 61 | I88: Translumina Therapeutics | J88: Pharmaceutical | K88: Faridabad, Haryana, India | L88: translumina.com | M88: https://www.linkedin.com/in/mayank-kumar-533609181/
A89: Ashley G. | B89: Ashley | C89: G. | D89: Senior Quality Engineer | E89: Senior | F89: 8 | G89: B | H89: 61 | I89: West Pharmaceutical Services | J89: Pharmaceutical | K89: Mesa, Arizona, United States | L89: westpharma.com | M89: https://www.linkedin.com/in/ashley-g-634a0258/
A90: Austin Nguyenphu | B90: Austin | C90: Nguyenphu | D90: Senior Quality Engineer | E90: Senior | F90: 8 | G90: B | H90: 61 | I90: West Pharmaceutical Services | J90: Pharmaceutical | K90: Phoenix, Arizona, United States | L90: westpharma.com | M90: https://www.linkedin.com/in/austin-nguyenphu-b33010112/
A91: Adam Barnhard | B91: Adam | C91: Barnhard | D91: Senior Software Engineer | E91: Senior | F91: 8 | G91: C | H91: 46 | I91: Allergan Aesthetics, an AbbVie Company | J91: Pharmaceutical | K91: Denver, Colorado, United States | L91: allerganaesthetics.com | M91: https://www.linkedin.com/in/adambarnhard/
A92: Akshay Kumar | B92: Akshay | C92: Kumar | D92: Senior Software Engineer, Data and AI Engineering | E92: Senior | F92: 8 | G92: C | H92: 46 | I92: Bristol Myers Squibb | J92: Pharmaceutical | K92: Hyderabad, Telangana, India | L92: bms.com | M92: https://www.linkedin.com/in/akshay-kumar-93759615a/
... A100: Erwin Geussens | B100: Erwin | C100: Geussens | D100: Procurement Specialist | E100: Specialist | F100: 9 | G100: B+ | H100: 78 | I100: Organon | J100: Pharmaceutical | K100: Leuven, Flemish Region, Belgium | L100: organon.com | M100: https://www.linkedin.com/in/erwin-geussens-879b2ba4/
A101: Narayan Patar | B101: Narayan | C101: Patar | D101: Procurement Specialist | E101: Specialist | F101: 9 | G101: B+ | H101: 78 | I101: Pharmaceutical Industry | J101: Pharmaceutical | K101: Pune, Maharashtra, India | M101: https://www.linkedin.com/in/narayan-patar-96627614/
A102: Jose Antonio Alonso | B102: Jose | C102: Alonso | D102: Procurement Specialist | E102: Specialist | F102: 9 | G102: B+ | H102: 78 | I102: Teva Pharmaceuticals | J102: Pharmaceutical | K102: Leiden, South Holland, Netherlands | L102: tevapharm.com | M102: https://www.linkedin.com/in/jose-antonio-alonso-143b7831/
A103: Amro Al-Kiswani | B103: Amro | C103: Al-Kiswani | D103: Raw and Packaging Materials Procurement Specialist | E103: Specialist | F103: 9 | G103: B+ | H103: 78 | I103: The Jordanian Pharmaceutical Manufacturing Company | J103: Pharmaceutical | K103: عمان الأردن | L103: jpm.com.jo | M103: https://www.linkedin.com/in/amro-alkswani/
A104: Kaori N. | B104: Kaori | C104: N. | D104: Indirect Procurement Specialist | E104: Specialist | F104: 9 | G104: B+ | H104: 78 | I104: T’s Pharma Co., Ltd. | J104: Pharmaceutical | K104: Tokyo, Tokyo, Japan | L104: takeda-teva.com | M104: https://www.linkedin.com/in/kaori-n-389b55295/
A105: Jesse Luo | B105: Jesse | C105: Luo | D105: Supplier Development Engineer | E105: Engineer | F105: 10 | G105: A+ | H105: 92 | I105: Merck | J105: Pharmaceutical | K105: Philadelphia, Pennsylvania, United States | L105: merck.us | M105: https://www.linkedin.com/in/luojesse/
A106: Xavier Wiley | B106: Xavier | C106: Wiley | D106: Supplier Quality Engineer | E106: Engineer | F106: 10 | G106: A+ | H106: 92 | I106: Merck | J106: Pharmaceutical | K106: Raleigh-Durham-Chapel Hill Area | L106: merck.us | M106: https://www.linkedin.com/in/xavier-wiley/
A107: Amir Azodi | B107: Amir | C107: Azodi | D107: Quality Assurance Engineer | E107: Engineer | F107: 10 | G107: C+ | H107: 57 | I107: Crane ChemPharma & Energy | J107: Pharmaceutical | K107: Greater Sydney Area | L107: cranecpe.com | M107: https://www.linkedin.com/in/amir-azodi-47267778/
A108: Malavika M | B108: Malavika | C108: M | D108: Validation Quality Engineer | E108: Engineer | F108: 10 | G108: C+ | H108: 57 | I108: Exela Pharma Sciences LLC | J108: Pharmaceutical | K108: United States | L108: exelapharma.com | M108: https://www.linkedin.com/in/malavika-m-05b34b21b/
A109: Altus Meyer | B109: Altus | C109: Meyer | D109: Project Quality Engineer | E109: Engineer | F109: 10 | G109: C+ | H109: 57 | I109: invoX | J109: Pharmaceutical | K109: Greater London, United Kingdom | L109: invoxpharma.com | M109: https://www.linkedin.com/in/altus-meyer-0402bb206/
A110: Jyothi Prasad Goud Ravula | B110: Jyothi | C110: Ravula | D110: Quality Engineer | E110: Engineer | F110: 10 | G110: C+ | H110: 57 | I110: Merck | J110: Pharmaceutical | K110: Denton, Texas, United States | L110: merck.us | M110: https://www.linkedin.com/in/jyothiprasadr23/
A111: Jyothi Prasad Goud Ravula | B111: Jyothi | C111: Ravula | D111: Quality Engineer | E111: Engineer | F111: 10 | G111: C+ | H111: 57 | I111: Merck | J111: Pharmaceutical | K111: Denton, Texas, United States | L111: merck.us | M111: https://www.linkedin.com/in/jyothi-prasad-goud-ravula-b90942221/
A112: Erin Bennecke | B112: Erin | C112: Bennecke | D112: Quality Engineer | E112: Engineer | F112: 10 | G112: C+ | H112: 57 | I112: Merz Aesthetics | J112: Pharmaceutical | K112: Sturtevant, Wisconsin, United States | L112: merzaesthetics.com | M112: https://www.linkedin.com/in/erin-bennecke-7ab84123/
A113: Deepak Yadav | B113: Deepak | C113: Yadav | D113: Quality Assurance Engineer | E113: Engineer | F113: 10 | G113: C+ | H113: 57 | I113: Modern Automotives Ltd | J113: Pharmaceutical | K113: Mandi Gobindgarh, Punjab, India | L113: modernautomotives.com | M113: https://www.linkedin.com/in/deepak-yadav-731829265/
... A144: Vivek Kumar | B144: Vivek | C144: Kumar | D144: Global Category Buyer | E144: Buyer | F144: 11 | G144: A | H144: 82 | I144: Sanofi | J144: Pharmaceutical | K144: Hyderabad, Telangana, India | L144: sanofi.com | M144: https://www.linkedin.com/in/vivek-kumar-94372077/
A145: King Akinsusi | B145: Akinsusi | D145: Pharmaceutical Development Buyer | E145: Buyer | F145: 11 | G145: A | H145: 82 | I145: Servier | J145: Pharmaceutical | K145: Massy, Île-de-France, France | L145: servier.com | M145: https://www.linkedin.com/in/akinsusi/
A146: Julia Guedes Secco Sousa | B146: Julia | C146: Sousa | D146: Junior Buyer – Raw Materials & Packaging | E146: Buyer | F146: 11 | G146: A | H146: 82 | I146: Thépenier Pharma & Cosmetics | J146: Pharmaceutical | K146: Paris, Île-de-France, France | L146: thepenier-pharma.com | M146: https://www.linkedin.com/in/julia-guedes-secco/
A147: Komal Advani | B147: Komal | C147: Advani | D147: Procurement officer | E147: Buyer | F147: 11 | G147: A | H147: 82 | I147: Torrent Pharmaceuticals Ltd | J147: Pharmaceutical | K147: Ahmedabad, Gujarat, India | L147: torrentpharma.com | M147: https://www.linkedin.com/in/komal-advani-a235b463/
A148: kajal Gujarathi | B148: kajal | C148: Gujarathi | D148: Strategic Buyer | E148: Buyer | F148: 11 | G148: A | H148: 82 | I148: Xeolas Pharmaceuticals | J148: Pharmaceutical | K148: Dublin, County Dublin, Ireland | L148: xeolas.com | M148: https://www.linkedin.com/in/kajal-gujarathi-b6ba46123/
A149: Ajay Jayaraj | B149: Ajay | C149: Jayaraj | D149: Databricks Developer - SDE | E149: Other | F149: 12 | G149: C | H149: 38 | I149: Astellas Pharma | J149: Pharmaceutical | K149: Bengaluru, Karnataka, India | L149: astellas.com | M149: https://www.linkedin.com/in/ajayj2000/
A150: Nicolas Dodeman | B150: Nicolas | C150: Dodeman | D150: Acheteur Industriel | E150: Other | F150: 12 | G150: C | H150: 38 | I150: Boehringer Ingelheim | J150: Pharmaceutical | K150: Lyon, Auvergne-Rhône-Alpes, France | L150: boehringer-ingelheim.com | M150: https://www.linkedin.com/in/nicolas-dodeman/

Sheet Medical Devices
A1: Full Name | B1: First Name | C1: Last Name | D1: Job Title | E1: Seniority Level | F1: Seniority Rank | G1: Lead Score | H1: Opportunity Score | I1: Company Name | J1: Industry | K1: Location | L1: Company Domain | M1: LinkedIn Profile | N1: Phone | O1: Email/Gmail | P1: Follow Up 1 | Q1: Follow Up 2 | R1: Follow Up 3 | S1: Follow Up 4 | T1: Follow Up 5 | U1: Email 1 | V1: Email 2 | W1: Email 3 | X1: Email 4 | Y1: Email 5 | Z1: Cold Call 1 | AA1: Cold Call 2 | AB1: Cold Call 3 | AC1: Meeting | AD1: RFQ | AE1: Quote | AF1: Won | AG1: Lost | AH1: Outcome Status | AI1: Rejection Reason | AJ1: Interest Reason | AK1: Notes | AL1: First Contact | AM1: Last Contact | AN1: Next Follow-up
A2: Asad Nizamani | B2: Asad | C2: Nizamani | D2: Sr. Sourcing Manager (Abbott Global Procurement) | E2: Manager | F2: 6 | G2: A+ | H2: 94 | I2: Abbott | J2: Medical Devices | K2: Pakistan, Pakistan | L2: abbott.com | M2: https://www.linkedin.com/in/asad-nizamani-8172832a/
A3: Bahar Merve Soykan Betin | B3: Bahar | C3: Betin | D3: Direct Procurement Manager | E3: Manager | F3: 6 | G3: A+ | H3: 94 | I3: Abbott | J3: Medical Devices | K3: Istanbul, Turkey | L3: abbott.com | M3: https://www.linkedin.com/in/bahar-merve-soykan-betin-91871696/
A4: Jason C. | B4: Jason | C4: C. | D4: Corporate Procurement Manager - Biologics | E4: Manager | F4: 6 | G4: A+ | H4: 94 | I4: Abbott | J4: Medical Devices | K4: Greater Chicago Area, United States | L4: abbott.com | M4: https://www.linkedin.com/in/jchorazy/
A5: Maarten Petter | B5: Maarten | C5: Petter | D5: Procurement Manager Packaging | E5: Manager | F5: 6 | G5: A+ | H5: 94 | I5: Abbott | J5: Medical Devices | K5: Staphorst, Overijssel, Netherlands | L5: abbott.com | M5: https://www.linkedin.com/in/maarten-petter-81861b28/
A6: Michael Tardi | B6: Michael | C6: Tardi | D6: Global Strategic Purchasing – Procurement Manager (Reagents & Biologics) | E6: Manager | F6: 6 | G6: A+ | H6: 94 | I6: Abbott | J6: Medical Devices | K6: Greater Chicago Area | L6: abbott.com | M6: https://www.linkedin.com/in/michaeltardi/
A7: Christina Janus | B7: Christina | C7: Janus | D7: Strategic Procurement Manager, Direct Spend | E7: Manager | F7: 6 | G7: A+ | H7: 94 | I7: Ambu | J7: Medical Devices | K7: Copenhagen, Capital Region, Denmark | L7: ambu.com | M7: https://www.linkedin.com/in/christina-janus-061a2b1/
A8: Luis Aguado | B8: Luis | C8: Aguado | D8: Sr. Quality/Supplier Quality Engineer/Manager | E8: Manager | F8: 6 | G8: A+ | H8: 100 | I8: Ascensia Diabetes Care | J8: Medical Devices | K8: Dover, New Jersey, United States | L8: ascensia.com | M8: https://www.linkedin.com/in/luis-aguado-8a676935/
A9: Lyubov Dolgopolova | B9: Lyubov | C9: Dolgopolova | D9: Senior Procurement Manager | E9: Manager | F9: 6 | G9: A+ | H9: 94 | I9: Bausch + Lomb | J9: Medical Devices | K9: Moscow City, Russia | L9: bausch.com | M9: https://www.linkedin.com/in/lyubovdolgopolova/
A10: Aleksandra Brodowicz | B10: Aleksandra | C10: Brodowicz | D10: Senior Procurement Manager EMEA & APAC | E10: Manager | F10: 6 | G10: A+ | H10: 94 | I10: Baxter International Inc. | J10: Medical Devices | K10: Warsaw Metropolitan Area, Poland | L10: baxter.com | M10: https://www.linkedin.com/in/aleksandra-brodowicz-a4aa2365/
A11: Gerardo Treviño | B11: Gerardo | C11: Treviño | D11: Global Commodity Manager | E11: Manager | F11: 6 | G11: A+ | H11: 94 | I11: Baxter International Inc. | J11: Medical Devices | K11: Nuevo León, Mexico | L11: baxter.com | M11: https://www.linkedin.com/in/gerardo-treviño-5a4450101/
A12: Johnny Chinchilla | B12: Johnny | C12: Chinchilla | D12: Sr. Procurement Manager Infusion Therapies & Technologies | E12: Manager | F12: 6 | G12: A+ | H12: 94 | I12: Baxter International Inc. | J12: Medical Devices | K12: Costa Rica | L12: baxter.com | M12: https://www.linkedin.com/in/johnnychinchillacr/
A13: Claire Brossy-Laporte | B13: Claire | C13: Brossy-Laporte | D13: SG&A Procurement Manager EMEA | E13: Manager | F13: 6 | G13: A+ | H13: 94 | I13: BD | J13: Medical Devices | K13: Greater Grenoble Metropolitan Area, France | L13: bd.com | M13: https://www.linkedin.com/in/claire-brossy-laporte-b3563946/
... A195: Aurora Jiménez Vargas | B195: Aurora | C195: Vargas | D195: Quality Engineer III | E195: Engineer | F195: 10 | G195: B | H195: 64 | I195: Abbott | J195: Medical Devices | K195: San Jose, Costa Rica | L195: abbott.com | M195: https://www.linkedin.com/in/aurora-jiménez-vargas/
A196: Gundla . | B196: Gundla | D196: Manufacturing Quality Engineer | E196: Engineer | F196: 10 | G196: B | H196: 64 | I196: Abbott | J196: Medical Devices | K196: Hillsboro, Oregon, United States | L196: abbott.com | M196: https://www.linkedin.com/in/balaji-varma-gundla-/
A197: Karla Sofìa Ramírez Sánchez | B197: Karla | C197: Sánchez | D197: Quality Engineer III | E197: Engineer | F197: 10 | G197: B | H197: 64 | I197: Abbott | J197: Medical Devices | K197: San Jose, Costa Rica | L197: abbott.com | M197: https://www.linkedin.com/in/karla-ram%c3%adrez-s%c3%a1nchez-61059b96/
A198: Ritvik raj v | B198: Ritvik | C198: raj | D198: Quality Engineer | E198: Engineer | F198: 10 | G198: B | H198: 64 | I198: Abbott | J198: Medical Devices | K198: Kingsville, Texas, United States | L198: abbott.com | M198: https://www.linkedin.com/in/ritvik-raj-v-a1317621a/
A199: Simran Sankhe | B199: Simran | C199: Sankhe | D199: Operations Quality Engineer | E199: Engineer | F199: 10 | G199: B | H199: 64 | I199: Abbott | J199: Medical Devices | K199: Kilkenny, County Kilkenny, Ireland | L199: abbott.com | M199: https://www.linkedin.com/in/simran-sankhe-601437121/
A200: VamsiKiran Eruvaram | B200: VamsiKiran | C200: Eruvaram | D200: Quality Engineer | E200: Engineer | F200: 10 | G200: B | H200: 64 | I200: Abbott | J200: Medical Devices | K200: Santa Clara, California, United States | L200: abbott.com | M200: https://www.linkedin.com/in/vamsikiran-eruvaram/
A201: Andrew Singgih | B201: Andrew | C201: Singgih | D201: Principal Quality Assurance Engineer | E201: Engineer | F201: 10 | G201: B | H201: 64 | I201: Adagio Medical Inc. | J201: Medical Devices | K201: Irvine, California, United States | L201: adagiomedical.com | M201: https://www.linkedin.com/in/andrew-singgih-3766552/
A202: Jesus Anaya | B202: Jesus | C202: Anaya | D202: Quality Engineer | E202: Engineer | F202: 10 | G202: B | H202: 64 | I202: Alcon | J202: Medical Devices | K202: Chino, California, United States | L202: alcon.com | M202: https://www.linkedin.com/in/jesus-anaya-0a269a156/
A203: Sabreen S. | B203: Sabreen | C203: S. | D203: Design Quality Engineer II | E203: Engineer | F203: 10 | G203: B | H203: 64 | I203: Arthrex | J203: Medical Devices | K203: United States | L203: arthrex.com | M203: https://www.linkedin.com/in/sabreen-shaik-b7a03516a/
A204: Will Lucas | B204: Will | C204: Lucas | D204: Principal Design Quality Engineer | E204: Engineer | F204: 10 | G204: B | H204: 64 | I204: Arthrex | J204: Medical Devices | K204: Camarillo, California, United States | L204: arthrex.com | M204: https://www.linkedin.com/in/willlucas1/
A205: Gnanendra Gopal | B205: Gnanendra | C205: Gopal | D205: Software and Diagnostics - Customer Quality Engineer | E205: Engineer | F205: 10 | G205: B | H205: 64 | I205: Ather Energy | J205: Medical Devices | K205: Bengaluru South, Karnataka, India | L205: atherenergy.com | M205: https://www.linkedin.com/in/gnanendragopal/
A206: Jonathon Elliott | B206: Jonathon | C206: Elliott | D206: Quality Engineer | E206: Engineer | F206: 10 | G206: B | H206: 64 | I206: Baxter Enterprises / Baxter Manufacturing | J206: Medical Devices | K206: Greenville-Spartanburg-Anderson, South Carolina Area | L206: baxterent.com | M206: https://www.linkedin.com/in/jonathon-elliott-382031171/
A207: Arun Mathew | B207: Arun | C207: Mathew | D207: Quality Engineer | E207: Engineer | F207: 10 | G207: B | H207: 64 | I207: Baylis Medical Technologies | J207: Medical Devices | K207: Oshawa, Ontario, Canada | L207: baylismedtech.com | M207: https://www.linkedin.com/in/arun-mathew-28384ba9/
A208: Dhruv Modi | B208: Dhruv | C208: Modi | D208: Manufacturing Quality Engineer | E208: Engineer | F208: 10 | G208: B | H208: 64 | I208: BD | J208: Medical Devices | K208: San Diego, California, United States | L208: bd.com | M208: https://www.linkedin.com/in/dhruv-modi9/
... A289: Carlos Finger | B289: Carlos | C289: Finger | D289: Analista de Qualidade Pleno | E289: Other | F289: 12 | G289: C | H289: 45 | I289: Taurus Armas | J289: Medical Devices | K289: Novo Hamburgo, Rio Grande do Sul, Brazil | L289: taurusarmas.com.br | M289: https://www.linkedin.com/in/carlos-finger-455847b3/

Sheet Industrial Equipment
A1: Full Name | B1: First Name | C1: Last Name | D1: Job Title | E1: Seniority Level | F1: Seniority Rank | G1: Lead Score | H1: Opportunity Score | I1: Company Name | J1: Industry | K1: Location | L1: Company Domain | M1: LinkedIn Profile | N1: Phone | O1: Email/Gmail | P1: Follow Up 1 | Q1: Follow Up 2 | R1: Follow Up 3 | S1: Follow Up 4 | T1: Follow Up 5 | U1: Email 1 | V1: Email 2 | W1: Email 3 | X1: Email 4 | Y1: Email 5 | Z1: Cold Call 1 | AA1: Cold Call 2 | AB1: Cold Call 3 | AC1: Meeting | AD1: RFQ | AE1: Quote | AF1: Won | AG1: Lost | AH1: Outcome Status | AI1: Rejection Reason | AJ1: Interest Reason | AK1: Notes | AL1: First Contact | AM1: Last Contact | AN1: Next Follow-up
A2: Andrew Mendez | B2: Andrew | C2: Mendez | D2: President | Senior Buyer | E2: C-Level | F2: 1 | G2: A+ | H2: 100 | I2: Blackstone Machinery | J2: Industrial Equipment | K2: Cerritos, California, United States | L2: blackstonemachinery.com | M2: https://www.linkedin.com/in/andrewmendez21/
A3: Mugo Wanjohi | B3: Mugo | C3: Wanjohi | D3: Senior sales associate used machinery, Digital marketing head , chief buyer | E3: C-Level | F3: 1 | G3: A+ | H3: 100 | I3: Machine 4 Africa LTD. | J3: Industrial Equipment | K3: Kenya | L3: machine4africa.com | M3: https://www.linkedin.com/in/mugo-wanjohi-55622b1b/
A4: Belinda T. | B4: Belinda | C4: T. | D4: Sourcing Manager - Strategic Commodity Management | E4: Manager | F4: 6 | G4: A+ | H4: 94 | I4: 3M | J4: Industrial Equipment | K4: Singapore | L4: mmm.com | M4: https://www.linkedin.com/in/belinda-t-48321459/
A5: Ryan Grant | B5: Ryan | C5: Grant | D5: Senior Global Sourcing Manager | E5: Manager | F5: 6 | G5: A+ | H5: 94 | I5: AirLife | J5: Industrial Equipment | K5: Greater Pittsburgh Region | L5: myairlife.com | M5: https://www.linkedin.com/in/ryan-grant-1a64663a/
A6: Claus Møller | B6: Claus | C6: Møller | D6: Global Purchasing Manager | E6: Manager | F6: 6 | G6: A+ | H6: 94 | I6: Alfa Laval | J6: Industrial Equipment | K6: Greater Malmö Metropolitan Area, Sweden | L6: alfalaval.com | M6: https://www.linkedin.com/in/claus-m%c3%b8ller-3a6b6a8/
A7: Terje Klyver | B7: Terje | C7: Klyver | D7: Global Purchasing Manager | E7: Manager | F7: 6 | G7: A+ | H7: 94 | I7: Alfa Laval | J7: Industrial Equipment | K7: Tumba, Stockholm County, Sweden | L7: alfalaval.com | M7: https://www.linkedin.com/in/terje-klyver-7800503/
A8: Renê Bajo | B8: Renê | C8: Bajo | D8: USA Purchasing Manager - HOY Compressor Division | E8: Manager | F8: 6 | G8: A+ | H8: 94 | I8: Atlas Copco | J8: Industrial Equipment | K8: Fort Mill, South Carolina, United States | L8: atlascopco.com | M8: https://www.linkedin.com/in/renê-bajo-b826b874/
A9: Hauke Hans | B9: Hauke | C9: Hans | D9: Leiter Einkauf / Purchasing Manager | E9: Manager | F9: 6 | G9: A+ | H9: 94 | I9: Atlas Copco Group | J9: Industrial Equipment | K9: Neustadt an der Donau, Bavaria, Germany | L9: atlascopcogroup.com | M9: https://www.linkedin.com/in/hauke-hans-75a76916/
A10: Romain Boré | B10: Romain | C10: Boré | D10: Procurement Manager - Pipe, fittings and structural steel | E10: Manager | F10: 6 | G10: A+ | H10: 94 | I10: Boccard | J10: Industrial Equipment | K10: Sillingy, Auvergne-Rhône-Alpes, France | L10: boccard.com | M10: https://www.linkedin.com/in/romain-bore/
A11: Andrew Moore | B11: Andrew | C11: Moore | D11: Global Procurement Manager | E11: Manager | F11: 6 | G11: A+ | H11: 94 | I11: Caterpillar Inc. | J11: Industrial Equipment | K11: Mossville, Illinois, United States | L11: caterpillar.com | M11: https://www.linkedin.com/in/andrew-moore-048aa/
A12: Baljinder Singh | B12: Baljinder | C12: Singh | D12: Procurement Manager | E12: Manager | F12: 6 | G12: A+ | H12: 94 | I12: Caterpillar Inc. | J12: Industrial Equipment | K12: Tucson, Arizona, United States | L12: caterpillar.com | M12: https://www.linkedin.com/in/baljinder-singh-52bb2a36/
A13: Cynthia Rogers | B13: Cynthia | C13: Rogers | D13: Procurement Manager, Fasteners | E13: Manager | F13: 6 | G13: A+ | H13: 94 | I13: Caterpillar Inc. | J13: Industrial Equipment | K13: Peoria Metropolitan Area | L13: caterpillar.com | M13: https://www.linkedin.com/in/cynrogers/
... A48: swapnil kulkarni | B48: Swapnil | C48: Kulkarni | D48: Procurement Manager | E48: Manager | F48: 6 | G48: A+ | H48: 94 | I48: Kirloskar Brothers Limited | J48: Industrial Equipment | K48: Pune, Maharashtra, India | L48: kirloskarpumps.com | M48: https://www.linkedin.com/in/swapnil-kulkarni-14183a1b/
A49: 杨瑞霞Vivien | B49: Vivien | D49: Purchasing Manager | E49: Manager | F49: 6 | G49: A+ | H49: 94 | I49: Lei Shing Hong Machinery | J49: Industrial Equipment | K49: Shanghai, China | L49: lsh-ppower.com | M49: https://www.linkedin.com/in/vivien-杨瑞霞-674b6116/
A50: Karla Mayela Ruiz Meza | B50: Karla | C50: Meza | D50: Commodity Manager CVP North America | E50: Manager | F50: 6 | G50: A+ | H50: 94 | I50: Littelfuse | J50: Industrial Equipment | K50: San Luis Potosí, San Luis Potosí, México | L50: littelfuse.com | M50: https://www.linkedin.com/in/karla-mayela-ruiz-meza-62717161/
A51: Anand Khedkar | B51: Anand | C51: Khedkar | D51: Strategic Sourcing Manager | E51: Manager | F51: 6 | G51: A+ | H51: 94 | I51: Mahindra and Mahindra Limited [Automotive and Farm Equipment Business] | J51: Industrial Equipment | K51: Mumbai, Maharashtra, India | L51: mahindracareers.com | M51: https://www.linkedin.com/in/anand-khedkar-12ba88b7/
A52: Arshad shaikh | B52: Arshad | C52: shaikh | D52: Assistant Purchasing Manager | E52: Manager | F52: 6 | G52: A+ | H52: 94 | I52: Mahindra and Mahindra Limited [Automotive and Farm Equipment Business] | J52: Industrial Equipment | K52: Pune District, Maharashtra, India | L52: mahindracareers.com | M52: https://www.linkedin.com/in/arshad-shaikh-336025111/
A53: Mahesh Jatte | B53: Mahesh | C53: Jatte | D53: Assistant Manager - SCM Buyer | E53: Manager | F53: 6 | G53: A+ | H53: 94 | I53: Mahindra and Mahindra Limited [Automotive and Farm Equipment Business] | J53: Industrial Equipment | K53: Mumbai, Maharashtra, India | L53: mahindracareers.com | M53: https://www.linkedin.com/in/mahesh-jatte-b57810211/
A54: Syed Z. | B54: Syed | C54: Z. | D54: Cost Engineering & Strategic Sourcing Manager | E54: Manager | F54: 6 | G54: A+ | H54: 94 | I54: Mahindra and Mahindra Limited [Automotive and Farm Equipment Business] | J54: Industrial Equipment | K54: Bengaluru, Karnataka, India | L54: mahindracareers.com | M54: https://www.linkedin.com/in/syed-z-b381057a/
A55: André Lopes | B55: André | C55: Lopes | D55: Sourcing Manager (Strategic Team) | E55: Manager | F55: 6 | G55: A+ | H55: 94 | I55: Metso | J55: Industrial Equipment | K55: São Bernardo do Campo, São Paulo, Brazil | L55: metso.com | M55: https://www.linkedin.com/in/andr%c3%a9-lopes-06464190/
A56: Anu Penttinen | B56: Anu | C56: Penttinen | D56: Project Procurement Manager | E56: Manager | F56: 6 | G56: A+ | H56: 94 | I56: Metso | J56: Industrial Equipment | K56: Helsinki, Uusimaa, Finland | L56: metso.com | M56: https://www.linkedin.com/in/anu-penttinen/
A57: Gokhan Santurkaya | B57: Gokhan | C57: Santurkaya | D57: Global Mill Lining Procurement Manager | E57: Manager | F57: 6 | G57: A+ | H57: 94 | I57: Metso | J57: Industrial Equipment | K57: Ankara, Turkey | L57: metso.com | M57: https://www.linkedin.com/in/gokhan-santurkaya-61428261/
A58: Vesa Nieminen | B58: Vesa | C58: Nieminen | D58: Global Category Sourcing Manager | E58: Manager | F58: 6 | G58: A+ | H58: 94 | I58: Metso | J58: Industrial Equipment | K58: Helsinki, Uusimaa, Finland | L58: metso.com | M58: https://www.linkedin.com/in/vesa-nieminen-1a567764/
A59: Tarun Shankar | B59: Tarun | C59: Shankar | D59: Sourcing Manager | E59: Manager | F59: 6 | G59: A+ | H59: 94 | I59: Metso Outotec | J59: Industrial Equipment | K59: Surat, Gujarat, India | L59: mogroup.com | M59: https://www.linkedin.com/in/tarun-shankar-0b664438/
A60: Andre Coenen | B60: Andre | C60: Coenen | D60: Purchasing Manager | E60: Manager | F60: 6 | G60: A+ | H60: 94 | I60: Nedschroef Machinery | J60: Industrial Equipment | K60: Kuringen, Flemish Region, Belgium | L60: nedschroefmachinery.com | M60: https://www.linkedin.com/in/coenenandre/
A61: Romain Chies | B61: Romain | C61: Chies | D61: Global Indirect Purchasing Manager | E61: Manager | F61: 6 | G61: A+ | H61: 94 | I61: OPmobility | J61: Industrial Equipment | K61: Brittany, France | L61: opmobility.com | M61: https://www.linkedin.com/in/romain-chies/
... A105: Michael Traber | B105: Michael | C105: Traber | D105: Senior Buyer | E105: Senior | F105: 8 | G105: A | H105: 88 | I105: ITT Flow Technologies | J105: Industrial Equipment | K105: Houston, Texas, United States | L105: itt.com | M105: https://www.linkedin.com/in/michael-traber-023bb0b/
A106: Noel Soliva | B106: Noel | C106: Soliva | D106: Sr. Strategic Buyer - OSAT Procurement | E106: Senior | F106: 8 | G106: A | H106: 88 | I106: Littelfuse Phils, Inc. | J106: Industrial Equipment | K106: Cebu, Central Visayas, Philippines | M106: https://www.linkedin.com/in/noel-soliva-4a22367/
A107: Cynthia Falone | B107: Cynthia | C107: Falone | D107: Senior Buyer | E107: Senior | F107: 8 | G107: A | H107: 88 | I107: Milton Roy, An Ingersoll Rand Business | J107: Industrial Equipment | K107: Warminster, Pennsylvania, United States | L107: miltonroy.com | M107: https://www.linkedin.com/in/cynthia-falone-6643047/
A108: Luis Ferraz | B108: Luis | C108: Ferraz | D108: Capital Equipment Senior Buyer | E108: Senior | F108: 8 | G108: A | H108: 88 | I108: Molex | J108: Industrial Equipment | K108: Detroit Metropolitan Area, United States | L108: molex.com | M108: https://www.linkedin.com/in/luis-felipe-fregonezi-ferraz/
A109: William P. Mahoney, Jr. | B109: William | C109: Mahoney | D109: Senior Buyer | E109: Senior | F109: 8 | G109: A | H109: 88 | I109: Parker Hannifin | J109: Industrial Equipment | K109: Greater Boston | L109: parker.com | M109: https://www.linkedin.com/in/william-p-mahoney-jr-671368126/
A110: Guilherme Piwowarczyk Reis | B110: Guilherme | C110: Reis | D110: Senior Buyer | E110: Senior | F110: 8 | G110: A | H110: 88 | I110: Sulzer | J110: Industrial Equipment | K110: Jundiaí, São Paulo, Brazil | L110: sulzer.com | M110: https://www.linkedin.com/in/guipiworeis/
A111: Filip Heimerle | B111: Filip | C111: Heimerle | D111: Senior buyer | E111: Senior | F111: 8 | G111: A | H111: 88 | I111: WITTE Automotive | J111: Industrial Equipment | K111: Karlovy Vary, Czechia | L111: witte-automotive.com | M111: https://www.linkedin.com/in/filip-heimerle-994b2216/
A112: Tanmay Gupta | B112: Tanmay | C112: Gupta | D112: Senior Quality Engineer | E112: Senior | F112: 8 | G112: B | H112: 68 | I112: Atlas Copco Group | J112: Industrial Equipment | K112: Pune Division, Maharashtra, India | L112: atlascopcogroup.com | M112: https://www.linkedin.com/in/tanmay-gupta-575a0556/
A113: J.R. Plote | B113: J.R. | C113: Plote | D113: Senior Quality Engineer | E113: Senior | F113: 8 | G113: B | H113: 68 | I113: Eaton | J113: Industrial Equipment | K113: Greater Milwaukee, United States | L113: eaton.com | M113: https://www.linkedin.com/in/j-r-plote-27b5aa11a/
A114: Anton Zemleroub | B114: Anton | C114: Zemleroub | D114: Senior Quality Engineer | E114: Senior | F114: 8 | G114: B | H114: 68 | I114: Foxconn Industrial Internet - FII | J114: Industrial Equipment | K114: San Jose, California, United States | L114: applytojob.com | M114: https://www.linkedin.com/in/anton-zemleroub-01193b12/
A115: Gayathri V. | B115: Gayathri | C115: V. | D115: Senior Quality Engineer – Data & AI Automation (SDET) | E115: Senior | F115: 8 | G115: B | H115: 68 | I115: IQVIA | J115: Industrial Equipment | K115: Plano, Texas, United States | L115: iqvia.com | M115: https://www.linkedin.com/in/gvemuri4/
A116: Mayank Mishra | B116: Mayank | C116: Mishra | D116: Senior Quality Engineer | E116: Senior | F116: 8 | G116: B | H116: 68 | I116: Metso | J116: Industrial Equipment | K116: Alwar, Rajasthan, India | L116: metso.com | M116: https://www.linkedin.com/in/mayank-mishra-371785229/
A117: Logan Mulderrig | B117: Logan | C117: Mulderrig | D117: Senior Quality Assurance Engineer | E117: Senior | F117: 8 | G117: B | H117: 68 | I117: Pentair | J117: Industrial Equipment | K117: Raleigh, North Carolina, United States | L117: pentair.com | M117: https://www.linkedin.com/in/loganmulderrig/
A118: Tan Woei Chang | B118: Tan | C118: Chang | D118: Senior Quality Engineer (INDUSTRIAL) | E118: Senior | F118: 8 | G118: B | H118: 68 | I118: Plexus Corp. | J118: Industrial Equipment | K118: Bayan Lepas, Penang, Malaysia | L118: plexus.com | M118: https://www.linkedin.com/in/tan-woei-chang-40a81649/
... A187: Ravindra W. | B187: Ravindra | C187: W. | D187: Software Development Engineer | E187: Engineer | F187: 10 | G187: C | H187: 49 | I187: Alfa Laval | J187: Industrial Equipment | K187: Pune Division, Maharashtra, India | L187: alfalaval.com | M187: https://www.linkedin.com/in/ravindra-waghchoure-a5390aa9/
A188: Shivani Rathod | B188: Shivani | C188: Rathod | D188: Software Engineer | E188: Engineer | F188: 10 | G188: C | H188: 49 | I188: ArcelorMittal Global Business & Technologies | J188: Industrial Equipment | K188: Hyderabad, Telangana, India | M188: https://www.linkedin.com/in/shivani-rathod-63486019b/
A189: Baudouin BELPAIRE | B189: Baudouin | C189: BELPAIRE | D189: Automation & Embedded Software Engineer - Motion Control & Command Systems | E189: Engineer | F189: 10 | G189: C | H189: 49 | I189: BOBST | J189: Industrial Equipment | K189: Lyon et périphérie | L189: bobst.com | M189: https://www.linkedin.com/in/baudouin-belpaire/
A190: Dimpal Kalra | B190: Dimpal | C190: Kalra | D190: Software Engineer | E190: Engineer | F190: 10 | G190: C | H190: 49 | I190: Caterpillar Inc. | J190: Industrial Equipment | K190: Bengaluru, Karnataka, India | L190: caterpillar.com | M190: https://www.linkedin.com/in/dimpal-kalra-6a0b23115/
A191: Karthik S | B191: Karthik | C191: S | D191: Software Engineer I | E191: Engineer | F191: 10 | G191: C | H191: 49 | I191: Caterpillar Inc. | J191: Industrial Equipment | K191: Bengaluru, Karnataka, India | L191: caterpillar.com | M191: https://www.linkedin.com/in/karthik-s-141102201/
A192: Rohit Ravikumar | B192: Rohit | C192: Ravikumar | D192: Embedded Software Engineer - HIL | E192: Engineer | F192: 10 | G192: C | H192: 49 | I192: Caterpillar Inc. | J192: Industrial Equipment | K192: Peoria Metropolitan Area | L192: caterpillar.com | M192: https://www.linkedin.com/in/rohitravikumar-/
A193: Sharmila Singaram | B193: Sharmila | C193: Singaram | D193: Software Engineer | E193: Engineer | F193: 10 | G193: C | H193: 49 | I193: Caterpillar Inc. | J193: Industrial Equipment | K193: Chennai, Tamil Nadu, India | L193: caterpillar.com | M193: https://www.linkedin.com/in/sharmila-singaram-85b9a8250/
A194: Shirish Paramashivaiah | B194: Shirish | C194: Paramashivaiah | D194: Embedded Software Engineer | E194: Engineer | F194: 10 | G194: C | H194: 49 | I194: Caterpillar Inc. | J194: Industrial Equipment | K194: Peoria, Illinois, United States | L194: caterpillar.com | M194: https://www.linkedin.com/in/shirish-param/
A195: Vinoth Kannan | B195: Vinoth | C195: Kannan | D195: Embedded Software Engineer(Test Automation) | E195: Engineer | F195: 10 | G195: C | H195: 49 | I195: Cirrus Logic | J195: Industrial Equipment | K195: Edinburgh, Scotland, United Kingdom | L195: cirrus.com | M195: https://www.linkedin.com/in/vinothkann97/
A196: Amit Kumar | B196: Amit | C196: Kumar | D196: Embedded Software Engineer | E196: Engineer | F196: 10 | G196: C | H196: 49 | I196: CNH | J196: Industrial Equipment | K196: Pune District, Maharashtra, India | L196: cnh.com | M196: https://www.linkedin.com/in/amit-kumar-2207801ab/
A197: Zeyad Mostafa | B197: Zeyad | C197: Mostafa | D197: Software Engineer– AI & Automation | E197: Engineer | F197: 10 | G197: C | H197: 49 | I197: DeRoyal | J197: Industrial Equipment | K197: Vermillion, South Dakota, United States | L197: deroyal.com | M197: https://www.linkedin.com/in/zeyad-mostafa-89052b260/
A198: Reagan Sun | B198: Reagan | C198: Sun | D198: Software Engineer (EIT) - Fabrication Design Automation | E198: Engineer | F198: 10 | G198: C | H198: 49 | I198: Haakon Industries Ltd. | J198: Industrial Equipment | K198: Greater Vancouver Metropolitan Area | L198: haakon.com | M198: https://www.linkedin.com/in/reagan-sun-16b78a1b/
A199: Vins Patel | B199: Vins | C199: Patel | D199: Software Engineer — Debug Tools & Automation | E199: Engineer | F199: 10 | G199: C | H199: 49 | I199: Intel | J199: Industrial Equipment | K199: Bangalore Urban, Karnataka, India | L199: intel.com | M199: https://www.linkedin.com/in/vinspatel/
A200: Yuriy Bilyk | B200: Yuriy | C200: Bilyk | D200: GPU Software Development Engineer - GPU Test Automation Ecosystem Architect | E200: Engineer | F200: 10 | G200: C | H200: 49 | I200: Intel | J200: Industrial Equipment | K200: Folsom, California, United States | L200: intel.com | M200: https://www.linkedin.com/in/bilyky/
... A282: S. Papadopoulos | B282: S. | C282: Papadopoulos | D282: Acheteur projet | E282: Other | F282: 12 | G282: C | H282: 45 | I282: WITTMANN Group | J282: Industrial Equipment | K282: Grenoble, Auvergne-Rhône-Alpes, France | L282: wittmann-group.com | M282: https://www.linkedin.com/in/sofian-papadopoulos-1a43b1106/

Sheet HVAC Appliances
A1: Full Name | B1: First Name | C1: Last Name | D1: Job Title | E1: Seniority Level | F1: Seniority Rank | G1: Lead Score | H1: Opportunity Score | I1: Company Name | J1: Industry | K1: Location | L1: Company Domain | M1: LinkedIn Profile | N1: Phone | O1: Email/Gmail | P1: Follow Up 1 | Q1: Follow Up 2 | R1: Follow Up 3 | S1: Follow Up 4 | T1: Follow Up 5 | U1: Email 1 | V1: Email 2 | W1: Email 3 | X1: Email 4 | Y1: Email 5 | Z1: Cold Call 1 | AA1: Cold Call 2 | AB1: Cold Call 3 | AC1: Meeting | AD1: RFQ | AE1: Quote | AF1: Won | AG1: Lost | AH1: Outcome Status | AI1: Rejection Reason | AJ1: Interest Reason | AK1: Notes | AL1: First Contact | AM1: Last Contact | AN1: Next Follow-up
A2: Ghanashyam T | B2: Ghanashyam | C2: T | D2: Sourcing Manager | E2: Manager | F2: 6 | G2: A+ | H2: 94 | I2: A.O. Smith India | J2: HVAC Appliances | K2: Bengaluru, Karnataka, India | L2: aosmithindia.com | M2: https://www.linkedin.com/in/ghanashyam-t-52a79621/
A3: Susan Siegel | B3: Susan | C3: Siegel | D3: Group Commodity Manager, Indirect | E3: Manager | F3: 6 | G3: A+ | H3: 94 | I3: Broan-NuTone | J3: HVAC Appliances | K3: New York City Metropolitan Area, United States | L3: broan-nutone.com | M3: https://www.linkedin.com/in/susan-siegel/
A4: Gülhande AYDIN | B4: Gülhande | C4: AYDIN | D4: Commodity Manager | E4: Manager | F4: 6 | G4: A+ | H4: 94 | I4: BSH Home Appliances Group | J4: HVAC Appliances | K4: Turkey | L4: bsh-group.com | M4: https://www.linkedin.com/in/g%c3%bclhande-aydin-722371a8/
A5: Serkan Burak YILDIRIM | B5: Serkan | C5: YILDIRIM | D5: Purchasing Manager | E5: Manager | F5: 6 | G5: A+ | H5: 94 | I5: BSH Home Appliances Group | J5: HVAC Appliances | K5: Greenville-Washington, North Carolina Area | L5: bsh-group.com | M5: https://www.linkedin.com/in/serkan-burak-yildirim-b1081535/
A6: Roberto Najera Flores | B6: Roberto | C6: Flores | D6: Strategic Sourcing Manager | E6: Manager | F6: 6 | G6: A+ | H6: 94 | I6: Daikin Applied Americas | J6: HVAC Appliances | K6: Nuevo León, Mexico | L6: daikinapplied.com | M6: https://www.linkedin.com/in/roberto-najera-flores-b0b20258/
A7: Milton J. SEGOVIA | B7: Milton | C7: SEGOVIA | D7: Senior Commodity Manager | E7: Manager | F7: 6 | G7: A+ | H7: 94 | I7: Daikin Comfort | J7: HVAC Appliances | K7: Monterrey Metropolitan Area | L7: daikincomfort.com | M7: https://www.linkedin.com/in/msegovia132628/
A8: Rakesh Sethukumar | B8: Rakesh | C8: Sethukumar | D8: Strategic Sourcing Manager | E8: Manager | F8: 6 | G8: A+ | H8: 94 | I8: Danfoss | J8: HVAC Appliances | K8: Scarborough, Ontario, Canada | L8: danfoss.com | M8: https://www.linkedin.com/in/rakeshsethu/
A9: Bhanudas Patil | B9: Bhanudas | C9: Patil | D9: Global Sourcing Manager | E9: Manager | F9: 6 | G9: A+ | H9: 94 | I9: Danfoss Power Solutions | J9: HVAC Appliances | K9: Pune Division, Maharashtra, India | L9: danfoss.com | M9: https://www.linkedin.com/in/bhanudas-patil-a56a2963/
A10: Roger Rieckers | B10: Roger | C10: Rieckers | D10: Senior Commodity Manager | E10: Manager | F10: 6 | G10: A+ | H10: 94 | I10: GE Appliances, a Haier company | J10: HVAC Appliances | K10: New Albany, Indiana, United States | L10: geappliancesco.com | M10: https://www.linkedin.com/in/roger-rieckers/
A11: Kerim Tulgar | B11: Kerim | C11: Tulgar | D11: Procurement Manager | E11: Manager | F11: 6 | G11: A+ | H11: 94 | I11: Haier Europe | J11: HVAC Appliances | K11: Eskişehir, Turkey | L11: haier-europe.com | M11: https://www.linkedin.com/in/kerim-tulgar-a014918b/
A12: Riccardo Granata | B12: Riccardo | C12: Granata | D12: Global Commodity Manager Transformation & Strategic Components | E12: Manager | F12: 6 | G12: A+ | H12: 94 | I12: Haier Europe | J12: HVAC Appliances | K12: Corbetta, Lombardy, Italy | L12: haier-europe.com | M12: https://www.linkedin.com/in/riccardogranata/
A13: Paweł Nośko | B13: Paweł | C13: Nośko | D13: Procurement Manager Capital and Tooling | E13: Manager | F13: 6 | G13: A+ | H13: 100 | I13: KIRCHHOFF Automotive | J13: HVAC Appliances | K13: Mielecki, Podkarpackie, Poland | L13: kirchhoff-automotive.com | M13: https://www.linkedin.com/in/paweł-nośko-72b64212a/
... A81: Sabine Hantke | B81: Sabine | C81: Hantke | D81: Einkäuferin | E81: Other | F81: 12 | G81: C | H81: 45 | I81: Miele | J81: HVAC Appliances | K81: Gütersloh, North Rhine-Westphalia, Germany | L81: miele.com | M81: https://www.linkedin.com/in/sabine-hantke-0ab738236/

Sheet Packaging
A1: Full Name | B1: First Name | C1: Last Name | D1: Job Title | E1: Seniority Level | F1: Seniority Rank | G1: Lead Score | H1: Opportunity Score | I1: Company Name | J1: Industry | K1: Location | L1: Company Domain | M1: LinkedIn Profile | N1: Phone | O1: Email/Gmail | P1: Follow Up 1 | Q1: Follow Up 2 | R1: Follow Up 3 | S1: Follow Up 4 | T1: Follow Up 5 | U1: Email 1 | V1: Email 2 | W1: Email 3 | X1: Email 4 | Y1: Email 5 | Z1: Cold Call 1 | AA1: Cold Call 2 | AB1: Cold Call 3 | AC1: Meeting | AD1: RFQ | AE1: Quote | AF1: Won | AG1: Lost | AH1: Outcome Status | AI1: Rejection Reason | AJ1: Interest Reason | AK1: Notes | AL1: First Contact | AM1: Last Contact | AN1: Next Follow-up | AO1: Lead Warmth Level | AP1: Priority | AQ1: Recommended Channel | AR1: Current Stage | AS1: Value Proposition | AT1: Pain Point
A2: KC Christensen | B2: KC | C2: Christensen | D2: CEO Used Equipment Buyer Packaging Specialist Investment Recovery | E2: C-Level | F2: 1 | G2: A+ | H2: 100 | I2: Aaron Kendell Packaging Equipment (AEK) | J2: Packaging | K2: Belvidere, Illinois, United States | L2: aekpack.com | M2: https://www.linkedin.com/in/kcchristensen1/
A3: Ken Stevens | B3: Ken | C3: Stevens | D3: Sr. Director Sourcing & Procurement ; sr. Group Sourcing Manager Mech. assies, tooling & packaging | E3: Director | F3: 4 | G3: A+ | H3: 100 | I3: ASML | J3: Packaging | K3: Kalmthout, Flemish Region, Belgium | L3: asml.com | M3: https://www.linkedin.com/in/ken-stevens-a5386568/
A4: Naree Ferreira | B4: Naree | C4: Ferreira | D4: Global Sourcing Manager Packaging Strategic Projects | E4: Manager | F4: 6 | G4: A+ | H4: 94 | I4: AB InBev | J4: Packaging | K4: Leuven, Flemish Region, Belgium | L4: ab-inbev.com | M4: https://www.linkedin.com/in/naree-ferreira-20210324/
A5: Sonia Sánchez Baena | B5: Sonia | C5: Baena | D5: Packaging procurement manager | E5: Manager | F5: 6 | G5: A+ | H5: 94 | I5: AB InBev | J5: Packaging | K5: Mexico City, Mexico | L5: ab-inbev.com | M5: https://www.linkedin.com/in/sonia-sánchez-baena-b3354810a/
A6: Tanja Caddell | B6: Tanja | C6: Caddell | D6: Sr. Commodity Manager, Packaging, Mgr. of team for Fasteners, Machined Parts & Springs | E6: Manager | F6: 6 | G6: A+ | H6: 94 | I6: Allegion | J6: Packaging | K6: Colorado Springs, Colorado, United States | L6: allegion.com | M6: https://www.linkedin.com/in/tanja-caddell-277a1310/
A7: Milena Nagamine | B7: Milena | C7: Nagamine | D7: Senior Procurement Manager | Raw Materials, Components, Packaging & Outsourcing | E7: Manager | F7: 6 | G7: A+ | H7: 94 | I7: Alpargatas S.A. | J7: Packaging | K7: São Paulo e Região | L7: alpargatas.com.br | M7: https://www.linkedin.com/in/milena-nagamine-a48b2344/
A8: Nuria Teran | B8: Nuria | C8: Teran | D8: Purchasing Manager Metal, Fasteners & Packaging EMEA & ASIA | E8: Manager | F8: 6 | G8: A+ | H8: 94 | I8: Antolin | J8: Packaging | K8: Greater Burgos Metropolitan Area | L8: antolin.com | M8: https://www.linkedin.com/in/nuria-teran-8071a69/
A9: Erkan Gunes | B9: Erkan | C9: Gunes | D9: Purchasing Manager | E9: Manager | F9: 6 | G9: A+ | H9: 94 | I9: Apack Packaging Technologies | J9: Packaging | K9: Istanbul, Turkey | L9: apack.com.tr | M9: https://www.linkedin.com/in/erkan-gunes-16ab0716b/
A10: Paulo Gurita | B10: Paulo | C10: Gurita | D10: Purchasing Manager BAC (Brazil, Argentina & Chile) | E10: Manager | F10: 6 | G10: A+ | H10: 94 | I10: Avery Dennison Label and Packaging Materials | J10: Packaging | K10: Greater Campinas | L10: averydennison.com | M10: https://www.linkedin.com/in/paulo-gurita-55723513/
A11: Melisa Devichund | B11: Melisa | C11: Devichund | D11: Procurement Manager- Packaging | E11: Manager | F11: 6 | G11: A+ | H11: 94 | I11: AVI Limited | J11: Packaging | K11: City of Johannesburg, Gauteng, South Africa | L11: avi.co.za | M11: https://www.linkedin.com/in/melisa-sukku-52a58535/
A12: Marcio Remor, MBA, SCPro | B12: Marcio | C12: SCPro | D12: Strategic Sourcing Manager - Packaging | E12: Manager | F12: 6 | G12: A+ | H12: 94 | I12: Barr Brands | J12: Packaging | K12: Collierville, Tennessee, United States | L12: barrbrands.com | M12: https://www.linkedin.com/in/marcio-remor-mba-scpro-26162835/
A13: Alejandro Parodi | B13: Alejandro | C13: Parodi | D13: Global Procurement Manager Logistics & Packaging | E13: Manager | F13: 6 | G13: A+ | H13: 94 | I13: Bekaert | J13: Packaging | K13: Leuven, Flemish Region, Belgium | L13: bekaert.com | M13: https://www.linkedin.com/in/alejandro-parodi/
... A250: Weslei Coimbra | B250: Weslei | C250: Coimbra | D250: Comprador | E250: Other | F250: 12 | G250: C | H250: 45 | I250: ULMA Packaging Brasil | J250: Packaging | K250: Santa Bárbara d'Oeste, São Paulo, Brazil | L250: ulmapackaging.com.br | M250: https://www.linkedin.com/in/weslei-coimbra-011654181/
A251: Bruno Pack | B251: Bruno | C251: Pack | D251: Senior Buyer | E251: Senior | F251: 7 | I251: Tetra Pak | J251: Packaging | AH251: Active | AO251: Frío | AP251: Media | AQ251: LinkedIn | AR251: Nuevo lead

Sheet Consumer Goods
A1: Full Name | B1: First Name | C1: Last Name | D1: Job Title | E1: Seniority Level | F1: Seniority Rank | G1: Lead Score | H1: Opportunity Score | I1: Company Name | J1: Industry | K1: Location | L1: Company Domain | M1: LinkedIn Profile | N1: Phone | O1: Email/Gmail | P1: Follow Up 1 | Q1: Follow Up 2 | R1: Follow Up 3 | S1: Follow Up 4 | T1: Follow Up 5 | U1: Email 1 | V1: Email 2 | W1: Email 3 | X1: Email 4 | Y1: Email 5 | Z1: Cold Call 1 | AA1: Cold Call 2 | AB1: Cold Call 3 | AC1: Meeting | AD1: RFQ | AE1: Quote | AF1: Won | AG1: Lost | AH1: Outcome Status | AI1: Rejection Reason | AJ1: Interest Reason | AK1: Notes | AL1: First Contact | AM1: Last Contact | AN1: Next Follow-up
A2: Sebastien Aumiaux | B2: Sebastien | C2: Aumiaux | D2: Group Chief Procurement Officer | E2: C-Level | F2: 1 | G2: A+ | H2: 93 | I2: Cooper Consumer Health | J2: Consumer Goods | K2: Bordeaux, Nouvelle-Aquitaine, France | L2: cooperconsumerhealth.com | M2: https://www.linkedin.com/in/sebastien-aumiaux-3972973/
A3: Shailendra Sadera | B3: Shailendra | C3: Sadera | D3: Chief Procurement Officer | E3: C-Level | F3: 1 | G3: A+ | H3: 93 | I3: Unilever | J3: Consumer Goods | K3: London, England, United Kingdom | L3: unilever.com | M3: https://www.linkedin.com/in/shailendra-sadera-64a5171/
A4: Sharon Wang | B4: Sharon | C4: Wang | D4: Sourcing Manager - Plastics Engineering | E4: Manager | F4: 6 | G4: A+ | H4: 100 | I4: Newell Brands | J4: Consumer Goods | K4: Charlotte, North Carolina, United States | L4: newellbrands.com | M4: https://www.linkedin.com/in/sharon-wang-635451124/
A5: Rawan El-Ashkar | B5: Rawan | C5: El-Ashkar | D5: Senior purchasing manager for Fabric care injection molding NA | E5: Manager | F5: 6 | G5: A+ | H5: 100 | I5: Procter & Gamble | J5: Consumer Goods | K5: Cincinnati, Ohio, United States | L5: pg.com | M5: https://www.linkedin.com/in/rawanelashkar/
A6: Thomas Delfau | B6: Thomas | C6: Delfau | D6: Senior Purchasing Manager - EU Resins and Masterbatches | E6: Manager | F6: 6 | G6: A+ | H6: 100 | I6: Procter & Gamble | J6: Consumer Goods | K6: Geneva, Switzerland | L6: pg.com | M6: https://www.linkedin.com/in/thomas-delfau-2b89825a/
A7: Richard Chin | B7: Richard | C7: Chin | D7: Sourcing Manager (Colorants, Additives, Inks, Injection Molding) | E7: Manager | F7: 6 | G7: A+ | H7: 100 | I7: Reynolds Consumer Products | J7: Consumer Goods | K7: Greater Chicago Area | L7: reynoldsconsumerproducts.com | M7: https://www.linkedin.com/in/richard-chin-a1781564/
A8: Victor de Lima Spilleir | B8: Victor | C8: de Lima Spilleir | D8: Procurement Manager - Rigid Plastics & Electrical Devices | E8: Manager | F8: 6 | G8: A+ | H8: 100 | I8: SC Johnson | J8: Consumer Goods | K8: Rio de Janeiro, Brazil | L8: scjohnson.com | M8: https://www.linkedin.com/in/victor-de-lima-spilleir-28b389156/
A9: Nico Febriady | B9: Nico | C9: Febriady | D9: Global Procurement Manager Plastics Sustainability | E9: Manager | F9: 6 | G9: A+ | H9: 100 | I9: Unilever | J9: Consumer Goods | K9: Indonesia, Indonesia | L9: unilever.com | M9: https://www.linkedin.com/in/nico-febriady-04974b4b/
A10: Veeresh Kotagi | B10: Veeresh | C10: Kotagi | D10: Global Assistant Procurement Manager – Injection Moulds & Rigids | E10: Manager | F10: 6 | G10: A+ | H10: 100 | I10: Unilever | J10: Consumer Goods | K10: Mumbai, Maharashtra, India | L10: unilever.com | M10: https://www.linkedin.com/in/veeresh-kotagi-b33990198/
A11: Venugopal (Venu) Reddy | B11: Venugopal | C11: Reddy | D11: Procurement Manager - Plastics Sustainability | Analytics | Reporting | Assurance | E11: Manager | F11: 6 | G11: A+ | H11: 100 | I11: Unilever | J11: Consumer Goods | K11: Mumbai, Maharashtra, India | L11: unilever.com | M11: https://www.linkedin.com/in/venugopal-venu-reddy-9b717618/
A12: Binod GC | B12: Binod | C12: GC | D12: Regional Procurement Manager at Coca-Cola beverages Nepal | E12: Manager | F12: 6 | G12: A | H12: 87 | I12: Coca-Cola Beverages Nepal | J12: Consumer Goods | K12: Bharatpur, Nepal | L12: bnl.com.np | M12: https://www.linkedin.com/in/binod-gc-64534960/
A13: Morgan Chatelain | B13: Morgan | C13: Chatelain | D13: Capital Equipment Procurement Manager | E13: Manager | F13: 6 | G13: A | H13: 87 | I13: Coca-Cola Europacific Partners | J13: Consumer Goods | K13: Paris, Île-de-France, France | L13: cocacolaep.com | M13: https://www.linkedin.com/in/morgan-chatelain-581b1a105/
... A119: Khaled Amro | B119: Khaled | C119: Amro | D119: Procurement Specialist - Henkel Consumer Brands GCC | E119: Specialist | F119: 9 | G119: B+ | H119: 78 | I119: Henkel | J119: Consumer Goods | K119: Dubai, United Arab Emirates | L119: henkel.com | M119: https://www.linkedin.com/in/khaled-amro/
A120: Eric Vanevenhoven | B120: Eric | C120: Vanevenhoven | D120: Procurement Specialist | E120: Specialist | F120: 9 | G120: B+ | H120: 78 | I120: Kimberly-Clark | J120: Consumer Goods | K120: Appleton, Wisconsin, United States | M120: https://www.linkedin.com/in/eric-vanevenhoven-68407943/
A121: Giovanna Danziato | B121: Giovanna | C121: Danziato | D121: Procurement Specialist | E121: Specialist | F121: 9 | G121: B+ | H121: 78 | I121: Reckitt | J121: Consumer Goods | K121: Vitória Brasil, São Paulo, Brazil | L121: reckitt.com | M121: https://www.linkedin.com/in/giovanna-danziato/
A122: Salvious L. Machado | B122: Salvious | C122: Machado | D122: Procurement Specialist | E122: Specialist | F122: 9 | G122: B+ | H122: 78 | I122: Unilever | J122: Consumer Goods | K122: Mumbai, Maharashtra, India | L122: unilever.com | M122: https://www.linkedin.com/in/salvious-machado/
A123: Erick Rene Montemayor Garza | B123: Erick | C123: Garza | D123: Molding Quality Engineer | E123: Engineer | F123: 10 | G123: A | H123: 82 | I123: the LEGO Group | J123: Consumer Goods | K123: San Nicolás de Los Garza, Nuevo León, Mexico | L123: lego.com | M123: https://www.linkedin.com/in/erick-rene-montemayor-garza-6a4690227/
A124: Daniel-Octavian Simion | B124: Daniel-Octavian | C124: Simion | D124: Software Engineer | E124: Engineer | F124: 10 | G124: C | H124: 42 | I124: the LEGO Group | J124: Consumer Goods | K124: Copenhagen, Capital Region, Denmark | L124: lego.com | M124: https://www.linkedin.com/in/simiondaniel/
A125: Zuardin Akbar | B125: Zuardin | C125: Akbar | D125: Software Engineer | E125: Engineer | F125: 10 | G125: C | H125: 42 | I125: the LEGO Group | J125: Consumer Goods | K125: Billund, South Denmark, Denmark | L125: lego.com | M125: https://www.linkedin.com/in/zuardinakbar/
A126: April Cassin | B126: April | C126: Cassin | D126: Buyer, Plastic Assemblies | E126: Buyer | F126: 11 | G126: A+ | H126: 100 | I126: Unilever | J126: Consumer Goods | K126: New York City Metropolitan Area, United States | L126: unilever.com | M126: https://www.linkedin.com/in/aprilcassin/
A127: Francesco Ravizza | B127: Francesco | C127: Ravizza | D127: UFLP - Buyer - Injection Moulded Plastics: Home Care & Foods | E127: Buyer | F127: 11 | G127: A+ | H127: 100 | I127: Unilever | J127: Consumer Goods | K127: Netherlands | L127: unilever.com | M127: https://www.linkedin.com/in/francesco-ravizza-81b5b0160/
A128: Michael Nicolo | B128: Michael | C128: Nicolo | D128: Buyer | E128: Buyer | F128: 11 | G128: A | H128: 82 | I128: Church & Dwight Co., Inc. | J128: Consumer Goods | K128: Burlington, New Jersey, United States | L128: churchdwight.com | M128: https://www.linkedin.com/in/michael-nicolo-0b216010/
A129: Erik Alexander | B129: Erik | C129: Alexander | D129: Raw Materials Buyer | E129: Buyer | F129: 11 | G129: A | H129: 82 | I129: Newell Brands | J129: Consumer Goods | K129: Nashville Metropolitan Area | L129: newellbrands.com | M129: https://www.linkedin.com/in/erik-alexander-b4251b9/
A130: Anika Nawar, CSCATM | B130: Anika | C130: CSCA | D130: Procurement Officer | E130: Buyer | F130: 11 | G130: A | H130: 82 | I130: Reckitt | J130: Consumer Goods | K130: Dhaka, Bangladesh | L130: reckitt.com | M130: https://www.linkedin.com/in/anikanawarcsca/
A131: Elizabeth Q. | B131: Elizabeth | C131: Q. | D131: Procurement Buyer | E131: Buyer | F131: 11 | G131: A | H131: 82 | I131: Reckitt | J131: Consumer Goods | K131: Greater Sydney Area | L131: reckitt.com | M131: https://www.linkedin.com/in/elizabeth-q-3abb2860/

Sheet Software IT
A1: Full Name | B1: First Name | C1: Last Name | D1: Job Title | E1: Seniority Level | F1: Seniority Rank | G1: Lead Score | H1: Opportunity Score | I1: Company Name | J1: Industry | K1: Location | L1: Company Domain | M1: LinkedIn Profile | N1: Phone | O1: Email/Gmail | P1: Follow Up 1 | Q1: Follow Up 2 | R1: Follow Up 3 | S1: Follow Up 4 | T1: Follow Up 5 | U1: Email 1 | V1: Email 2 | W1: Email 3 | X1: Email 4 | Y1: Email 5 | Z1: Cold Call 1 | AA1: Cold Call 2 | AB1: Cold Call 3 | AC1: Meeting | AD1: RFQ | AE1: Quote | AF1: Won | AG1: Lost | AH1: Outcome Status | AI1: Rejection Reason | AJ1: Interest Reason | AK1: Notes | AL1: First Contact | AM1: Last Contact | AN1: Next Follow-up
A2: Jason Garceau | B2: Jason | C2: Garceau | D2: SVP of Strategic Sourcing & ABL Chief Procurement Officer | E2: C-Level | F2: 1 | G2: B+ | H2: 75 | I2: Acuity | J2: Software IT | K2: Stockton, New Jersey, United States | L2: acuityinc.com | M2: https://www.linkedin.com/in/jason-garceau/
A3: Ben Szostek | B3: Ben | C3: Szostek | D3: Chief Procurement Officer | E3: C-Level | F3: 1 | G3: B+ | H3: 75 | I3: Apex Tool Group, LLC | J3: Software IT | K3: Davidson, North Carolina, United States | L3: apextoolgroup.com | M3: https://www.linkedin.com/in/ben-szostek-58720a11/
A4: Ghazi Chaoui | B4: Ghazi | C4: Chaoui | D4: Chief Procurement Officer at COHERENT | E4: C-Level | F4: 1 | G4: B+ | H4: 75 | I4: II-VI Incorporated | J4: Software IT | K4: San Jose, California, United States | L4: coherent.com | M4: https://www.linkedin.com/in/ghazi-chaoui-030a5523/
A5: Frank Mckay | B5: Frank | C5: Mckay | D5: Chief Supply Chain & Procurement Officer | E5: C-Level | F5: 1 | G5: B+ | H5: 75 | I5: Jabil | J5: Software IT | K5: St. Petersburg, Florida, United States | L5: jabil.com | M5: https://www.linkedin.com/in/frank-mckay-1297a14/
A6: Rahul Sinnarkar | B6: Rahul | C6: Sinnarkar | D6: Chief Procurement Manager | E6: C-Level | F6: 1 | G6: B+ | H6: 75 | I6: John Cockerill | J6: Software IT | K6: Mumbai Metropolitan Region, India | L6: johncockerill.com | M6: https://www.linkedin.com/in/rahul-sinnarkar-36141a23/
A7: Marco Milani | B7: Marco | C7: Milani | D7: Chief Procurement Officer at kdc/one Home Care Division | E7: C-Level | F7: 1 | G7: B+ | H7: 75 | I7: kdc/one | J7: Software IT | K7: Trento, Trentino-Alto Adige, Italy | L7: kdc-one.com | M7: https://www.linkedin.com/in/milanimarco/
A8: Simon Saba | B8: Simon | C8: Saba | D8: Group Chief Procurement Officer (Purchasing, Supply Chain, QM, ESG, Real Estate), Managing Director | E8: C-Level | F8: 1 | G8: B+ | H8: 75 | I8: Keenfinity Group | J8: Software IT | K8: Stuttgart Region, Germany | L8: keenfinity-group.com | M8: https://www.linkedin.com/in/simon-saba/
A9: Eric Salisbury | B9: Eric | C9: Salisbury | D9: Chief Legal Affairs & Procurement Officer - Board of Directors Secretary | E9: C-Level | F9: 1 | G9: B+ | H9: 75 | I9: SANY America | J9: Software IT | K9: Greater Chicago Area, United States | L9: sanyamerica.com | M9: https://www.linkedin.com/in/eric-salisbury1/
A10: Cedric Ducros | B10: Cedric | C10: Ducros | D10: Chief Procurement Officer | E10: C-Level | F10: 1 | G10: B+ | H10: 75 | I10: SEQENS | J10: Software IT | K10: Geneva, Geneva, Switzerland | L10: seqens.com | M10: https://www.linkedin.com/in/c%c3%a9dric-ducros-2961696/
A11: Shawn Pace | B11: Shawn | C11: Pace | D11: Vice President and Chief Procurement Officer | E11: C-Level | F11: 1 | G11: B+ | H11: 75 | I11: The Goodyear Tire & Rubber Company | J11: Software IT | K11: Canton, Ohio, United States | L11: goodyear.com | M11: https://www.linkedin.com/in/shawn-pace-2919022/
A12: Oscar Luis Rego (Eur Eng.) | B12: Oscar | C12: Rego | D12: EVP - Chief Procurement Officer | E12: C-Level | F12: 1 | G12: B+ | H12: 75 | I12: TK Elevator | J12: Software IT | K12: Madrid, Community of Madrid, Spain | L12: tkelevator.com | M12: https://www.linkedin.com/in/oscarrego/
A13: Cesar Toscano | B13: Cesar | C13: Toscano | D13: CEO & Founder (Principal Software Engineer) | E13: C-Level | F13: 1 | G13: C | H13: 40 | I13: Weller Labs | J13: Software IT | K13: San Francisco, California, United States | L13: wellerlabs.com | M13: https://www.linkedin.com/in/cesartoscano/
... A79: Nathan Kroll | B79: Nathan | C79: Kroll | D79: Senior Purchasing Manager | E79: Manager | F79: 6 | G79: B | H79: 69 | I79: AUMOVIO | J79: Software IT | K79: Detroit Metropolitan Area | L79: aumovio.com | M79: https://www.linkedin.com/in/nathankroll/
A80: Amit Bajare | B80: Amit | C80: Bajare | D80: Manager Project Buyer | E80: Manager | F80: 6 | G80: B | H80: 69 | I80: AUO Mobility Solutions | J80: Software IT | K80: Pune, Maharashtra, India | M80: https://www.linkedin.com/in/amit-bajare-2847b51a/
A81: Ashwin Swaminathan | B81: Ashwin | C81: Swaminathan | D81: Commodity Manager | E81: Manager | F81: 6 | G81: B | H81: 69 | I81: Autocar Trucks | J81: Software IT | K81: United States | L81: autocartruck.com | M81: https://www.linkedin.com/in/ashwin-swaminathan-1508111a/
A82: Alexander H. | B82: Alexander | C82: H. | D82: Global Mechanics and APAC Sourcing Manager | E82: Manager | F82: 6 | G82: B | H82: 69 | I82: AutoStoreTM | J82: Software IT | K82: United States, United States | L82: autostoresystem.com | M82: https://www.linkedin.com/in/alexanderhovik/
A83: Suresh Viswanathan | B83: Suresh | C83: Viswanathan | D83: Strategic Sourcing Manager | E83: Manager | F83: 6 | G83: B | H83: 69 | I83: AVTEC Limited | J83: Software IT | K83: Chennai, Tamil Nadu, India | L83: avtec.in | M83: https://www.linkedin.com/in/suresh-v-06122a96/
A84: Elliot O'Connell | B84: Elliot | C84: O'Connell | D84: Procurement Manager | E84: Manager | F84: 6 | G84: B | H84: 69 | I84: Avtron Power Solutions | J84: Software IT | K84: United Kingdom | L84: avtronpower.com | M84: https://www.linkedin.com/in/elliot-o-connell-76756957/
A85: Olivia Ishman | B85: Olivia | C85: Ishman | D85: Purchasing Manager – Architectural Lighting Manufacturing | E85: Manager | F85: 6 | G85: B | H85: 69 | I85: BASO | J85: Software IT | K85: Monroe, Connecticut, United States | L85: basolighting.com | M85: https://www.linkedin.com/in/olivia-ishman-254b43144/
A86: Jessica Hernandez Barraza | B86: Jessica | C86: Barraza | D86: Global Sustainabiliy Procurement Manager | E86: Manager | F86: 6 | G86: B | H86: 69 | I86: BAT | J86: Software IT | K86: United Kingdom, United Kingdom | L86: bat.com | M86: https://www.linkedin.com/in/jessica-hernandez-barraza-5250aa109/
A87: Joanna Stepniak | B87: Joanna | C87: Stepniak | D87: Global Sourcing Manager | E87: Manager | F87: 6 | G87: B | H87: 69 | I87: BAT | J87: Software IT | K87: Poole, England, United Kingdom | L87: bat.com | M87: https://www.linkedin.com/in/joanna-stepniak-33b682127/
A88: Sohail Tariq | B88: Sohail | C88: Tariq | D88: Area Sourcing Manager Middle East (Indirects) | E88: Manager | F88: 6 | G88: B | H88: 69 | I88: BAT | J88: Software IT | K88: United Arab Emirates | L88: bat.com | M88: https://www.linkedin.com/in/sohail-tariq-017b4910/
A89: Karen Estrada | B89: Karen | C89: Estrada | D89: Senior Commodity Manager | E89: Manager | F89: 6 | G89: B | H89: 69 | I89: BCS Automotive Interface Solutions | J89: Software IT | K89: Mexico, Mexico | L89: bcs-ais.com | M89: https://www.linkedin.com/in/karen-estrada-72514ba4/
A90: Fabio Tonazzo | B90: Fabio | C90: Tonazzo | D90: Commodity Sourcing Manager | E90: Manager | F90: 6 | G90: B | H90: 69 | I90: Beko Europe | J90: Software IT | K90: Varese, Lombardy, Italy | L90: bekoeurope.com | M90: https://www.linkedin.com/in/fabio-tonazzo/
A91: Amit Upadhyay | B91: Amit | C91: Upadhyay | D91: NPD - Procurement Manager | E91: Manager | F91: 6 | G91: B | H91: 69 | I91: BellaVita | J91: Software IT | K91: Mumbai, Maharashtra, India | L91: bellavitaorganic.com | M91: https://www.linkedin.com/in/amit-upadhyay-977841139/
A92: Joseph Wong | B92: Joseph | C92: Wong | D92: Global Commodity Manager | E92: Manager | F92: 6 | G92: B | H92: 69 | I92: Benchmark | J92: Software IT | K92: Butterworth, Penang, Malaysia | L92: bench.com | M92: https://www.linkedin.com/in/joseph-wong-b95105126/
... A157: Ivaylo Savov | B157: Ivaylo | C157: Savov | D157: Purchasing Manager | E157: Manager | F157: 6 | G157: B | H157: 69 | I157: FACOTEC - Espresso pod machine | J157: Software IT | K157: La Trinité, Provence-Alpes-Côte d'Azur, France | L157: facotec.com | M157: https://www.linkedin.com/in/ivaylo-savov-9b90896/
A158: 吴浩思 | B158: 浩思 | C158: 吴 | D158: Senior Sourcing Manager | E158: Manager | F158: 6 | G158: B | H158: 69 | I158: Fast Turn Chip Electronics Limited | J158: Software IT | L158: fastturnchip.com | M158: https://www.linkedin.com/in/浩思-吴-a88035226/
A159: Ashwin Prasad Ponnada | B159: Ashwin | C159: Ponnada | D159: Strategic Sourcing Manager | E159: Manager | F159: 6 | G159: B | H159: 69 | I159: Fathom Digital Manufacturing | J159: Software IT | K159: Champaign, Illinois, United States | L159: fathommfg.com | M159: https://www.linkedin.com/in/ashwinprasadponnada/
A160: Davoud Safaei | B160: Davoud | C160: Safaei | D160: Global Commodity Manager | E160: Manager | F160: 6 | G160: B | H160: 69 | I160: First Brands Group, LLC | J160: Software IT | K160: Zona metropolitană București | L160: firstbrandsgroup.com | M160: https://www.linkedin.com/in/davoud-safaei-b93277111/
A161: José Lozano | B161: José | C161: Lozano | D161: Strategic Commodity Manager | E161: Manager | F161: 6 | G161: B | H161: 69 | I161: First Brands Group, LLC | J161: Software IT | K161: Monterrey, Nuevo León, Mexico | L161: firstbrandsgroup.com | M161: https://www.linkedin.com/in/josé-lozano/
A162: José Lozano | B162: José | C162: Lozano | D162: Strategic Commodity Manager | E162: Manager | F162: 6 | G162: B | H162: 69 | I162: First Brands Group, LLC | J162: Software IT | K162: Monterrey, Nuevo León, Mexico | L162: firstbrandsgroup.com | M162: https://www.linkedin.com/in/jose-lozano-mx/
A163: LEONG WING FOOK | B163: Leong | C163: Fook | D163: Global Commodity Manager | E163: Manager | F163: 6 | G163: B | H163: 69 | I163: Flex | J163: Software IT | K163: Johore, Malaysia | L163: flex.com | M163: https://www.linkedin.com/in/leong-wing-fook-75535325/
A164: Sergio Gonzalez | B164: Sergio | C164: Gonzalez | D164: GLOBAL COMMODITY MANAGER | E164: Manager | F164: 6 | G164: B | H164: 69 | I164: Flex | J164: Software IT | K164: Zapopan, Jalisco, Mexico | L164: flex.com | M164: https://www.linkedin.com/in/sergio-gonzalez-ab4b6752/
A165: Yudi Yu | B165: Yudi | C165: Yu | D165: Regional Procurement Manager, Asia Pacific | E165: Manager | F165: 6 | G165: B | H165: 69 | I165: Flora Food Group | J165: Software IT | K165: Jakarta Metropolitan Area | L165: florafoodgroup.com | M165: https://www.linkedin.com/in/yudiyu/
A166: Mario Lopez Montelongo | B166: Mario | C166: Montelongo | D166: Global Commodity Manager | E166: Manager | F166: 6 | G166: B | H166: 69 | I166: Franklin Electric | J166: Software IT | K166: Nuevo León, México | L166: franklin-electric.com | M166: https://www.linkedin.com/in/mario-lopez-montelongo-0a03903b/
A167: Loic Clochard | B167: Loic | C167: Clochard | D167: Procurement Manager | E167: Manager | F167: 6 | G167: B | H167: 69 | I167: Froneri | J167: Software IT | K167: Bordeaux, Nouvelle-Aquitaine, France | L167: froneri.com | M167: https://www.linkedin.com/in/loic-clochard/
A168: Mahmoud Nahhas | B168: Mahmoud | C168: Nahhas | D168: Commodity Manager | E168: Manager | F168: 6 | G168: B | H168: 69 | I168: G&W Electric Co. | J168: Software IT | K168: Greater Chicago Area | L168: gwelectric.com | M168: https://www.linkedin.com/in/mahmoud-nahhas-87485044/
A169: Tim Mason | B169: Tim | C169: Mason | D169: Global Strategic Sourcing Manager | E169: Manager | F169: 6 | G169: B | H169: 69 | I169: Garmin | J169: Software IT | K169: Kansas City Metropolitan Area | L169: garmin.com | M169: https://www.linkedin.com/in/tim-mason-893648b/
A170: Alexandra Gherghiceanu | B170: Alexandra | C170: Gherghiceanu | D170: GBE FCC&EC Procurement Manager | E170: Manager | F170: 6 | G170: B | H170: 69 | I170: Garrett - Advancing Motion | J170: Software IT | K170: Bucharest Metropolitan Area | L170: garrettmotion.com | M170: https://www.linkedin.com/in/alexandra-gherghiceanu-83851478/
... A260: Jukka Tiilikainen | B260: Jukka | C260: Tiilikainen | D260: Sourcing Manager External Manufacturing | E260: Manager | F260: 6 | G260: B | H260: 69 | I260: LifeScan | J260: Software IT | K260: Switzerland, Switzerland | L260: lifescan.com | M260: https://www.linkedin.com/in/jukka-tiilikainen/
A261: William Boulus | B261: William | C261: Boulus | D261: Sr. Purchasing Manager | E261: Manager | F261: 6 | G261: B | H261: 69 | I261: Linamar Corporation | J261: Software IT | K261: Macomb, Michigan, United States | M261: https://www.linkedin.com/in/williamboulus/
A262: Yash B. | B262: Yash | C262: B. | D262: Sourcing Manager | E262: Manager | F262: 6 | G262: B | H262: 69 | I262: Linde Advanced Material Technologies | J262: Software IT | K262: New York City Metropolitan Area, United States | L262: linde-amt.com | M262: https://www.linkedin.com/in/yashbhatia5/
A263: Anubhav Pathak | B263: Anubhav | C263: Pathak | D263: Global CAPEX Commodity Manager | E263: Manager | F263: 6 | G263: B | H263: 69 | I263: Linxens | J263: Software IT | K263: Rayong, Thailand | L263: linxens.com | M263: https://www.linkedin.com/in/anubhav-pathak-1022b1b/
A264: wolf liu | B264: Wolf | C264: Liu | D264: Global sourcing manager | E264: Manager | F264: 6 | G264: B | H264: 69 | I264: Lite-On Mobile Mechanical | J264: Software IT | K264: Guangzhou-Foshan Metropolitan Area | L264: liteonmobile.com | M264: https://www.linkedin.com/in/wolf-liu-a0225141/
A265: Brian Terrano | B265: Brian | C265: Terrano | D265: Purchasing Manager | E265: Manager | F265: 6 | G265: B | H265: 69 | I265: Litens Aftermarket, N.A. | J265: Software IT | K265: Detroit Metropolitan Area | L265: litensaftermarket.com | M265: https://www.linkedin.com/in/brian-terrano/
A266: Tyler Olson | B266: Tyler | C266: Olson | D266: Commodity Manager | E266: Manager | F266: 6 | G266: B | H266: 69 | I266: Logisnext Americas Inc. | J266: Software IT | K266: Greater Houston | L266: logisnextamericas.com | M266: https://www.linkedin.com/in/tylerolson61/
A267: Nadeem Siddiqui | B267: Nadeem | C267: Siddiqui | D267: Procurement Manager | E267: Manager | F267: 6 | G267: B | H267: 69 | I267: Macter International Limited | J267: Software IT | K267: Karāchi, Sindh, Pakistan | L267: macter.com | M267: https://www.linkedin.com/in/nadeemsiddiqui1/
A268: Alberto Turchi | B268: Alberto | C268: Turchi | D268: Commodity Manager | E268: Manager | F268: 6 | G268: B | H268: 69 | I268: Marelli | J268: Software IT | K268: Turin, Piedmont, Italy | L268: marelli.com | M268: https://www.linkedin.com/in/alberto-turchi-1166858/
A269: Paul Knight | B269: Paul | C269: Knight | D269: Senior Procurement Manager | E269: Manager | F269: 6 | G269: B | H269: 69 | I269: Marelli | J269: Software IT | K269: Houghton-Le-Spring, England, United Kingdom | L269: marelli.com | M269: https://www.linkedin.com/in/paul-knight-6b2671bb/
A270: Khushboo Thakur | B270: Khushboo | C270: Thakur | D270: Global Strategic Sourcing Manager - Raw Materials | E270: Manager | F270: 6 | G270: B | H270: 69 | I270: Marico Limited | J270: Software IT | K270: Mumbai, Maharashtra, India | L270: marico.com | M270: https://www.linkedin.com/in/khushboo-thakur4/
A271: Abhishek Tiwari | B271: Abhishek | C271: Tiwari | D271: Commodity Manager | E271: Manager | F271: 6 | G271: B | H271: 69 | I271: Maruti Suzuki India Limited | J271: Software IT | K271: Gurgaon, Haryana, India | L271: marutisuzuki.com | M271: https://www.linkedin.com/in/abhishektwr699/
A272: Barry A. Tomsky C.P.M. | B272: Barry | C272: Tomsky | D272: Purchasing Manager | E272: Manager | F272: 6 | G272: B | H272: 69 | I272: Master Machine & Repair Corp. | J272: Software IT | K272: Woodridge, Illinois, United States | L272: mastermachineandrepair.com | M272: https://www.linkedin.com/in/barry-a-tomsky-c-p-m-339bb77/
A273: John B. | B273: John | C273: B. | D273: Purchasing Manager | E273: Manager | F273: 6 | G273: B | H273: 69 | I273: MATCOR Metal Fabrication | J273: Software IT | K273: High Point, North Carolina, United States | L273: matcormetalfab.com | M273: https://www.linkedin.com/in/beaverjr/
... A297: Judson Goldsmith | B297: Judson | C297: Goldsmith | D297: Strategic Sourcing Manager | E297: Manager | F297: 6 | G297: B | H297: 69 | I297: Nestlé Purina North America | J297: Software IT | K297: St Louis, Missouri, United States | L297: purinajobs.com | M297: https://www.linkedin.com/in/judsongoldsmith/
A298: Amol Pathak | B298: Amol | C298: Pathak | D298: Global Sourcing Manager | E298: Manager | F298: 6 | G298: B | H298: 69 | I298: Neuman & Esser Engineering (I) Private Limited | J298: Software IT | K298: Pune Division, Maharashtra, India | M298: https://www.linkedin.com/in/amol-pathak-8144411b1/
A299: Deanna Oakes | B299: Deanna | C299: Oakes | D299: Purchasing Manager | E299: Manager | F299: 6 | G299: B | H299: 69 | I299: NexaMotion Group | J299: Software IT | K299: North Canton, Ohio, United States | L299: nexamotiongroup.com | M299: https://www.linkedin.com/in/deanna-oakes-16688b40/
A300: Bartłomiej Żeberek | B300: Bartłomiej | C300: Żeberek | D300: Commodity Manager EMEA | E300: Manager | F300: 6 | G300: B | H300: 69 | I300: Nexteer Automotive | J300: Software IT | K300: Tychy, Śląskie, Poland | L300: nexteer.com | M300: https://www.linkedin.com/in/bart%c5%82omiej-%c5%bceberek/
A301: MBA Juan Carlos Solis Urenda | B301: MBA | C301: Urenda | D301: Global Commodity Manager | E301: Manager | F301: 6 | G301: B | H301: 69 | I301: Nexteer Automotive | J301: Software IT | K301: Querétaro, Mexico | L301: nexteer.com | M301: https://www.linkedin.com/in/mba-juan-carlos-solis-urenda-7a3b6056/
A302: Saeed Noor | B302: Saeed | C302: Noor | D302: Sr. Purchasing Manager | E302: Manager | F302: 6 | G302: B | H302: 69 | I302: Nexteer Automotive | J302: Software IT | K302: Saginaw, Michigan, United States | L302: nexteer.com | M302: https://www.linkedin.com/in/saeed-noor-31b3571b/
A303: Yee Hui Ang | B303: Yee | C303: Ang | D303: Commodity Manager | E303: Manager | F303: 6 | G303: B | H303: 69 | I303: NI (National Instruments) | J303: Software IT | K303: Butterworth, Penang, Malaysia | L303: ni.com | M303: https://www.linkedin.com/in/yee-hui-ang-822474150/
A304: Manthan Lad | B304: Manthan | C304: Lad | D304: Advanced Purchasing Mechanical Group Sourcing Manager | E304: Manager | F304: 6 | G304: B | H304: 69 | I304: Nidec Mobility America Corporation | J304: Software IT | K304: Greater Chicago Area | L304: nidec.com | M304: https://www.linkedin.com/in/manthan-lad-99576610/
A305: Bilge Dilber Özdede | B305: Bilge | C305: Özdede | D305: Global Purchasing Commodity Manager | E305: Manager | F305: 6 | G305: B | H305: 69 | I305: Nobel Automotive | J305: Software IT | K305: Türkiye, Türkiye | L305: nobelautomotive.com | M305: https://www.linkedin.com/in/bilge-dilber-özdede-b8353567/
A306: Michael Jackson | B306: Michael | C306: Jackson | D306: Purchasing Manager (direct) | E306: Manager | F306: 6 | G306: B | H306: 69 | I306: North American Stamping Group | J306: Software IT | K306: Nashville, Tennessee, United States | L306: nasg.net | M306: https://www.linkedin.com/in/michael-jackson-495118247/
A307: Corentin GODET | B307: Corentin | C307: GODET | D307: Purchasing Manager | E307: Manager | F307: 6 | G307: B | H307: 69 | I307: Novalac Nutrition & Health | J307: Software IT | K307: Paris, Île-de-France, France | L307: novalac.com | M307: https://www.linkedin.com/in/corentin-godet-840513154/
A308: Brad Everingham | B308: Brad | C308: Everingham | D308: Purchasing Manager (Indirect) | E308: Manager | F308: 6 | G308: B | H308: 69 | I308: NSK | J308: Software IT | K308: Canton, Michigan, United States | L308: nsk.com | M308: https://www.linkedin.com/in/bradfordaeveringham/
A309: Khoa Nguyen | B309: Khoa | C309: Nguyen | D309: Sourcing Manager | Metal Fabrication, Machining, Castings, Hardware, & Steel Tubing | E309: Manager | F309: 6 | G309: B | H309: 69 | I309: nVent | J309: Software IT | K309: Minneapolis, Minnesota, United States | L309: nvent.com | M309: https://www.linkedin.com/in/khoa-nguyen-a022b577/
A310: Mark Hofer | B310: Mark | C310: Hofer | D310: Purchasing Manager | E310: Manager | F310: 6 | G310: B | H310: 69 | I310: Ohio Steel Industries | J310: Software IT | K310: Hilliard, Ohio, United States | L310: ohiosteel.com | M310: https://www.linkedin.com/in/mark-hofer-7304676/
... A436: Atul Lathi CSPTM | B436: Atul | C436: Lathi | D436: Strategic Sourcing Manager | E436: Manager | F436: 6 | G436: B | H436: 69 | I436: Voltas Limited - A TATA Enterprise | J436: Software IT | K436: India | L436: voltas.com | M436: https://www.linkedin.com/in/atul-lathi-csp™-24a62720/
A437: Mary Bailey | B437: Mary | C437: Bailey | D437: Procurement Manager | E437: Manager | F437: 6 | G437: B | H437: 69 | I437: Westwin Elements | J437: Software IT | K437: Houston, Texas, United States | M437: https://www.linkedin.com/in/mary-bailey-2903a952/
A438: Everardo Arbey Reyes Marquez | B438: Everardo | C438: Marquez | D438: Purchasing Manager | E438: Manager | F438: 6 | G438: B | H438: 69 | I438: WKK Technology Queretaro S.A. de C.V. | J438: Software IT | K438: Querétaro, Querétaro, Mexico | L438: wkkintl.com | M438: https://www.linkedin.com/in/everardo-arbey-reyes-marquez-5ab71780/
A439: Chad Spangler | B439: Chad | C439: Spangler | D439: Global Sourcing Manager, Strategic Manufacturing | E439: Manager | F439: 6 | G439: B | H439: 69 | I439: Woodstream Corporation | J439: Software IT | K439: Hummelstown, Pennsylvania, United States | L439: woodstream.com | M439: https://www.linkedin.com/in/chad-spangler-6b40aa47/
A440: Mauricio Seañez | B440: Mauricio | C440: Seañez | D440: Strategic Procurement/Sourcing Manager | E440: Manager | F440: 6 | G440: B | H440: 69 | I440: Xylem | J440: Software IT | K440: Dayton, Ohio, United States | L440: jimseekamp.com | M440: https://www.linkedin.com/in/mauricio-seañez-408a32110/
A441: D Senthil Nathan | B441: D | C441: Nathan | D441: Senior Procurement Manager | E441: Manager | F441: 6 | G441: B | H441: 69 | I441: Yield Engineering Systems | J441: Software IT | K441: Coimbatore, Tamil Nadu, India | L441: yes.tech | M441: https://www.linkedin.com/in/d-senthil-nathan-b62341b8/
A442: Dennis J. Cruz | B442: Dennis | C442: Cruz | D442: Purchasing Manager | E442: Manager | F442: 6 | G442: B | H442: 69 | I442: Zhongding Group | J442: Software IT | K442: Brighton, Michigan, United States | L442: zhongdinggroup.com | M442: https://www.linkedin.com/in/dennis-j-cruz-7a27519/
A443: Luis S. | B443: Luis | C443: S. | D443: Senior Strategic Sourcing Manager | E443: Manager | F443: 6 | G443: B | H443: 69 | I443: Zoox | J443: Software IT | K443: San Mateo, California, United States | L443: zoox.com | M443: https://www.linkedin.com/in/luisfe13/
A444: Sudhan Rajkumar (Raj) Natarajan | B444: Sudhan | C444: Natarajan | D444: Strategic Sourcing Manager | E444: Manager | F444: 6 | G444: B | H444: 69 | I444: Zoox | J444: Software IT | K444: United States, United States | L444: zoox.com | M444: https://www.linkedin.com/in/sudhan-rajkumar-05b57496/
A445: Hongxia Yang | B445: Hongxia | C445: Yang | D445: Software Engineer Tech Lead Manager | E445: Manager | F445: 6 | G445: C | H445: 34 | I445: AMD | J445: Software IT | K445: New York, New York, United States | L445: amd.com | M445: https://www.linkedin.com/in/hongxia-yang-688b0319/
A446: George Lo | B446: George | C446: Lo | D446: Staff Software Engineer / Engineering Manager | E446: Manager | F446: 6 | G446: C | H446: 34 | I446: Apple | J446: Software IT | K446: San Francisco Bay Area | L446: apple.com | M446: https://www.linkedin.com/in/twgeolo/
A447: VICTOR G. | B447: Victor | C447: G. | D447: Technical Program Manager | Product Engineer | SQE (CIS, VCSEL) | E447: Manager | F447: 6 | G447: C | H447: 49 | I447: Apple | J447: Software IT | K447: San Diego, California, United States | L447: apple.com | M447: https://www.linkedin.com/in/victor-getman/
A448: Deborah Ybarra | B448: Deborah | C448: Ybarra | D448: Quality Manager/ Senior Quality Engineer | E448: Manager | F448: 6 | G448: C | H448: 49 | I448: Batesville | J448: Software IT | K448: Greensburg, Indiana, United States | L448: batesville.com | M448: https://www.linkedin.com/in/deborah-ybarra-b679996a/
A449: Adrian Krause | B449: Adrian | C449: Krause | D449: Quality Engineer/Manager | E449: Manager | F449: 6 | G449: C | H449: 49 | I449: Cinco Engineering (Pty) Ltd | J449: Software IT | K449: Cape Town, Western Cape, South Africa | L449: 3cmetal.com | M449: https://www.linkedin.com/in/adrian-krause-a4175a7a/
... A451: Anwin Francis | B451: Anwin | C451: Francis | D451: Snr. Quality Assurance Manager (till date); Manager (5 years); Asst Manager & SQE (2 years each) | E451: Manager | F451: 6 | G451: C | H451: 49 | I451: ENNOVI | J451: Software IT | K451: Batam, Riau Islands, Indonesia | L451: ennovi.com | M451: https://www.linkedin.com/in/anwinfrancis/
A452: Nilesh Desale | B452: Nilesh | C452: Desale | D452: Sr. Manager Corporate Purchase - SQE (BIW & Body Exterior ) | E452: Manager | F452: 6 | G452: C | H452: 49 | I452: Fiat India Automobile Private Limited. Ranjangaon. | J452: Software IT | K452: Pune District, Maharashtra, India | M452: https://www.linkedin.com/in/nilesh-desale-a3a2a1b5/
A453: Haleigh R. | B453: Haleigh | C453: R. | D453: Quality Engineer II - Trusted Advisor to Quality Operations Manager | E453: Manager | F453: 6 | G453: C | H453: 49 | I453: Guerbet | J453: Software IT | K453: Raleigh, North Carolina, United States | L453: guerbet.com | M453: https://www.linkedin.com/in/haleighrrp/
A454: Hédel Nuñez Bolívar | B454: Hédel | C454: Bolívar | D454: Staff Software Engineer / IT Manager | E454: Manager | F454: 6 | G454: C | H454: 34 | I454: KDK Automotive Czech, s.r.o. | J454: Software IT | K454: Plzeň, Czechia | L454: knamdoprace.cz | M454: https://www.linkedin.com/in/hedelnb/
A455: John Joseph Latshaw | B455: John | C455: Latshaw | D455: Manager, Applications - Epic Security & Software Quality Assurance | E455: Manager | F455: 6 | G455: C | H455: 49 | I455: MemorialCare | J455: Software IT | K455: Cypress, California, United States | L455: memorialcare.org | M455: https://www.linkedin.com/in/joelatshaw/
A456: KS Sheng | B456: KS | C456: Sheng | D456: SDE Site Manager | E456: Manager | F456: 6 | G456: C | H456: 34 | I456: Motorola Mobility (a Lenovo Company) | J456: Software IT | K456: Changping District, Beijing, China | L456: motorola.com | M456: https://www.linkedin.com/in/ks-sheng-7668b914/
A457: Daniel Medina | B457: Daniel | C457: Medina | D457: Sr Staff/Manager Software Engineer | E457: Manager | F457: 6 | G457: C | H457: 34 | I457: Qualcomm | J457: Software IT | K457: Cork, County Cork, Ireland | L457: qualcomm.com | M457: https://www.linkedin.com/in/daniel-medina-71419385/
A458: Tripat Kadam | B458: Tripat | C458: Kadam | D458: Assistant Manager - SQA | E458: Manager | F458: 6 | G458: C | H458: 49 | I458: Quantum Energy Limited | J458: Software IT | K458: Greater Hyderabad Area | L458: quantumenergy.in | M458: https://www.linkedin.com/in/tripat-kadam-53b961173/
A459: Nathan Fong | B459: Nathan | C459: Fong | D459: Quality Analyst Engineer (Interim Quality Manager) | E459: Manager | F459: 6 | G459: C | H459: 49 | I459: Thermon | J459: Software IT | K459: New Braunfels, Texas, United States | L459: thermon.com | M459: https://www.linkedin.com/in/nathan-fong-43554111/
A460: Enea Tamarri | B460: Enea | C460: Tamarri | D460: Sr. Manager SQE EMEA Finish Goods and Components | E460: Manager | F460: 6 | G460: C | H460: 49 | I460: Versuni | J460: Software IT | K460: Italy | L460: versuni.com | M460: https://www.linkedin.com/in/enea-tamarri-83a6928/
A461: Susan Breeding | B461: Susan | C461: Breeding | D461: Lead Buyer & Category Strategist / Tooling / Global Indirect Procurement | E461: Lead | F461: 7 | G461: A+ | H461: 90 | I461: AAM - American Axle & Manufacturing | J461: Software IT | K461: Detroit Metropolitan Area | L461: aam.com | M461: https://www.linkedin.com/in/susan-breeding-85100712/
A462: Joaquin B. | B462: Joaquin | C462: B. | D462: Supplier Quality Engineer Lead | E462: Lead | F462: 7 | G462: A | H462: 80 | I462: Fictiv | J462: Software IT | K462: Monterrey, Nuevo León, Mexico | L462: fictiv.com | M462: https://www.linkedin.com/in/joaquinbtc/
A463: Richard Peters | B463: Richard | C463: Peters | D463: Ineos Automotive Lead Supplier Quality Engineer - Grenadier Accessories | E463: Lead | F463: 7 | G463: A | H463: 80 | I463: INEOS Automotive | J463: Software IT | K463: Kenilworth, England, United Kingdom | L463: ineosgrenadier.com | M463: https://www.linkedin.com/in/richard-peters-63094034/
A464: Robert Bayer | B464: Robert | C464: Bayer | D464: Lead Supplier Quality Engineer | E464: Lead | F464: 7 | G464: A | H464: 80 | I464: Milacron | J464: Software IT | K464: Cincinnati, Ohio, United States | L464: milacron.com | M464: https://www.linkedin.com/in/usmachineservicesrobert-bayer/
... A539: Vignesh kumar Ramesh kumar | B539: Vignesh | C539: kumar | D539: Supplier Quality Engineer- Senior | E539: Senior | F539: 8 | G539: B+ | H539: 78 | I539: Knorr-Bremse AG | J539: Software IT | K539: Greater Chicago Area | L539: knorr-bremse.com | M539: https://www.linkedin.com/in/vignesh-kumar-ramesh-kumar-520b5448/
A540: Rahul Mishra | B540: Rahul | C540: Mishra | D540: Senior supplier Quality Engineer | E540: Senior | F540: 8 | G540: B+ | H540: 78 | I540: Linamar Corporation | J540: Software IT | K540: Dewas, Madhya Pradesh, India | M540: https://www.linkedin.com/in/rahul-mishra-6b6b54141/
A541: David Allen Wong | B541: David | C541: Wong | D541: Senior MTS Supplier Quality Engineer | E541: Senior | F541: 8 | G541: B+ | H541: 78 | I541: Maxim Integrated | J541: Software IT | K541: San Jose, California, United States | L541: maximintegrated.com | M541: https://www.linkedin.com/in/davidallenwong/
...

Sheet Other
A1: Full Name | B1: First Name | C1: Last Name | D1: Job Title | E1: Seniority Level | F1: Seniority Rank | G1: Lead Score | H1: Opportunity Score | I1: Company Name | J1: Industry | K1: Location | L1: Company Domain | M1: LinkedIn Profile | N1: Phone | O1: Email/Gmail | P1: Follow Up 1 | Q1: Follow Up 2 | R1: Follow Up 3 | S1: Follow Up 4 | T1: Follow Up 5 | U1: Email 1 | V1: Email 2 | W1: Email 3 | X1: Email 4 | Y1: Email 5 | Z1: Cold Call 1 | AA1: Cold Call 2 | AB1: Cold Call 3 | AC1: Meeting | AD1: RFQ | AE1: Quote | AF1: Won | AG1: Lost | AH1: Outcome Status | AI1: Rejection Reason | AJ1: Interest Reason | AK1: Notes | AL1: First Contact | AM1: Last Contact | AN1: Next Follow-up
A2: Ricardo Borsari | B2: Ricardo | C2: Borsari | D2: Chief Operating Officer | Chief Procurement Officer | C-Level | E2: C-Level | F2: 1 | G2: A | H2: 85 | I2: ABG Corp | J2: Other | K2: Campinas, São Paulo, Brazil | L2: abgbrasil.com | M2: https://www.linkedin.com/in/ricardo-borsari-3233751a/
A3: Mihir Pandya | B3: Mihir | C3: Pandya | D3: Chief Procurement Officer | E3: C-Level | F3: 1 | G3: A | H3: 85 | I3: APAGCoSyst Electronic Control Systems | J3: Other | K3: Gurugram, Haryana, India | L3: apagcosyst.com | M3: https://www.linkedin.com/in/mihir-pandya-4a101217/
A4: Amiya Verma | B4: Amiya | C4: Verma | D4: Chief Procurement Officer | E4: C-Level | F4: 1 | G4: A | H4: 85 | I4: ARISE IIP | J4: Other | K4: Mumbai, Maharashtra, India | L4: ariseiip.com | M4: https://www.linkedin.com/in/amiya-verma-6091a1b/
A5: SUMANTO BHANDARI | B5: Sumanto | C5: Bhandari | D5: President & Chief Procurement Officer (CPO) | E5: C-Level | F5: 1 | G5: A | H5: 85 | I5: Finolex Industries Ltd | J5: Other | K5: Mumbai, Maharashtra, India | L5: finolexpipes.com | M5: https://www.linkedin.com/in/sumanto-bhandari-0142ba9/
A6: Lola Kokila | B6: Lola | C6: Kokila | D6: Executive Business Procurement Manager | E6: Executive | F6: 3 | G6: B+ | H6: 79 | I6: Challenge Power Transmission Plc | J6: Other | K6: Zhejiang, China | L6: challengept.com | M6: https://www.linkedin.com/in/lola-kokila-1072b241/
A7: Jesús Alvarado | B7: Jesús | C7: Alvarado | D7: Managing Director/Country Sourcing Manager - Idex Mexico | E7: Director | F7: 4 | G7: A | H7: 83 | I7: IDEX Corporation | J7: Other | K7: Monterrey, Nuevo León, Mexico | L7: idexcorp.com | M7: https://www.linkedin.com/in/jesusgalvarado/
A8: Pankaj Mane | B8: Pankaj | C8: Mane | D8: Procurement Manager (Head of Procurement) | E8: Head | F8: 5 | G8: A | H8: 81 | I8: Merino Group | J8: Other | K8: Vadodara, Gujarat, India | L8: merinolaminates.com | M8: https://www.linkedin.com/in/pankaj-mane-22838022/
A9: Mounesh Allolikar | B9: Mounesh | C9: Allolikar | D9: Purchasing Manager (CAPEX-Tooling and Investment )Domestics and Offshoring | E9: Manager | F9: 6 | G9: A+ | H9: 100 | I9: Antolin | J9: Other | K9: Pune, Maharashtra, India | L9: antolin.com | M9: https://www.linkedin.com/in/mounesh-allolikar-cipp-b50299116/
A10: Oscar Salamanca | B10: Oscar | C10: Salamanca | D10: Raw Materials Procurement Manager - Aluminum & Plastic | E10: Manager | F10: 6 | G10: A+ | H10: 100 | I10: Bocar | J10: Other | K10: Toluca, México, Mexico | L10: bocar.com | M10: https://www.linkedin.com/in/oscar-salamanca-0526b65b/
A11: Nicolas Teixeira | B11: Nicolas | C11: Teixeira | D11: Regional Purchasing Manager - Plastic Bottles & Resins - Europe | E11: Manager | F11: 6 | G11: A+ | H11: 100 | I11: Henkel | J11: Other | K11: Düsseldorf, North Rhine-Westphalia, Germany | L11: henkel.com | M11: https://www.linkedin.com/in/nicolas-teixeira-41a74360/
A12: Ekin Selen Yagan | B12: Ekin | C12: Yagan | D12: Sourcing Manager-Plastic Interior | E12: Manager | F12: 6 | G12: A+ | H12: 100 | I12: Scania Group | J12: Other | K12: Stockholm County, Sweden | L12: scania.com | M12: https://www.linkedin.com/in/ekinselenyagan/
A13: Carlos Eduardo Aguirre González | B13: Carlos | C13: González | D13: Sourcing Manager - Plastics | E13: Manager | F13: 6 | G13: A+ | H13: 100 | I13: The Toro Company | J13: Other | K13: Monterrey, Nuevo León, Mexico | L13: thetorocompany.com | M13: https://www.linkedin.com/in/ceaguirreg/
... A26: Viktoriia Koshevarova | B26: Viktoriia | C26: Koshevarova | D26: Senior Sourcing Manager (Global Indirect Procurement) | E26: Manager | F26: 6 | G26: B+ | H26: 79 | I26: Amway ESAN | J26: Other | K26: Cracow, Małopolskie, Poland | L26: amwayglobal.com | M26: https://www.linkedin.com/in/viktoriia-koshevarova-0a25a08/
A27: Michelangelo Olivares | B27: Michelangelo | C27: Olivares | D27: Procurement Manager | E27: Manager | F27: 6 | G27: B+ | H27: 79 | I27: Analog Devices Malaysia | J27: Other | K27: Penang, Malaysia | M27: https://www.linkedin.com/in/michelangelo-olivares-26689428/
A28: Jimmy Huang | B28: Jimmy | C28: Huang | D28: Strategic Sourcing Manager | E28: Manager | F28: 6 | G28: B+ | H28: 79 | I28: Apple | J28: Other | K28: Shanghai, China | L28: apple.com | M28: https://www.linkedin.com/in/jimmy-huang-6872b79/
A29: Prashant Awadhiya | B29: Prashant | C29: Awadhiya | D29: Global Supply and Sourcing Manager | Corporate India Procurement | E29: Manager | F29: 6 | G29: B+ | H29: 79 | I29: Apple | J29: Other | K29: Bengaluru, Karnataka, India | L29: apple.com | M29: https://www.linkedin.com/in/prashant-awadhiya-823a4044/
A30: 尹希孟 Ximeng YIN (Simon) | B30: Ximeng | C30: YIN | D30: Global Strategic Sourcing Manager | E30: Manager | F30: 6 | G30: B+ | H30: 79 | I30: Apple | J30: Other | K30: Shanghai, China | L30: apple.com | M30: https://www.linkedin.com/in/尹希孟-ximeng-yin-simon-62051b103/
A31: Ahmed Osman CISCP - CISCM | B31: Ahmed | C31: CISCM | D31: Local Procurement Manager | E31: Manager | F31: 6 | G31: B+ | H31: 79 | I31: Arab Steel Fabrication ASF - El Sewedy Industries | J31: Other | K31: القاهرة قسم مصر الجديدة مصر | L31: asf.com.eg | M31: https://www.linkedin.com/in/ahmed-osman-87211b3b/
A32: uğur oral | B32: Uğur | C32: Oral | D32: (SRM) Department purchasing manager | E32: Manager | F32: 6 | G32: B+ | H32: 79 | I32: ARÇELİK-LG | J32: Other | K32: Greater Istanbul | M32: https://www.linkedin.com/in/u%c4%9fur-oral-112615213/
A33: Kevin Fernandes | B33: Kevin | C33: Fernandes | D33: Purchasing Manager | E33: Manager | F33: 6 | G33: B+ | H33: 79 | I33: Asian Paints PPG Pvt. Ltd. | J33: Other | K33: Mumbai, Maharashtra, India | M33: https://www.linkedin.com/in/kevin-fernandes-54935436/
A34: Sergio Bazzani | B34: Sergio | C34: Bazzani | D34: Sourcing/Purchasing Manager | E34: Manager | F34: 6 | G34: B+ | H34: 79 | I34: Auveco, LLC | J34: Other | K34: Greater Orlando | L34: auveco.com | M34: https://www.linkedin.com/in/sergiotorobazzani/
A35: Deepak Rawat | B35: Deepak | C35: Rawat | D35: Strategic Sourcing Manager | E35: Manager | F35: 6 | G35: B+ | H35: 79 | I35: Bajaj Auto Ltd | J35: Other | K35: Pune District, Maharashtra, India | L35: bajajauto.com | M35: https://www.linkedin.com/in/deepak-rawat-5a677157/
A36: Jens Hejberg | B36: Jens | C36: Hejberg | D36: Senior procurement manager | E36: Manager | F36: 6 | G36: B+ | H36: 79 | I36: Bang & Olufsen | J36: Other | K36: Central Denmark Region, Denmark | L36: bang-olufsen.com | M36: https://www.linkedin.com/in/jens-hejberg-b8ab92/
A37: Akash Deshmukh | B37: Akash | C37: Deshmukh | D37: Assistant Sourcing Manager India | E37: Manager | F37: 6 | G37: B+ | H37: 79 | I37: Barnes | J37: Other | K37: Pune, Maharashtra, India | L37: onebarnes.com | M37: https://www.linkedin.com/in/akash-deshmukh-932b612a/
A38: Kaan Odabaş | B38: Kaan | C38: Odabaş | D38: Procurement Manager | E38: Manager | F38: 6 | G38: B+ | H38: 79 | I38: BASE A.Ş. | J38: Other | K38: Turkey | L38: basestudio.com.tr | M38: https://www.linkedin.com/in/kaanodabas/
A39: Manuel Braipson | B39: Manuel | C39: Braipson | D39: Purchasing Manager | E39: Manager | F39: 6 | G39: B+ | H39: 79 | I39: BEA Sensors Europe | J39: Other | K39: Liège, Walloon Region, Belgium | L39: beasensors.com | M39: https://www.linkedin.com/in/manuel-braipson-72a17261/
A40: Nihat Özkan | B40: Nihat | C40: Özkan | D40: Senior Purchasing Manager | E40: Manager | F40: 6 | G40: B+ | H40: 79 | I40: Beko Global | J40: Other | K40: Greater Istanbul | L40: beko.com | M40: https://www.linkedin.com/in/nihat-ã¶zkan-87835117/
A41: MANGESH DESAI | B41: Mangesh | C41: Desai | D41: Procurement Manager | E41: Manager | F41: 6 | G41: B+ | H41: 79 | I41: Benninger Group | J41: Other | K41: Pune Division, Maharashtra, India | L41: benningergroup.com | M41: https://www.linkedin.com/in/mangesh-desai-b2361ba1/
A42: Nick Sampson | B42: Nick | C42: Sampson | D42: Purchasing Manager | E42: Manager | F42: 6 | G42: B+ | H42: 79 | I42: Bio Services International (BSI) | J42: Other | K42: Belgium | L42: bsi-products.com | M42: https://www.linkedin.com/in/nick-sampson-216a6913/
A43: Artur Walędziński | B43: Artur | C43: Walędziński | D43: Purchasing Manager / Strategic Purchasing Department | E43: Manager | F43: 6 | G43: B+ | H43: 79 | I43: BMZ Poland | J43: Other | K43: Katowice, Śląskie, Poland | L43: bmz-battery.com | M43: https://www.linkedin.com/in/artur-walędziński-a768689b/
A44: Nelson Velazquez | B44: Nelson | C44: Velazquez | D44: Purchasing Manager | E44: Manager | F44: 6 | G44: B+ | H44: 79 | I44: Bosal | J44: Other | K44: Querétaro, Mexico | L44: bosal.com | M44: https://www.linkedin.com/in/nelson-velazquez-35840b56/
A45: Anshul Saraf, B. Com | B45: Anshul | C45: Com | D45: Purchasing Manager | E45: Manager | F45: 6 | G45: B+ | H45: 79 | I45: Brandt Group of Companies | J45: Other | K45: Regina, Saskatchewan, Canada | L45: brandt.ca | M45: https://www.linkedin.com/in/anshulsaraf/
... A47: America Ortiz | B47: America | C47: Ortiz | D47: Procurement Manager | E47: Manager | F47: 6 | G47: B+ | H47: 79 | I47: Bryant Rubber Corporation | J47: Other | K47: Tijuana, Baja California, Mexico | L47: bryantrubber.com | M47: https://www.linkedin.com/in/america-ortiz-849704162/
A48: Patrick Lexér | B48: Patrick | C48: Lexér | D48: Purchasing Manager | E48: Manager | F48: 6 | G48: B+ | H48: 79 | I48: Bulten Hallstahammar AB | J48: Other | K48: Gothenburg, Västra Götaland County, Sweden | M48: https://www.linkedin.com/in/patrick-lexer/
A49: Özcan KALAYCI | B49: Özcan | C49: KALAYCI | D49: Plant Purchasing Manager | E49: Manager | F49: 6 | G49: B+ | H49: 79 | I49: Calderys | J49: Other | K49: Tekirdağ, Turkey | L49: calderys.com | M49: https://www.linkedin.com/in/ã¶zcan-kalayci-64966a52/
A50: Geni Slot | B50: Geni | C50: Slot | D50: Purchasing Manager | E50: Manager | F50: 6 | G50: B+ | H50: 79 | I50: Cavex Holland BV | J50: Other | K50: Haarlem, Noord-Holland, Nederland | L50: cavex.nl | M50: https://www.linkedin.com/in/geni-slot-40280017/
A51: Said Abdelaziz Mohamed Ahmed | B51: Said | C51: Ahmed | D51: Assistant Procurement Manager | E51: Manager | F51: 6 | G51: B+ | H51: 79 | I51: CEER | J51: Other | K51: الرياض السعودية | L51: ceermotors.com | M51: https://www.linkedin.com/in/said-abdelaziz-mohamed-ahmed-67639b36/
A52: Franziska Schulze | B52: Franziska | C52: Schulze | D52: Procurement Manager EMEA | E52: Manager | F52: 6 | G52: B+ | H52: 79 | I52: Clarios | J52: Other | K52: Hannover, Lower Saxony, Germany | L52: clarios.com | M52: https://www.linkedin.com/in/franziska-schulze-171a8595/
A53: Jessin N. | B53: Jessin | C53: N. | D53: Procurement Manager | E53: Manager | F53: 6 | G53: B+ | H53: 79 | I53: Cleveland-Cliffs | J53: Other | K53: Canada | L53: clevelandcliffs.com | M53: https://www.linkedin.com/in/jessin-m-nazeem/
A54: Jorge Serratos | B54: Jorge | C54: Serratos | D54: Sourcing Manager | E54: Manager | F54: 6 | G54: B+ | H54: 79 | I54: Constructora MJS | J54: Other | K54: Zapopan, Jalisco, Mexico | L54: constructoramjs.com | M54: https://www.linkedin.com/in/jorge-serratos-8bb19261/
A55: Jerry Windhorst | B55: Jerry | C55: Windhorst | D55: Senior Sourcing Manager | E55: Manager | F55: 6 | G55: B+ | H55: 79 | I55: Corelle Brands | J55: Other | K55: Greater Chicago Area | L55: corelle.com | M55: https://www.linkedin.com/in/jerry-windhorst-06440317/
A56: Yuvraj Gaikwad | B56: Yuvraj | C56: Gaikwad | D56: Sourcing Manager | E56: Manager | F56: 6 | G56: B+ | H56: 79 | I56: Curtis Instruments | J56: Other | K56: Pune Division, Maharashtra, India | L56: curtisinstruments.com | M56: https://www.linkedin.com/in/yuvraj99/
A57: Kaniz Khadiza | B57: Kaniz | C57: Khadiza | D57: Procurement Manager | E57: Manager | F57: 6 | G57: B+ | H57: 79 | I57: Dabur Bangladesh | J57: Other | K57: Dhaka, Bangladesh | L57: dabur.com | M57: https://www.linkedin.com/in/kaniz-khadiza-a302a14b/
A58: Ahmed Albdrawy | B58: Ahmed | C58: Albdrawy | D58: Sr. Associate purchasing Manager | E58: Manager | F58: 6 | G58: B+ | H58: 79 | I58: Dabur Egypt Ltd | J58: Other | K58: القاهرة القاهرة الجديدة مصر | L58: dabur.com | M58: https://www.linkedin.com/in/ahmed-albdrawy-5a756025/
A59: Reza Bachtiar | B59: Reza | C59: Bachtiar | D59: Procurement Manager | E59: Manager | F59: 6 | G59: B+ | H59: 79 | I59: Daimler Commercial Vehicles Manufacturing Indonesia (DCVMI) | J59: Other | K59: Bandung, West Java, Indonesia | M59: https://www.linkedin.com/in/reza-bachtiar-59a67879/
A60: Bob P. | B60: Bob | C60: P. | D60: Purchasing Manager, Global sourcing for Daimler trucks and buses | E60: Manager | F60: 6 | G60: B+ | H60: 79 | I60: Daimler Truck China | J60: Other | K60: Beijing, China | L60: daimlertruck.com | M60: https://www.linkedin.com/in/bob-p-3448b466/
A61: Carly van de Pol MBA, BSc, CLTD | B61: Carly | C61: BSc | D61: Procurement Manager | E61: Manager | F61: 6 | G61: B+ | H61: 79 | I61: Decibel Cannabis Company | J61: Other | K61: Calgary, Alberta, Canada | L61: decibelcc.com | M61: https://www.linkedin.com/in/carlyvandepol/
A62: Prasanna Sameer | B62: Prasanna | C62: Sameer | D62: Assistant Procurement Manager | E62: Manager | F62: 6 | G62: B+ | H62: 79 | I62: Deconstruct | J62: Other | K62: Krishna, Andhra Pradesh, India | L62: thedeconstruct.in | M62: https://www.linkedin.com/in/prasanna-sameer-3145b8197/
A63: Rohini Kamire | B63: Rohini | C63: Kamire | D63: Global NPI Procurement Manager | E63: Manager | F63: 6 | G63: B+ | H63: 79 | I63: Dentsply Sirona | J63: Other | K63: Germany | L63: dentsplysirona.com | M63: https://www.linkedin.com/in/rohinikamire/
A64: Derya Erden | B64: Derya | C64: Erden | D64: Indirect Procurement Manager | E64: Manager | F64: 6 | G64: B+ | H64: 79 | I64: DEVA Holding A.Ş. | J64: Other | K64: Turkey | L64: deva.com.tr | M64: https://www.linkedin.com/in/derya-erden-253b9683/
A65: Priyanka Chaudhari | B65: Priyanka | C65: Chaudhari | D65: Sourcing Manager | E65: Manager | F65: 6 | G65: B+ | H65: 79 | I65: Dorman Products | J65: Other | K65: Pune Division, Maharashtra, India | L65: dormanproducts.com | M65: https://www.linkedin.com/in/priyanka-chaudhari-b35b837b/
A66: Gustavo Vázquez Sáinz | B66: Gustavo | C66: Sáinz | D66: Global Sourcing Manager Mexico & LATAM / Supply Chain Specialist | E66: Manager | F66: 6 | G66: B+ | H66: 79 | I66: Dover Corporation | J66: Other | K66: Querétaro, Mexico | L66: dovercorporation.com | M66: https://www.linkedin.com/in/gustavo-vazquez-sainz-47624428/
A67: Thiwanka Kannangara | B67: Thiwanka | C67: Kannangara | D67: Procurement Manager | E67: Manager | F67: 6 | G67: B+ | H67: 79 | I67: DPL - Dipped Products PLC | J67: Other | K67: Colombo District, Western Province, Sri Lanka | L67: dplgroup.com | M67: https://www.linkedin.com/in/thiwanka-kannangara-062491138/
A68: Zoran Skundric | B68: Zoran | C68: Skundric | D68: Indirect Procurement Manager | E68: Manager | F68: 6 | G68: B+ | H68: 79 | I68: Dr. Max Srbija | J68: Other | K68: Serbia | L68: drmax.rs | M68: https://www.linkedin.com/in/zoran-skundric-b44ba74/
A69: Murat Ozkam | B69: Murat | C69: Ozkam | D69: Global Senior Purchasing Manager Stamping | E69: Manager | F69: 6 | G69: B+ | H69: 79 | I69: DRiV Incorporated | J69: Other | K69: Istanbul, Istanbul, Türkiye | L69: driv.com | M69: https://www.linkedin.com/in/muratozkam/
A70: Jayme Bernardo | B70: Jayme | C70: Bernardo | D70: Category Procurement Manager | E70: Manager | F70: 6 | G70: B+ | H70: 79 | I70: Dyson | J70: Other | K70: Laguna, Calabarzon, Philippines | L70: dyson.com | M70: https://www.linkedin.com/in/jayme-bernardo-0bba24ab/
A71: Rusydi Hassim | B71: Rusydi | C71: Hassim | D71: Associate Procurement Manager | E71: Manager | F71: 6 | G71: B+ | H71: 79 | I71: Dyson | J71: Other | K71: Johore, Malaysia | L71: dyson.com | M71: https://www.linkedin.com/in/rusydi-hassim-190b1b77/
... A116: Alok Gupta | B116: Alok | C116: Gupta | D116: Sourcing Procurement Manager | E116: Manager | F116: 6 | G116: B+ | H116: 79 | I116: Havells India Ltd | J116: Other | K116: Pune District, Maharashtra, India | L116: havells.com | M116: https://www.linkedin.com/in/alok-gupta-50244a128/
A117: Ahmed El-Nokrashy | B117: Ahmed | C117: El-Nokrashy | D117: Procurement Manager | E117: Manager | F117: 6 | G117: B+ | H117: 79 | I117: Heliophos Coatings | J117: Other | K117: Giza, Al Jizah, Egypt | M117: https://www.linkedin.com/in/ahmed-el-nokrashy-b72183a7/
A118: ALTAYRA COTO CISNEROS | B118: Altayra | C118: Cisneros | D118: Senior Regional Procurement Manager | E118: Manager | F118: 6 | G118: B+ | H118: 79 | I118: Henkel | J118: Other | K118: México, Mexico | L118: henkel.com | M118: https://www.linkedin.com/in/altayra-coto-cisneros-68b24b116/
A119: Gee Young Ng | B119: Gee | C119: Ng | D119: Purchasing Manager | E119: Manager | F119: 6 | G119: B+ | H119: 79 | I119: Henkel | J119: Other | K119: Amsterdam, North Holland, Netherlands | L119: henkel.com | M119: https://www.linkedin.com/in/gee-young-ng-653619b/
A120: Renato Quissak | B120: Renato | C120: Quissak | D120: Senior Procurement Manager | E120: Manager | F120: 6 | G120: B+ | H120: 79 | I120: Henkel | J120: Other | K120: Singapore, Singapore | L120: henkel.com | M120: https://www.linkedin.com/in/renato-quissak-25774637/
A121: Severin Janßen | B121: Severin | C121: Janßen | D121: Procurement Manager | E121: Manager | F121: 6 | G121: B+ | H121: 79 | I121: Henkel | J121: Other | K121: Düsseldorf, Nordrhein-Westfalen, Deutschland | L121: henkel.com | M121: https://www.linkedin.com/in/severin-jan%2525c3%25259fen-155372b8/
A122: Yessine OUERTANI | B122: Yessine | C122: OUERTANI | D122: Regional Purchasing Manager - Australia & New Zealand | E122: Manager | F122: 6 | G122: B+ | H122: 79 | I122: Henkel | J122: Other | K122: Chatswood West, New South Wales, Australia | L122: henkel.com | M122: https://www.linkedin.com/in/yessine-ouertani-561425126/
A123: Ajay Singh Shekhawat | B123: Ajay | C123: Shekhawat | D123: Sourcing Manager | E123: Manager | F123: 6 | G123: B+ | H123: 79 | I123: Hero MotoCorp | J123: Other | K123: Jaipur, Rajasthan, India | L123: heromotocorp.com | M123: https://www.linkedin.com/in/ajay-singh-shekhawat-904bb6166/
A124: Rahul Shinde | B124: Rahul | C124: Shinde | D124: Strategic Sourcing Manager | E124: Manager | F124: 6 | G124: B+ | H124: 79 | I124: Hero MotoCorp | J124: Other | K124: Pune, Maharashtra, India | L124: heromotocorp.com | M124: https://www.linkedin.com/in/rahul-shinde-95596978/
A125: Anwar Rana CIPS, MBA, CPP | B125: Anwar | C125: Rana | D125: Purchasing Manager | E125: Manager | F125: 6 | G125: B+ | H125: 79 | I125: High Liner Foods | J125: Other | K125: Canada, Canada | L125: highlinerfoods.com | M125: https://www.linkedin.com/in/anwarrana/
A126: Uday Patil | B126: Uday | C126: Patil | D126: Manager Procurement and Vendor Development | E126: Manager | F126: 6 | G126: B+ | H126: 79 | I126: Himalaya Wellness Company | J126: Other | K126: Bengaluru, Karnataka, India | L126: himalayawellness.in | M126: https://www.linkedin.com/in/uday-patil-94a63b10/
A127: Tanuj Chhabra | B127: Tanuj | C127: Chhabra | D127: Manager /Sr. Buyer /Lead residue sales | E127: Manager | F127: 6 | G127: B+ | H127: 79 | I127: Hindustan Zinc | J127: Other | K127: Udaipur, Rajasthan, India | L127: hzlindia.com | M127: https://www.linkedin.com/in/tanuj-chhabra-15360836/
A128: Monica Lugo Hernández | B128: Monica | C128: Hernández | D128: Purchasing Manager | E128: Manager | F128: 6 | G128: B+ | H128: 79 | I128: HIROTEC TOOLING DE MEXICO | J128: Other | K128: Guanajuato, Mexico | L128: hirotectooling.com | M128: https://www.linkedin.com/in/monica-lugo-hernández-376220a0/
A129: 罗强 | B129: 强 | C129: 罗 | D129: Sourcing Manager | E129: Manager | F129: 6 | G129: B+ | H129: 79 | I129: Holley | J129: Other | K129: Shanghai, China | L129: holley.com | M129: https://www.linkedin.com/in/johnson-luo-ab230213/
... A132: Jessica Ivonne Díaz | B132: Jessica | C132: Díaz | D132: Sourcing Manager | E132: Manager | F132: 6 | G132: B+ | H132: 79 | I132: Hubbell Incorporated | J132: Other | K132: Mexico, Mexico | L132: hubbell.com | M132: https://www.linkedin.com/in/jessica-ivonne-díaz-84a581105/
A133: VIKAS JAIN | B133: Vikas | C133: Jain | D133: Purchasing Manager | E133: Manager | F133: 6 | G133: B+ | H133: 79 | I133: India Automobile Industry | J133: Other | K133: Bengaluru, Karnataka, India | M133: https://www.linkedin.com/in/vikas-jain-53143463/
A134: Evelyn Morris | B134: Evelyn | C134: Morris | D134: Sr. Sourcing Manager | E134: Manager | F134: 6 | G134: B+ | H134: 79 | I134: Integer Holdings Corporation | J134: Other | K134: Dallas-Fort Worth Metroplex | L134: integer.net | M134: https://www.linkedin.com/in/evelyn-morris-a4b153252/
A135: Wynanda de Vries | B135: Wynanda | C135: de Vries | D135: Global Procurement Manager | E135: Manager | F135: 6 | G135: B+ | H135: 79 | I135: Intergas Verwarming B.V. | J135: Other | K135: Coevorden, Drenthe, Nederland | L135: intergas-verwarming.nl | M135: https://www.linkedin.com/in/wynanda-de-vries-14510958/
A136: Carmela Roa, CPP | B136: Carmela | C136: Roa | D136: Procurement Manager | E136: Manager | F136: 6 | G136: B+ | H136: 79 | I136: Interphil Laboratories Incorporated | J136: Other | K136: Philippines, Philippines | L136: interphil-lab.com | M136: https://www.linkedin.com/in/carmela-roa-cpp-a719133b/
A137: Visa Seinelä | B137: Visa | C137: Seinelä | D137: Sourcing Manager | E137: Manager | F137: 6 | G137: B+ | H137: 79 | I137: IXI | J137: Other | K137: Helsinki, Uusimaa, Finland | L137: ixieyewear.com | M137: https://www.linkedin.com/in/visaseinela/
A138: WC Lim | B138: WC | C138: Lim | D138: New Product Sourcing Manager | E138: Manager | F138: 6 | G138: B+ | H138: 79 | I138: Jabil | J138: Other | K138: 中国 广东省 广州 | L138: jabil.com | M138: https://www.linkedin.com/in/wc-lim-86-13814238410-a9a92989/
A139: Radhey Tripathi | B139: Radhey | C139: Tripathi | D139: Assistant Sourcing Manager | E139: Manager | F139: 6 | G139: B+ | H139: 79 | I139: JBM Group | J139: Other | K139: Faridabad, Haryana, India | L139: jbmgroup.com | M139: https://www.linkedin.com/in/radhey-tripathi-277531165/
A140: GUNJAN PATEL | B140: Gunjan | C140: Patel | D140: Procurement Manager (SCM) | E140: Manager | F140: 6 | G140: B+ | H140: 79 | I140: Jindal Advanced Materials | J140: Other | K140: New Delhi, Delhi, India | L140: jindaladvancedmaterials.com | M140: https://www.linkedin.com/in/patel-gunjan/
A141: Vinay Singh Lather | B141: Vinay | C141: Lather | D141: Procurement Manager | E141: Manager | F141: 6 | G141: B+ | H141: 79 | I141: Jindal Stainless | J141: Other | K141: Hisar, Haryana, India | L141: jindalstainless.com | M141: https://www.linkedin.com/in/vnlather/
A142: Dhairyasheel Kale | B142: Dhairyasheel | C142: Kale | D142: Costing and Procurement Manager | E142: Manager | F142: 6 | G142: B+ | H142: 79 | I142: JLR | J142: Other | K142: Pune, Maharashtra, India | L142: jlr.com | M142: https://www.linkedin.com/in/dhairyasheel-kale-47751178/
A143: Thamíris Grandin | B143: Thamíris | C143: Grandin | D143: Procurement Manager Latam: Accounts Payable Transformation Project - S/4HANA - Project Manager | E143: Manager | F143: 6 | G143: B+ | H143: 79 | I143: Johnson & Johnson | J143: Other | K143: São Paulo, São Paulo, Brazil | L143: jnj.com | M143: https://www.linkedin.com/in/tham%c3%adris-grandin-a3bbb050/
A144: Marcelo Kovaliski | B144: Marcelo | C144: Kovaliski | D144: Sr. Procurement Manager Americas | E144: Manager | F144: 6 | G144: B+ | H144: 79 | I144: Joyson Safety Systems | J144: Other | K144: Brazil | L144: joysonsafety.com | M144: https://www.linkedin.com/in/marcelo-kovaliski/
A145: Tatyaso Thorat | B145: Tatyaso | C145: Thorat | D145: Senior Sourcing Manager | E145: Manager | F145: 6 | G145: B+ | H145: 79 | I145: Kalmar | J145: Other | K145: Pune, Maharashtra, India | L145: kalmarglobal.com | M145: https://www.linkedin.com/in/tatyaso-thorat-cpsm-17245235/
... A248: Ritesh Jha ,PMP | B248: Ritesh | C248: Jha | D248: Project Procurement Manager | E248: Manager | F248: 6 | G248: B+ | H248: 79 | I248: SMS group India | J248: Other | K248: South Delhi, Delhi, India | L248: sms-group.com | M248: https://www.linkedin.com/in/ritesh-jha-pmp®-a5081561/
A249: Judicaël POTE | B249: Judicaël | C249: POTE | D249: Indirect Sourcing & Procurement Manager | E249: Manager | F249: 6 | G249: B+ | H249: 79 | I249: Société africaine de plantations d'hévéas | J249: Other | K249: Côte d'Ivoire | M249: https://www.linkedin.com/in/judica%c3%abl-pote-2b205754/
A250: Edva Kaizer | B250: Edva | C250: Kaizer | D250: Global Direct Procurement Manager | E250: Manager | F250: 6 | G250: B+ | H250: 79 | I250: SodaStream International, Ltd. | J250: Other | K250: Israel | L250: sodastream.com | M250: https://www.linkedin.com/in/edva-kaizer-550958ab/
A251: Ricardo Martínez, MBA | B251: Ricardo | C251: Martínez | D251: Strategic Sourcing Manager | E251: Manager | F251: 6 | G251: B+ | H251: 79 | I251: Stanley Black & Decker, Inc. | J251: Other | K251: Monterrey, Nuevo León, México | L251: stanleyblackanddecker.com | M251: https://www.linkedin.com/in/ricardo-martínez-mba-77466b12b/
A252: Sreeram Ragupathy Iyer- (CIPP),Six Sigma | B252: Sreeram | C252: Sigma | D252: Procurement Manager | E252: Manager | F252: 6 | G252: B+ | H252: 79 | I252: TAKRAF Group | J252: Other | K252: India | L252: takraf.com | M252: https://www.linkedin.com/in/sreeram-ragupathy-iyer-cipp®-six-sigma-46957638/
A253: Dnyaneshwar Mahale | B253: Dnyaneshwar | C253: Mahale | D253: Senior Purchasing Manager | E253: Manager | F253: 6 | G253: B+ | H253: 79 | I253: TATA AutoComp Systems Ltd | J253: Other | K253: Pune/Pimpri-Chinchwad Area, India | L253: tataautocomp.com | M253: https://www.linkedin.com/in/dnyaneshwar-mahale-81ba3959/
A254: Naresh Setti | B254: Naresh | C254: Setti | D254: Manager-Procurement | E254: Manager | F254: 6 | G254: B+ | H254: 79 | I254: Tata Motors | J254: Other | K254: Maharashtra, India | L254: tatamotors.com | M254: https://www.linkedin.com/in/naresh-setti-00a980a/
A255: Amelie Beauger | B255: Amelie | C255: Beauger | D255: Global Purchasing Manager | E255: Manager | F255: 6 | G255: B+ | H255: 79 | I255: Tesca Group | J255: Other | K255: France, France | L255: tescagroup.com | M255: https://www.linkedin.com/in/ameliebeauger/
A256: Wilson Ding | B256: Wilson | C256: Ding | D256: Senior Purchasing Manager, North America | E256: Manager | F256: 6 | G256: B+ | H256: 79 | I256: THK Rhythm Automotive | J256: Other | K256: Canada | L256: thk-rhythm-auto.com | M256: https://www.linkedin.com/in/wilson-ding-a2959533/
A257: Aloysio PIZARRO Jr | B257: Aloysio | C257: PIZARRO | D257: Purchasing Manager TI Automotive - South America | E257: Manager | F257: 6 | G257: B+ | H257: 79 | I257: TI Automotive | J257: Other | K257: São José dos Campos, São Paulo, Brazil | L257: tifluidsystems.com | M257: https://www.linkedin.com/in/aloysio-pizarro-jr-9b3ba713/
A258: David Carrió | B258: David | C258: Carrió | D258: Purchasing Manager FCS Spain | E258: Manager | F258: 6 | G258: B+ | H258: 79 | I258: TI Automotive | J258: Other | K258: Vilassar de Dalt, Catalonia, Spain | L258: tifluidsystems.com | M258: https://www.linkedin.com/in/david-carri%c3%b3-47b49a19/
A259: Gerardo Casas | B259: Gerardo | C259: Casas | D259: Strategic Sourcing Manager | E259: Manager | F259: 6 | G259: B+ | H259: 79 | I259: TIDI Products | J259: Other | K259: Tijuana, Baja California, Mexico | L259: tidiproducts.com | M259: https://www.linkedin.com/in/gerardocasasv/
A260: Javaid Iqbal (MBA, Supply Chain Certified) | B260: Javaid | C260: Iqbal | D260: Procurement Manager | E260: Manager | F260: 6 | G260: B+ | H260: 79 | I260: Treet Corp | J260: Other | K260: Lahore District, Punjab, Pakistan | L260: treetcorp.com | M260: https://www.linkedin.com/in/javaidiqbal1/
A261: Ayo Alase Bsc-Economics, MBA, ACA, DFCILSCM, MCIPSM, MCISN | B261: Ayo | C261: MCISN | D261: Senior Procurement Manager | E261: Manager | F261: 6 | G261: B+ | H261: 79 | I261: Tropical General Investments (TGI) Group | J261: Other | K261: Nigeria | L261: clicktgi.net | M261: https://www.linkedin.com/in/ayo-alase/
...

Sheet Dashboard
A1: Manufacturing Prospecting CRM V4 - Dashboard
A3: Industry | B3: Total Leads | C3: Follow Up 1 | D3: Follow Up 2 | E3: Follow Up 3 | F3: Follow Up 4 | G3: Follow Up 5 | H3: Email 1 | I3: Email 2 | J3: Email 3 | K3: Email 4 | L3: Email 5 | M3: Cold Call 1 | N3: Cold Call 2 | O3: Cold Call 3 | P3: Meeting | Q3: RFQ | R3: Quote | S3: Won | T3: Lost | U3: Blacklist | V3: Prospectar Después | W3: Activity Rate | X3: Meeting Rate | Y3: RFQ Rate | Z3: Quote Rate | AA3: Win Rate | AB3: Blacklist Rate | AC3: Future Rate
A4: Automotive | B4: =COUNTA(Automotive!$A$2:$A$5000) -> 922 | C4: =COUNTIF(Automotive!$P$2:$P$5000,"<>") -> 1 | D4: =COUNTIF(Automotive!$Q$2:$Q$5000,"<>") -> 0 | E4: =COUNTIF(Automotive!$R$2:$R$5000,"<>") -> 0 | F4: =COUNTIF(Automotive!$S$2:$S$5000,"<>") -> 0 | G4: =COUNTIF(Automotive!$T$2:$T$5000,"<>") -> 0 | H4: =COUNTIF(Automotive!$U$2:$U$5000,"<>") -> 0 | I4: =COUNTIF(Automotive!$V$2:$V$5000,"<>") -> 0 | J4: =COUNTIF(Automotive!$W$2:$W$5000,"<>") -> 0 | K4: =COUNTIF(Automotive!$X$2:$X$5000,"<>") -> 0 | L4: =COUNTIF(Automotive!$Y$2:$Y$5000,"<>") -> 0 | M4: =COUNTIF(Automotive!$Z$2:$Z$5000,"<>") -> 0 | N4: =COUNTIF(Automotive!$AA$2:$AA$5000,"<>") -> 0 | O4: =COUNTIF(Automotive!$AB$2:$AB$5000,"<>") -> 0 | P4: =COUNTIF(Automotive!$AC$2:$AC$5000,"<>") -> 0 | Q4: =COUNTIF(Automotive!$AD$2:$AD$5000,"<>") -> 1 | R4: =COUNTIF(Automotive!$AE$2:$AE$5000,"<>") -> 0 | S4: =MAX(COUNTIF(Automotive!$AH$2:$AH$5000,"Won"),COUNTIF(Automotive!$AF$2:$AF$5000,"<>")) -> 1 | T4: =MAX(COUNTIF(Automotive!$AH$2:$AH$5000,"Lost"),COUNTIF(Automotive!$AG$2:$AG$5000,"<>")) -> 0 | U4: =COUNTIF(Automotive!$AH$2:$AH$5000,"Blacklist") -> 0 | V4: =COUNTIF(Automotive!$AH$2:$AH$5000,"Prospectar Después") -> 0 | W4: =IFERROR(MAX(C4,H4,M4)/$B4,0) -> 0.0010845987 | X4: =IFERROR(P4/$B4,0) -> 0 | Y4: =IFERROR(Q4/$B4,0) -> 0.0010845987 | Z4: =IFERROR(R4/$B4,0) -> 0 | AA4: =IFERROR(S4/$B4,0) -> 0.0010845987 | AB4: =IFERROR(U4/$B4,0) -> 0 | AC4: =IFERROR(V4/$B4,0) -> 0
A5: Pharmaceutical | B5: =COUNTA(Pharmaceutical!$A$2:$A$5000) -> 149 | C5: =COUNTIF(Pharmaceutical!$P$2:$P$5000,"<>") -> 0 | D5: =COUNTIF(Pharmaceutical!$Q$2:$Q$5000,"<>") -> 0 | E5: =COUNTIF(Pharmaceutical!$R$2:$R$5000,"<>") -> 0 | F5: =COUNTIF(Pharmaceutical!$S$2:$S$5000,"<>") -> 0 | G5: =COUNTIF(Pharmaceutical!$T$2:$T$5000,"<>") -> 0 | H5: =COUNTIF(Pharmaceutical!$U$2:$U$5000,"<>") -> 0 | I5: =COUNTIF(Pharmaceutical!$V$2:$V$5000,"<>") -> 0 | J5: =COUNTIF(Pharmaceutical!$W$2:$W$5000,"<>") -> 0 | K5: =COUNTIF(Pharmaceutical!$X$2:$X$5000,"<>") -> 0 | L5: =COUNTIF(Pharmaceutical!$Y$2:$Y$5000,"<>") -> 0 | M5: =COUNTIF(Pharmaceutical!$Z$2:$Z$5000,"<>") -> 0 | N5: =COUNTIF(Pharmaceutical!$AA$2:$AA$5000,"<>") -> 0 | O5: =COUNTIF(Pharmaceutical!$AB$2:$AB$5000,"<>") -> 0 | P5: =COUNTIF(Pharmaceutical!$AC$2:$AC$5000,"<>") -> 0 | Q5: =COUNTIF(Pharmaceutical!$AD$2:$AD$5000,"<>") -> 0 | R5: =COUNTIF(Pharmaceutical!$AE$2:$AE$5000,"<>") -> 0 | S5: =MAX(COUNTIF(Pharmaceutical!$AH$2:$AH$5000,"Won"),COUNTIF(Pharmaceutical!$AF$2:$AF$5000,"<>")) -> 0 | T5: =MAX(COUNTIF(Pharmaceutical!$AH$2:$AH$5000,"Lost"),COUNTIF(Pharmaceutical!$AG$2:$AG$5000,"<>")) -> 0 | U5: =COUNTIF(Pharmaceutical!$AH$2:$AH$5000,"Blacklist") -> 0 | V5: =COUNTIF(Pharmaceutical!$AH$2:$AH$5000,"Prospectar Después") -> 0 | W5: =IFERROR(MAX(C5,H5,M5)/$B5,0) -> 0 | X5: =IFERROR(P5/$B5,0) -> 0 | Y5: =IFERROR(Q5/$B5,0) -> 0 | Z5: =IFERROR(R5/$B5,0) -> 0 | AA5: =IFERROR(S5/$B5,0) -> 0 | AB5: =IFERROR(U5/$B5,0) -> 0 | AC5: =IFERROR(V5/$B5,0) -> 0
A6: Medical Devices | B6: =COUNTA('Medical Devices'!$A$2:$A$5000) -> 288 | C6: =COUNTIF('Medical Devices'!$P$2:$P$5000,"<>") -> 0 | D6: =COUNTIF('Medical Devices'!$Q$2:$Q$5000,"<>") -> 0 | E6: =COUNTIF('Medical Devices'!$R$2:$R$5000,"<>") -> 0 | F6: =COUNTIF('Medical Devices'!$S$2:$S$5000,"<>") -> 0 | G6: =COUNTIF('Medical Devices'!$T$2:$T$5000,"<>") -> 0 | H6: =COUNTIF('Medical Devices'!$U$2:$U$5000,"<>") -> 0 | I6: =COUNTIF('Medical Devices'!$V$2:$V$5000,"<>") -> 0 | J6: =COUNTIF('Medical Devices'!$W$2:$W$5000,"<>") -> 0 | K6: =COUNTIF('Medical Devices'!$X$2:$X$5000,"<>") -> 0 | L6: =COUNTIF('Medical Devices'!$Y$2:$Y$5000,"<>") -> 0 | M6: =COUNTIF('Medical Devices'!$Z$2:$Z$5000,"<>") -> 0 | N6: =COUNTIF('Medical Devices'!$AA$2:$AA$5000,"<>") -> 0 | O6: =COUNTIF('Medical Devices'!$AB$2:$AB$5000,"<>") -> 0 | P6: =COUNTIF('Medical Devices'!$AC$2:$AC$5000,"<>") -> 0 | Q6: =COUNTIF('Medical Devices'!$AD$2:$AD$5000,"<>") -> 0 | R6: =COUNTIF('Medical Devices'!$AE$2:$AE$5000,"<>") -> 0 | S6: =MAX(COUNTIF('Medical Devices'!$AH$2:$AH$5000,"Won"),COUNTIF('Medical Devices'!$AF$2:$AF$5000,"<>")) -> 0 | T6: =MAX(COUNTIF('Medical Devices'!$AH$2:$AH$5000,"Lost"),COUNTIF('Medical Devices'!$AG$2:$AG$5000,"<>")) -> 0 | U6: =COUNTIF('Medical Devices'!$AH$2:$AH$5000,"Blacklist") -> 0 | V6: =COUNTIF('Medical Devices'!$AH$2:$AH$5000,"Prospectar Después") -> 0 | W6: =IFERROR(MAX(C6,H6,M6)/$B6,0) -> 0 | X6: =IFERROR(P6/$B6,0) -> 0 | Y6: =IFERROR(Q6/$B6,0) -> 0 | Z6: =IFERROR(R6/$B6,0) -> 0 | AA6: =IFERROR(S6/$B6,0) -> 0 | AB6: =IFERROR(U6/$B6,0) -> 0 | AC6: =IFERROR(V6/$B6,0) -> 0
A7: Industrial Equipment | B7: =COUNTA('Industrial Equipment'!$A$2:$A$5000) -> 281 | C7: =COUNTIF('Industrial Equipment'!$P$2:$P$5000,"<>") -> 0 | D7: =COUNTIF('Industrial Equipment'!$Q$2:$Q$5000,"<>") -> 0 | E7: =COUNTIF('Industrial Equipment'!$R$2:$R$5000,"<>") -> 0 | F7: =COUNTIF('Industrial Equipment'!$S$2:$S$5000,"<>") -> 0 | G7: =COUNTIF('Industrial Equipment'!$T$2:$T$5000,"<>") -> 0 | H7: =COUNTIF('Industrial Equipment'!$U$2:$U$5000,"<>") -> 0 | I7: =COUNTIF('Industrial Equipment'!$V$2:$V$5000,"<>") -> 0 | J7: =COUNTIF('Industrial Equipment'!$W$2:$W$5000,"<>") -> 0 | K7: =COUNTIF('Industrial Equipment'!$X$2:$X$5000,"<>") -> 0 | L7: =COUNTIF('Industrial Equipment'!$Y$2:$Y$5000,"<>") -> 0 | M7: =COUNTIF('Industrial Equipment'!$Z$2:$Z$5000,"<>") -> 0 | N7: =COUNTIF('Industrial Equipment'!$AA$2:$AA$5000,"<>") -> 0 | O7: =COUNTIF('Industrial Equipment'!$AB$2:$AB$5000,"<>") -> 0 | P7: =COUNTIF('Industrial Equipment'!$AC$2:$AC$5000,"<>") -> 0 | Q7: =COUNTIF('Industrial Equipment'!$AD$2:$AD$5000,"<>") -> 0 | R7: =COUNTIF('Industrial Equipment'!$AE$2:$AE$5000,"<>") -> 0 | S7: =MAX(COUNTIF('Industrial Equipment'!$AH$2:$AH$5000,"Won"),COUNTIF('Industrial Equipment'!$AF$2:$AF$5000,"<>")) -> 0 | T7: =MAX(COUNTIF('Industrial Equipment'!$AH$2:$AH$5000,"Lost"),COUNTIF('Industrial Equipment'!$AG$2:$AG$5000,"<>")) -> 0 | U7: =COUNTIF('Industrial Equipment'!$AH$2:$AH$5000,"Blacklist") -> 0 | V7: =COUNTIF('Industrial Equipment'!$AH$2:$AH$5000,"Prospectar Después") -> 0 | W7: =IFERROR(MAX(C7,H7,M7)/$B7,0) -> 0 | X7: =IFERROR(P7/$B7,0) -> 0 | Y7: =IFERROR(Q7/$B7,0) -> 0 | Z7: =IFERROR(R7/$B7,0) -> 0 | AA7: =IFERROR(S7/$B7,0) -> 0 | AB7: =IFERROR(U7/$B7,0) -> 0 | AC7: =IFERROR(V7/$B7,0) -> 0
A8: HVAC Appliances | B8: =COUNTA('HVAC Appliances'!$A$2:$A$5000) -> 80 | C8: =COUNTIF('HVAC Appliances'!$P$2:$P$5000,"<>") -> 0 | D8: =COUNTIF('HVAC Appliances'!$Q$2:$Q$5000,"<>") -> 0 | E8: =COUNTIF('HVAC Appliances'!$R$2:$R$5000,"<>") -> 0 | F8: =COUNTIF('HVAC Appliances'!$S$2:$S$5000,"<>") -> 0 | G8: =COUNTIF('HVAC Appliances'!$T$2:$T$5000,"<>") -> 0 | H8: =COUNTIF('HVAC Appliances'!$U$2:$U$5000,"<>") -> 0 | I8: =COUNTIF('HVAC Appliances'!$V$2:$V$5000,"<>") -> 0 | J8: =COUNTIF('HVAC Appliances'!$W$2:$W$5000,"<>") -> 0 | K8: =COUNTIF('HVAC Appliances'!$X$2:$X$5000,"<>") -> 0 | L8: =COUNTIF('HVAC Appliances'!$Y$2:$Y$5000,"<>") -> 0 | M8: =COUNTIF('HVAC Appliances'!$Z$2:$Z$5000,"<>") -> 0 | N8: =COUNTIF('HVAC Appliances'!$AA$2:$AA$5000,"<>") -> 0 | O8: =COUNTIF('HVAC Appliances'!$AB$2:$AB$5000,"<>") -> 0 | P8: =COUNTIF('HVAC Appliances'!$AC$2:$AC$5000,"<>") -> 0 | Q8: =COUNTIF('HVAC Appliances'!$AD$2:$AD$5000,"<>") -> 0 | R8: =COUNTIF('HVAC Appliances'!$AE$2:$AE$5000,"<>") -> 0 | S8: =MAX(COUNTIF('HVAC Appliances'!$AH$2:$AH$5000,"Won"),COUNTIF('HVAC Appliances'!$AF$2:$AF$5000,"<>")) -> 0 | T8: =MAX(COUNTIF('HVAC Appliances'!$AH$2:$AH$5000,"Lost"),COUNTIF('HVAC Appliances'!$AG$2:$AG$5000,"<>")) -> 0 | U8: =COUNTIF('HVAC Appliances'!$AH$2:$AH$5000,"Blacklist") -> 0 | V8: =COUNTIF('HVAC Appliances'!$AH$2:$AH$5000,"Prospectar Después") -> 0 | W8: =IFERROR(MAX(C8,H8,M8)/$B8,0) -> 0 | X8: =IFERROR(P8/$B8,0) -> 0 | Y8: =IFERROR(Q8/$B8,0) -> 0 | Z8: =IFERROR(R8/$B8,0) -> 0 | AA8: =IFERROR(S8/$B8,0) -> 0 | AB8: =IFERROR(U8/$B8,0) -> 0 | AC8: =IFERROR(V8/$B8,0) -> 0
A9: Packaging | B9: =COUNTA(Packaging!$A$2:$A$5000) -> 250 | C9: =COUNTIF(Packaging!$P$2:$P$5000,"<>") -> 0 | D9: =COUNTIF(Packaging!$Q$2:$Q$5000,"<>") -> 0 | E9: =COUNTIF(Packaging!$R$2:$R$5000,"<>") -> 0 | F9: =COUNTIF(Packaging!$S$2:$S$5000,"<>") -> 0 | G9: =COUNTIF(Packaging!$T$2:$T$5000,"<>") -> 0 | H9: =COUNTIF(Packaging!$U$2:$U$5000,"<>") -> 0 | I9: =COUNTIF(Packaging!$V$2:$V$5000,"<>") -> 0 | J9: =COUNTIF(Packaging!$W$2:$W$5000,"<>") -> 0 | K9: =COUNTIF(Packaging!$X$2:$X$5000,"<>") -> 0 | L9: =COUNTIF(Packaging!$Y$2:$Y$5000,"<>") -> 0 | M9: =COUNTIF(Packaging!$Z$2:$Z$5000,"<>") -> 0 | N9: =COUNTIF(Packaging!$AA$2:$AA$5000,"<>") -> 0 | O9: =COUNTIF(Packaging!$AB$2:$AB$5000,"<>") -> 0 | P9: =COUNTIF(Packaging!$AC$2:$AC$5000,"<>") -> 0 | Q9: =COUNTIF(Packaging!$AD$2:$AD$5000,"<>") -> 0 | R9: =COUNTIF(Packaging!$AE$2:$AE$5000,"<>") -> 0 | S9: =MAX(COUNTIF(Packaging!$AH$2:$AH$5000,"Won"),COUNTIF(Packaging!$AF$2:$AF$5000,"<>")) -> 0 | T9: =MAX(COUNTIF(Packaging!$AH$2:$AH$5000,"Lost"),COUNTIF(Packaging!$AG$2:$AG$5000,"<>")) -> 0 | U9: =COUNTIF(Packaging!$AH$2:$AH$5000,"Blacklist") -> 0 | V9: =COUNTIF(Packaging!$AH$2:$AH$5000,"Prospectar Después") -> 0 | W9: =IFERROR(MAX(C9,H9,M9)/$B9,0) -> 0 | X9: =IFERROR(P9/$B9,0) -> 0 | Y9: =IFERROR(Q9/$B9,0) -> 0 | Z9: =IFERROR(R9/$B9,0) -> 0 | AA9: =IFERROR(S9/$B9,0) -> 0 | AB9: =IFERROR(U9/$B9,0) -> 0 | AC9: =IFERROR(V9/$B9,0) -> 0
A10: Consumer Goods | B10: =COUNTA('Consumer Goods'!$A$2:$A$5000) -> 130 | C10: =COUNTIF('Consumer Goods'!$P$2:$P$5000,"<>") -> 0 | D10: =COUNTIF('Consumer Goods'!$Q$2:$Q$5000,"<>") -> 0 | E10: =COUNTIF('Consumer Goods'!$R$2:$R$5000,"<>") -> 0 | F10: =COUNTIF('Consumer Goods'!$S$2:$S$5000,"<>") -> 0 | G10: =COUNTIF('Consumer Goods'!$T$2:$T$5000,"<>") -> 0 | H10: =COUNTIF('Consumer Goods'!$U$2:$U$5000,"<>") -> 0 | I10: =COUNTIF('Consumer Goods'!$V$2:$V$5000,"<>") -> 0 | J10: =COUNTIF('Consumer Goods'!$W$2:$W$5000,"<>") -> 0 | K10: =COUNTIF('Consumer Goods'!$X$2:$X$5000,"<>") -> 0 | L10: =COUNTIF('Consumer Goods'!$Y$2:$Y$5000,"<>") -> 0 | M10: =COUNTIF('Consumer Goods'!$Z$2:$Z$5000,"<>") -> 0 | N10: =COUNTIF('Consumer Goods'!$AA$2:$AA$5000,"<>") -> 0 | O10: =COUNTIF('Consumer Goods'!$AB$2:$AB$5000,"<>") -> 0 | P10: =COUNTIF('Consumer Goods'!$AC$2:$AC$5000,"<>") -> 0 | Q10: =COUNTIF('Consumer Goods'!$AD$2:$AD$5000,"<>") -> 0 | R10: =COUNTIF('Consumer Goods'!$AE$2:$AE$5000,"<>") -> 0 | S10: =MAX(COUNTIF('Consumer Goods'!$AH$2:$AH$5000,"Won"),COUNTIF('Consumer Goods'!$AF$2:$AF$5000,"<>")) -> 0 | T10: =MAX(COUNTIF('Consumer Goods'!$AH$2:$AH$5000,"Lost"),COUNTIF('Consumer Goods'!$AG$2:$AG$5000,"<>")) -> 0 | U10: =COUNTIF('Consumer Goods'!$AH$2:$AH$5000,"Blacklist") -> 0 | V10: =COUNTIF('Consumer Goods'!$AH$2:$AH$5000,"Prospectar Después") -> 0 | W10: =IFERROR(MAX(C10,H10,M10)/$B10,0) -> 0 | X10: =IFERROR(P10/$B10,0) -> 0 | Y10: =IFERROR(Q10/$B10,0) -> 0 | Z10: =IFERROR(R10/$B10,0) -> 0 | AA10: =IFERROR(S10/$B10,0) -> 0 | AB10: =IFERROR(U10/$B10,0) -> 0 | AC10: =IFERROR(V10/$B10,0) -> 0
A11: Software IT | B11: =COUNTA('Software IT'!$A$2:$A$5000) -> 2316 | C11: =COUNTIF('Software IT'!$P$2:$P$5000,"<>") -> 0 | D11: =COUNTIF('Software IT'!$Q$2:$Q$5000,"<>") -> 0 | E11: =COUNTIF('Software IT'!$R$2:$R$5000,"<>") -> 0 | F11: =COUNTIF('Software IT'!$S$2:$S$5000,"<>") -> 0 | G11: =COUNTIF('Software IT'!$T$2:$T$5000,"<>") -> 0 | H11: =COUNTIF('Software IT'!$U$2:$U$5000,"<>") -> 0 | I11: =COUNTIF('Software IT'!$V$2:$V$5000,"<>") -> 0 | J11: =COUNTIF('Software IT'!$W$2:$W$5000,"<>") -> 0 | K11: =COUNTIF('Software IT'!$X$2:$X$5000,"<>") -> 0 | L11: =COUNTIF('Software IT'!$Y$2:$Y$5000,"<>") -> 0 | M11: =COUNTIF('Software IT'!$Z$2:$Z$5000,"<>") -> 0 | N11: =COUNTIF('Software IT'!$AA$2:$AA$5000,"<>") -> 0 | O11: =COUNTIF('Software IT'!$AB$2:$AB$5000,"<>") -> 0 | P11: =COUNTIF('Software IT'!$AC$2:$AC$5000,"<>") -> 0 | Q11: =COUNTIF('Software IT'!$AD$2:$AD$5000,"<>") -> 0 | R11: =COUNTIF('Software IT'!$AE$2:$AE$5000,"<>") -> 0 | S11: =MAX(COUNTIF('Software IT'!$AH$2:$AH$5000,"Won"),COUNTIF('Software IT'!$AF$2:$AF$5000,"<>")) -> 0 | T11: =MAX(COUNTIF('Software IT'!$AH$2:$AH$5000,"Lost"),COUNTIF('Software IT'!$AG$2:$AG$5000,"<>")) -> 0 | U11: =COUNTIF('Software IT'!$AH$2:$AH$5000,"Blacklist") -> 0 | V11: =COUNTIF('Software IT'!$AH$2:$AH$5000,"Prospectar Después") -> 0 | W11: =IFERROR(MAX(C11,H11,M11)/$B11,0) -> 0 | X11: =IFERROR(P11/$B11,0) -> 0 | Y11: =IFERROR(Q11/$B11,0) -> 0 | Z11: =IFERROR(R11/$B11,0) -> 0 | AA11: =IFERROR(S11/$B11,0) -> 0 | AB11: =IFERROR(U11/$B11,0) -> 0 | AC11: =IFERROR(V11/$B11,0) -> 0
A12: Other | B12: =COUNTA(Other!$A$2:$A$5000) -> 616 | C12: =COUNTIF(Other!$P$2:$P$5000,"<>") -> 0 | D12: =COUNTIF(Other!$Q$2:$Q$5000,"<>") -> 0 | E12: =COUNTIF(Other!$R$2:$R$5000,"<>") -> 0 | F12: =COUNTIF(Other!$S$2:$S$5000,"<>") -> 0 | G12: =COUNTIF(Other!$T$2:$T$5000,"<>") -> 0 | H12: =COUNTIF(Other!$U$2:$U$5000,"<>") -> 0 | I12: =COUNTIF(Other!$V$2:$V$5000,"<>") -> 0 | J12: =COUNTIF(Other!$W$2:$W$5000,"<>") -> 0 | K12: =COUNTIF(Other!$X$2:$X$5000,"<>") -> 0 | L12: =COUNTIF(Other!$Y$2:$Y$5000,"<>") -> 0 | M12: =COUNTIF(Other!$Z$2:$Z$5000,"<>") -> 0 | N12: =COUNTIF(Other!$AA$2:$AA$5000,"<>") -> 0 | O12: =COUNTIF(Other!$AB$2:$AB$5000,"<>") -> 0 | P12: =COUNTIF(Other!$AC$2:$AC$5000,"<>") -> 0 | Q12: =COUNTIF(Other!$AD$2:$AD$5000,"<>") -> 0 | R12: =COUNTIF(Other!$AE$2:$AE$5000,"<>") -> 0 | S12: =MAX(COUNTIF(Other!$AH$2:$AH$5000,"Won"),COUNTIF(Other!$AF$2:$AF$5000,"<>")) -> 0 | T12: =MAX(COUNTIF(Other!$AH$2:$AH$5000,"Lost"),COUNTIF(Other!$AG$2:$AG$5000,"<>")) -> 0 | U12: =COUNTIF(Other!$AH$2:$AH$5000,"Blacklist") -> 0 | V12: =COUNTIF(Other!$AH$2:$AH$5000,"Prospectar Después") -> 0 | W12: =IFERROR(MAX(C12,H12,M12)/$B12,0) -> 0 | X12: =IFERROR(P12/$B12,0) -> 0 | Y12: =IFERROR(Q12/$B12,0) -> 0 | Z12: =IFERROR(R12/$B12,0) -> 0 | AA12: =IFERROR(S12/$B12,0) -> 0 | AB12: =IFERROR(U12/$B12,0) -> 0 | AC12: =IFERROR(V12/$B12,0) -> 0
A15: KPI | B15: Value
A16: Total Leads | B16: =SUM(B4:B12) -> 5032
A17: Won | B17: =SUM(S4:S12) -> 1
A18: Lost | B18: =SUM(T4:T12) -> 0
A19: Blacklist | B19: =SUM(U4:U12) -> 0
A20: Prospectar Después | B20: =SUM(V4:V12) -> 0
A21: Win Rate | B21: =IFERROR(B16/B15,0) -> 0
A22: Blacklist Rate | B22: =IFERROR(B18/B15,0) -> 0
A23: Future Rate | B23: =IFERROR(B19/B15,0) -> 0
A26: Outcome Breakdown por Industria
A27: Industry | B27: Won | C27: Lost | D27: Blacklist | E27: Prospectar Después | F27: Total Leads
A28: Automotive | B28: =S4 -> 1 | C28: =T4 -> 0 | D28: =U4 -> 0 | E28: =V4 -> 0 | F28: =B4 -> 922
A29: Pharmaceutical | B29: =S5 -> 0 | C29: =T5 -> 0 | D29: =U5 -> 0 | E29: =V5 -> 0 | F29: =B5 -> 149
A30: Medical Devices | B30: =S6 -> 0 | C30: =T6 -> 0 | D30: =U6 -> 0 | E30: =V6 -> 0 | F30: =B6 -> 288
A31: Industrial Equipment | B31: =S7 -> 0 | C31: =T7 -> 0 | D31: =U7 -> 0 | E31: =V7 -> 0 | F31: =B7 -> 281
A32: HVAC Appliances | B32: =S8 -> 0 | C32: =T8 -> 0 | D32: =U8 -> 0 | E32: =V8 -> 0 | F32: =B8 -> 80
A33: Packaging | B33: =S9 -> 0 | C33: =T9 -> 0 | D33: =U9 -> 0 | E33: =V9 -> 0 | F33: =B9 -> 250
A34: Consumer Goods | B34: =S10 -> 0 | C34: =T10 -> 0 | D34: =U10 -> 0 | E34: =V10 -> 0 | F34: =B10 -> 130
A35: Software IT | B35: =S11 -> 0 | C35: =T11 -> 0 | D35: =U11 -> 0 | E35: =V11 -> 0 | F35: =B11 -> 2316
A36: Other | B36: =S12 -> 0 | C36: =T12 -> 0 | D36: =U12 -> 0 | E36: =V12 -> 0 | F36: =B12 -> 616
A41: Stage | B41: Count
A42: Follow Up 1 | B42: =SUM(C4:C12) -> 1
A43: Follow Up 2 | B43: =SUM(D4:D12) -> 0
A44: Follow Up 3 | B44: =SUM(E4:E12) -> 0
A45: Follow Up 4 | B45: =SUM(F4:F12) -> 0
A46: Follow Up 5 | B46: =SUM(G4:G12) -> 0
A47: Email 1 | B47: =SUM(H4:H12) -> 0
A48: Email 2 | B48: =SUM(I4:I12) -> 0
A49: Email 3 | B49: =SUM(J4:J12) -> 0
A50: Email 4 | B50: =SUM(K4:K12) -> 0
A51: Email 5 | B51: =SUM(L4:L12) -> 0
A52: Cold Call 1 | B52: =SUM(M4:M12) -> 0
A53: Cold Call 2 | B53: =SUM(N4:N12) -> 0
A54: Cold Call 3 | B54: =SUM(O4:O12) -> 0
A55: Meeting | B55: =SUM(P4:P12) -> 0
A56: RFQ | B56: =SUM(Q4:Q12) -> 1
A57: Quote | B57: =SUM(R4:R12) -> 0

Sheet Lead Queue
A1: Lead Queue - prioridades de trabajo diario
A3: Industry | B3: Full Name | C3: Company | D3: Job Title | E3: Lead Score | F3: Opportunity Score | G3: LinkedIn | H3: Phone | I3: Email/Gmail | J3: Next Action
A4: Packaging | B4: KC Christensen | C4: Aaron Kendell Packaging Equipment (AEK) | D4: CEO Used Equipment Buyer Packaging Specialist Investment Recovery | E4: A+ | F4: 100 | G4: https://www.linkedin.com/in/kcchristensen1/ | J4: Contactar / iniciar campaña
A5: Industrial Equipment | B5: Andrew Mendez | C5: Blackstone Machinery | D5: President | Senior Buyer | E5: A+ | F5: 100 | G5: https://www.linkedin.com/in/andrewmendez21/ | J5: Contactar / iniciar campaña
A6: Automotive | B6: Djordje Stevanovic | C6: Coesia S.p.A. | D6: Group Chief Procurement Officer | E6: A+ | F6: 100 | G6: https://www.linkedin.com/in/djordje-stevanovic-644b282/ | J6: Contactar / iniciar campaña
A7: Automotive | B7: Camillo Di Giulio | C7: Ferroli Group | D7: Chief Procurement Officer | E7: A+ | F7: 100 | G7: https://www.linkedin.com/in/camillodigiulio/ | J7: Contactar / iniciar campaña
A8: Industrial Equipment | B8: Mugo Wanjohi | C8: Machine 4 Africa LTD. | D8: Senior sales associate used machinery, Digital marketing head , chief buyer | E8: A+ | F8: 100 | G8: https://www.linkedin.com/in/mugo-wanjohi-55622b1b/ | J8: Contactar / iniciar campaña
A9: Automotive | B9: Shashi Gupta | C9: Samvardhana Motherson International Ltd. | D9: Chief Procurement Officer - Wiring Harness Division | E9: A+ | F9: 100 | G9: https://www.linkedin.com/in/shashi-gupta-b675324/ | J9: Contactar / iniciar campaña
A10: Packaging | B10: Ken Stevens | C10: ASML | D10: Sr. Director Sourcing & Procurement ; sr. Group Sourcing Manager Mech. assies, tooling & packaging | E10: A+ | F10: 100 | G10: https://www.linkedin.com/in/ken-stevens-a5386568/ | J10: Contactar / iniciar campaña
A11: Automotive | B11: Pierre Baudoin | C11: Valeo | D11: Group Purchasing Segment Director - Plastic Aspect Parts & CDA BG Plastics Commodity Manager | E11: A+ | F11: 100 | G11: https://www.linkedin.com/in/pierre-baudoin-93ba00107/ | J11: Contactar / iniciar campaña
A12: Automotive | B12: Iulian Zediu | C12: Allison Off-Highway Drive & Motion Systems | D12: Senior Supplier Development Engineer - Local Manager | E12: A+ | F12: 100 | G12: https://www.linkedin.com/in/iulian-zediu-60abb740/ | J12: Contactar / iniciar campaña
A13: Other | B13: Mounesh Allolikar | C13: Antolin | D13: Purchasing Manager (CAPEX-Tooling and Investment )Domestics and Offshoring | E13: A+ | F13: 100 | G13: https://www.linkedin.com/in/mounesh-allolikar-cipp-b50299116/ | J13: Contactar / iniciar campaña
A14: Medical Devices | B14: Luis Aguado | C14: Ascensia Diabetes Care | D14: Sr. Quality/Supplier Quality Engineer/Manager | E14: A+ | F14: 100 | G14: https://www.linkedin.com/in/luis-aguado-8a676935/ | J14: Contactar / iniciar campaña
A15: Automotive | B15: Günhan Tekin | C15: Beyçelik Gestamp | D15: Purchasing Manager | Raw Material | Tooling | Indirect Service | E15: A+ | F15: 100 | G15: https://www.linkedin.com/in/günhan-tekin-03612869/ | J15: Contactar / iniciar campaña
... A103: Automotive | B103: Viviana Linares | C103: Cummins Inc. | D103: Technical Specialist - Supplier Quality Engineer | E103: A+ | F103: 100 | G103: https://www.linkedin.com/in/vlinares03/ | J103: Contactar / iniciar campaña

Sheet Scheduled_Messages
A1: Schedule ID | B1: Lead ID | C1: Full Name | D1: Company | E1: Seniority Level | F1: Industry | G1: Channel | H1: Message | I1: Scheduled DateTime | J1: Status | K1: Sent DateTime | L1: Follow Up Step | M1: Notes
A2: SCH-00001 | B2: li:https://www.linkedin.com/in/djordje-stevanovic-644b282 | C2: Djordje Stevanovic | D2: Coesia S.p.A. | E2: C-Level | F2: Automotive | G2: LinkedIn | H2: Hola Djordje | I2: 2026-07-05T10:00 | J2: Sent | K2: 2026-07-01T19:32:57 | L2: Follow Up 1
A3: SCH-00002 | B3: li:https://www.linkedin.com/in/camillodigiulio | C3: Camillo Di Giulio | D3: Ferroli Group | E3: C-Level | F3: Automotive | G3: LinkedIn | H3: Hola Camillo | I3: 2026-07-05T10:00 | J3: Scheduled | L3: Follow Up 1
A4: SCH-00003 | B4: li:https://www.linkedin.com/in/shashi-gupta-b675324 | C4: Shashi Gupta | D4: Samvardhana Motherson International Ltd. | E4: C-Level | F4: Automotive | G4: LinkedIn | H4: Hola Shashi | I4: 2026-07-05T10:00 | J4: Scheduled | L4: Follow Up 1
A5: SCH-00004 | B5: li:https://www.linkedin.com/in/mostafa-badawy-b5034088 | C5: Mostafa Badawy | D5: Valeo | E5: C-Level | F5: Automotive | G5: LinkedIn | H5: Hola Mostafa | I5: 2026-07-05T10:00 | J5: Scheduled | L5: Follow Up 1
A6: SCH-00005 | B6: li:https://www.linkedin.com/in/pierre-baudoin-93ba00107 | C6: Pierre Baudoin | D6: Valeo | E6: Director | F6: Automotive | G6: LinkedIn | H6: Hola Pierre | I6: 2026-07-05T10:00 | J6: Scheduled | L6: Follow Up 1
A7: SCH-00006 | B7: li:https://www.linkedin.com/in/satish-tanwar-ba1533172 | C7: Satish Tanwar | D7: International tractors limited | E7: Head | F7: Automotive | G7: LinkedIn | H7: Hola Satish | I7: 2026-07-05T10:00 | J7: Scheduled | L7: Follow Up 1

Sheet Activity_Log
A1: Timestamp | B1: Persona | C1: Empresa | D1: Industria | E1: Fecha | F1: Canal | G1: Follow-up # | H1: Paso | I1: Mensaje | J1: Resultado
A2: 2026-07-01T19:32:57 | B2: Djordje Stevanovic | C2: Coesia S.p.A. | D2: Automotive | E2: 2026-07-01 | F2: LinkedIn | G2: 1 | H2: Follow Up 1 | I2: Hola Djordje | J2: Enviado

Sheet Notifications
A1: Timestamp | B1: Fecha | C1: Lead | D1: Empresa | E1: Canal | F1: Tipo de evento | G1: Mensaje/Resumen | H1: Estado actual | I1: Visto
A2: 2026-07-01T19:32:57 | B2: 2026-07-01 | C2: Camillo Di Giulio | D2: Ferroli Group | E2: LinkedIn | F2: Respuesta registrada | G2: Cotización solicitada: quote | H2: respondió | I2: Pendiente
A3: 2026-07-01T19:32:57 | B3: 2026-07-01 | C3: Shashi Gupta | D3: Samvardhana Motherson International Ltd. | E3: - | F3: Cambio de estado | G3: Estado → Won · cerrado | H3: won | I3: Pendiente
